Workbook

Sheet Tabla dinámica 1
I1: UGT | J1: Provincia | K1: Distrito | L1: Institución educativa | M1: COUNTA de Relación con estudiante
I2: VALLE FORTALEZA | J2: BOLOGNESI | K2: ANTONIO RAYMONDI | L2: 451 | M2: 18 | P2: Asistente | Q2: COUNTUNIQUE de Apellidos y nombres
K3: CAJACAY | L3: 048 ELVA BARBA TRINIDAD | M3: 12 | Q3: 0
L4: 1649 | M4: 12 | O4: Total | Q4: 0
L5: 616 | M5: 6 | O5: HUARMEY | P5: Docente | Q5: 9
K6: COLQUIOC | L6: 028 | M6: 5 | P6: Familia | Q6: 48
L7: 030 | M7: 4 | O7: Total HUARMEY | Q7: 56
L8: 1646 | M8: 7 | O8: MINA | P8: Docente | Q8: 22
L9: 357 | M9: 19 | P9: Familia | Q9: 293
J10: RECUAY | K10: PARARIN | L10: 2626 | M10: 4 | O10: Total MINA | Q10: 315
L11: 394 | M11: 3 | O11: SAN MARCOS | P11: Docente | Q11: 8
L12: 416 - Rinconada | M12: 23 | P12: Familia | Q12: 60
I13: Suma total | M13: 113 | O13: Total SAN MARCOS | Q13: 68
O14: VALLE FORTALEZA | P14: Docente | Q14: 38
P15: Familia | Q15: 153
O16: Total VALLE FORTALEZA | Q16: 189
O17: Suma total | Q17: 628
I29: UGT | J29: Provincia | K29: Distrito | L29: Institución educativa | M29: COUNTUNIQUE de Apellidos y nombres
I30: VALLE FORTALEZA | J30: BOLOGNESI | K30: ANTONIO RAYMONDI | L30: 451 | M30: 2
K31: CAJACAY | L31: 048 ELVA BARBA TRINIDAD | M31: 4
L32: 1649 | M32: 5
L33: 616 | M33: 1
K34: COLQUIOC | L34: 028 | M34: 1
L35: 030 | M35: 1
L36: 1646 | M36: 2
L37: 357 | M37: 3
L38: LOS PALILLOS | M38: 2
J39: RECUAY | K39: PARARIN | L39: 2626 | M39: 2
L40: 394 | M40: 1
L41: 416 - Rinconada | M41: 3
I42: Suma total | M42: 27

Sheet Revisión cuaderno
A1: n° | B1: UGT | C1: Provincia | D1: Distrito | E1: Centro Poblado | F1: Institución educativa | G1: Nivel modular | H1: Cod modular | I1: Cod local | J1: Fecha de revisión | K1: Apellidos y nombres | L1: DNI | M1: Apellidos y nombre del niño/a | N1: Grado | O1: Aula/Sección | P1: Núcleo familiar | Q1: % Avance | R1: Comentarios | S1: Facilitador/a
B2: SAN MARCOS | C2: HUARI | D2: SAN MARCOS | E2: OPAYACO/OPAYACU | F2: 099 | G2: Inicial - Jardín | H2: 1551738 | I2: 631640 | J2: 45903 | K2: Rocia Mosquera Vega | M2: Leyva Mosquera Naim Owen | N2: Ini-3ero | O2: 3 años | P2: Leyva Mosquera Naim Owen/Ini-3ero/3 años | S2: Stephany Decheco Vera
B3: SAN MARCOS | C3: HUARI | D3: SAN MARCOS | E3: OPAYACO/OPAYACU | F3: 099 | G3: Inicial - Jardín | H3: 1551738 | I3: 631640 | J3: 45917 | K3: Rocia Mosquera Vega | M3: Leyva Mosquera Naim Owen | N3: Ini-3ero | O3: 3 años | P3: Leyva Mosquera Naim Owen/Ini-3ero/3 años | S3: Stephany Decheco Vera
B4: SAN MARCOS | C4: HUARI | D4: SAN MARCOS | E4: OPAYACO/OPAYACU | F4: 099 | G4: Inicial - Jardín | H4: 1551738 | I4: 631640 | J4: 45932 | K4: Rocia Mosquera Vega | M4: Leyva Mosquera Naim Owen | N4: Ini-3ero | O4: 3 años | P4: Leyva Mosquera Naim Owen/Ini-3ero/3 años | S4: Stephany Decheco Vera
B5: SAN MARCOS | C5: HUARI | D5: SAN MARCOS | E5: OPAYACO/OPAYACU | F5: 099 | G5: Inicial - Jardín | H5: 1551738 | I5: 631640 | J5: 45952 | K5: Rocia Mosquera Vega | M5: Leyva Mosquera Naim Owen | N5: Ini-3ero | O5: 3 años | P5: Leyva Mosquera Naim Owen/Ini-3ero/3 años | S5: Stephany Decheco Vera
B6: SAN MARCOS | C6: HUARI | D6: SAN MARCOS | E6: OPAYACO/OPAYACU | F6: 099 | G6: Inicial - Jardín | H6: 1551738 | I6: 631640 | J6: 45917 | K6: Andria Durán Flores | M6: Garay Durán Jahir Leandro | N6: Ini-3ero | O6: 3 años | P6: Garay Durán Jahir Leandro/Ini-3ero/3 años | S6: Stephany Decheco Vera
B7: SAN MARCOS | C7: HUARI | D7: SAN MARCOS | E7: OPAYACO/OPAYACU | F7: 099 | G7: Inicial - Jardín | H7: 1551738 | I7: 631640 | J7: 45932 | K7: Andria Durán Flores | M7: Garay Durán Jahir Leandro | N7: Ini-3ero | O7: 3 años | P7: Garay Durán Jahir Leandro/Ini-3ero/3 años | S7: Stephany Decheco Vera
B8: SAN MARCOS | C8: HUARI | D8: SAN MARCOS | E8: OPAYACO/OPAYACU | F8: 099 | G8: Inicial - Jardín | H8: 1551738 | I8: 631640 | J8: 45903 | K8: Edith Castro Veramendi | M8: Ortiz Castro Evelin Victoria Valentina | N8: Ini-3ero | O8: 3 años | P8: Ortiz Castro Evelin Victoria Valentina/Ini-3ero/3 años | S8: Stephany Decheco Vera
B9: MINA | C9: HUARI | D9: HUACHIS | E9: CAMBIO 90 | F9: LAS TRUCHAS | G9: Inicial No Escolarizado | H9: 0783226 | J9: 45916 | K9: Felix León Guisella | M9: Aquino Felix Samara Damaris | O9: única | P9: Aquino Felix Samara Damaris/única | Q9: 20 | S9: Jackelyn Juro Dueñas
B10: MINA | C10: HUARI | D10: HUACHIS | E10: CAMBIO 90 | F10: LAS TRUCHAS | G10: Inicial No Escolarizado | H10: 0783226 | J10: 45916 | K10: Gomez Alvarado Emma | L10: 72109011 | M10: Aquino Gomez Zohemy Skarlet | O10: única | P10: Aquino Gomez Zohemy Skarlet/única | Q10: 20 | S10: Jackelyn Juro Dueñas
B11: MINA | C11: HUARI | D11: HUACHIS | E11: CAMBIO 90 | F11: LAS TRUCHAS | G11: Inicial No Escolarizado | H11: 0783226 | J11: 45916 | K11: Alva Prada Isabela | M11: Garay Alva Adriel Dyam | O11: única | P11: Garay Alva Adriel Dyam/única | Q11: 20 | S11: Jackelyn Juro Dueñas
B12: MINA | C12: HUARI | D12: HUACHIS | E12: CAMBIO 90 | F12: LAS TRUCHAS | G12: Inicial No Escolarizado | H12: 0783226 | J12: 45916 | K12: Fernandez Flores Janet | L12: 10138468 | M12: Castro Fernandez Ghinna Mileth | O12: única | P12: Castro Fernandez Ghinna Mileth/única | Q12: 20 | S12: Jackelyn Juro Dueñas
B13: MINA | C13: HUARI | D13: HUACHIS | E13: CAMBIO 90 | F13: LAS TRUCHAS | G13: Inicial No Escolarizado | H13: 0783226 | J13: 45938 | K13: Felix León Guisella | M13: Aquino Felix Samara Damaris | O13: única | P13: Aquino Felix Samara Damaris/única | Q13: 50 | S13: Jackelyn Juro Dueñas
B14: MINA | C14: HUARI | D14: HUACHIS | E14: CAMBIO 90 | F14: LAS TRUCHAS | G14: Inicial No Escolarizado | H14: 0783226 | J14: 45938 | K14: Gomez Alvarado Emma | L14: 72109011 | M14: Aquino Gomez Zohemy Skarlet | O14: única | P14: Aquino Gomez Zohemy Skarlet/única | Q14: 50 | S14: Jackelyn Juro Dueñas
B15: MINA | C15: HUARI | D15: HUACHIS | E15: CAMBIO 90 | F15: LAS TRUCHAS | G15: Inicial No Escolarizado | H15: 0783226 | J15: 45938 | K15: Alva Prada Isabela | M15: Garay Alva Adriel Dyam | O15: única | P15: Garay Alva Adriel Dyam/única | Q15: 50 | S15: Jackelyn Juro Dueñas
B16: MINA | C16: HUARI | D16: HUACHIS | E16: CAMBIO 90 | F16: LAS TRUCHAS | G16: Inicial No Escolarizado | H16: 0783226 | J16: 45938 | K16: Fernandez Flores Janet | L16: 10138468 | M16: Castro Fernandez Ghinna Mileth | O16: única | P16: Castro Fernandez Ghinna Mileth/única | Q16: 50 | S16: Jackelyn Juro Dueñas
B17: MINA | C17: HUARI | D17: HUACHIS | E17: CAMBIO 90 | F17: LAS TRUCHAS | G17: Inicial No Escolarizado | H17: 0783226 | J17: 45961 | K17: Felix León Guisella | M17: Aquino Felix Samara Damaris | O17: única | P17: Aquino Felix Samara Damaris/única | Q17: 80 | S17: Jackelyn Juro Dueñas
B18: MINA | C18: HUARI | D18: HUACHIS | E18: CAMBIO 90 | F18: LAS TRUCHAS | G18: Inicial No Escolarizado | H18: 0783226 | J18: 45961 | K18: Gomez Alvarado Emma | L18: 72109011 | M18: Aquino Gomez Zohemy Skarlet | O18: única | P18: Aquino Gomez Zohemy Skarlet/única | Q18: 80 | S18: Jackelyn Juro Dueñas
B19: MINA | C19: HUARI | D19: HUACHIS | E19: CAMBIO 90 | F19: LAS TRUCHAS | G19: Inicial No Escolarizado | H19: 0783226 | J19: 45961 | K19: Alva Prada Isabela | M19: Garay Alva Adriel Dyam | O19: única | P19: Garay Alva Adriel Dyam/única | Q19: 80 | S19: Jackelyn Juro Dueñas
B20: MINA | C20: HUARI | D20: HUACHIS | E20: CAMBIO 90 | F20: LAS TRUCHAS | G20: Inicial No Escolarizado | H20: 0783226 | J20: 45961 | K20: Fernandez Flores Janet | L20: 10138468 | M20: Castro Fernandez Ghinna Mileth | O20: única | P20: Castro Fernandez Ghinna Mileth/única | Q20: 80 | S20: Jackelyn Juro Dueñas
B21: MINA | C21: HUARI | D21: HUACHIS | E21: CAMBIO 90 | F21: LAS TRUCHAS | G21: Inicial No Escolarizado | H21: 0783226 | J21: 45966 | K21: Felix León Guisella | M21: Aquino Felix Samara Damaris | O21: única | P21: Aquino Felix Samara Damaris/única | Q21: 100 | S21: Jackelyn Juro Dueñas
B22: MINA | C22: HUARI | D22: HUACHIS | E22: CAMBIO 90 | F22: LAS TRUCHAS | G22: Inicial No Escolarizado | H22: 0783226 | J22: 45966 | K22: Gomez Alvarado Emma | L22: 72109011 | M22: Aquino Gomez Zohemy Skarlet | O22: única | P22: Aquino Gomez Zohemy Skarlet/única | Q22: 100 | S22: Jackelyn Juro Dueñas
B23: MINA | C23: HUARI | D23: HUACHIS | E23: CAMBIO 90 | F23: LAS TRUCHAS | G23: Inicial No Escolarizado | H23: 0783226 | J23: 45966 | K23: Alva Prada Isabela | M23: Garay Alva Adriel Dyam | O23: única | P23: Garay Alva Adriel Dyam/única | Q23: 100 | S23: Jackelyn Juro Dueñas
B24: MINA | C24: HUARI | D24: HUACHIS | E24: CAMBIO 90 | F24: LAS TRUCHAS | G24: Inicial No Escolarizado | H24: 0783226 | J24: 45966 | K24: Fernandez Flores Janet | L24: 10138468 | M24: Castro Fernandez Ghinna Mileth | O24: única | P24: Castro Fernandez Ghinna Mileth/única | Q24: 100 | S24: Jackelyn Juro Dueñas
B25: MINA | C25: HUARI | D25: SAN PEDRO DE CHANA | E25: WISHLLAC | F25: 690 | G25: Inicial - Jardín | H25: 1675040 | I25: 759493 | J25: 45895 | K25: Evangelista Caqui Clerinda | L25: 71935349 | M25: Evangelista Caqui Clerinda | N25: Ini-5nto | O25: 5 años | P25: Castro Evangelista, Jafed | Q25: 20 | S25: Jackelyn Juro Dueñas
B26: MINA | C26: HUARI | D26: SAN PEDRO DE CHANA | E26: WISHLLAC | F26: 690 | G26: Inicial - Jardín | H26: 1675040 | I26: 759493 | J26: 45895 | K26: Evangelista Caqui Clerinda | L26: 71935349 | M26: Trujillo Guerra Marlene | N26: Ini-4rto | O26: 4 años | P26: Obregón Trujillo, Afret | Q26: 20 | S26: Jackelyn Juro Dueñas
B27: MINA | C27: HUARI | D27: SAN PEDRO DE CHANA | E27: WISHLLAC | F27: 690 | G27: Inicial - Jardín | H27: 1675040 | I27: 759493 | J27: 45895 | K27: Nuñez Silva Antonia | M27: Aquino Ramirez, Viviana | N27: Ini-4rto | O27: 4 años | P27: Aquino Ramirez, Viviana/Ini-4rto/4 años | Q27: 20 | S27: Jackelyn Juro Dueñas
B28: MINA | C28: HUARI | D28: SAN PEDRO DE CHANA | E28: WISHLLAC | F28: 690 | G28: Inicial - Jardín | H28: 1675040 | I28: 759493 | J28: 45910 | K28: Evangelista Caqui Clerinda | L28: 71935349 | M28: Evangelista Caqui Clerinda | N28: Ini-5nto | O28: 5 años | P28: Evangelista Caqui Clerinda/Ini-5nto/5 años | Q28: 50 | S28: Jackelyn Juro Dueñas
B29: MINA | C29: HUARI | D29: SAN PEDRO DE CHANA | E29: WISHLLAC | F29: 690 | G29: Inicial - Jardín | H29: 1675040 | I29: 759493 | J29: 45910 | K29: Evangelista Caqui Clerinda | L29: 71935349 | M29: Trujillo Guerra Marlene | N29: Ini-4rto | O29: 4 años | P29: Trujillo Guerra Marlene/Ini-4rto/4 años | Q29: 50 | S29: Jackelyn Juro Dueñas
B30: MINA | C30: HUARI | D30: SAN PEDRO DE CHANA | E30: WISHLLAC | F30: 690 | G30: Inicial - Jardín | H30: 1675040 | I30: 759493 | J30: 45938 | K30: Evangelista Caqui Clerinda | L30: 71935349 | M30: Evangelista Caqui Clerinda | N30: Ini-5nto | O30: 5 años | P30: Evangelista Caqui Clerinda/Ini-5nto/5 años | Q30: 80 | S30: Jackelyn Juro Dueñas
B31: MINA | C31: HUARI | D31: SAN PEDRO DE CHANA | E31: WISHLLAC | F31: 690 | G31: Inicial - Jardín | H31: 1675040 | I31: 759493 | J31: 45938 | K31: Evangelista Caqui Clerinda | L31: 71935349 | M31: Trujillo Guerra Marlene | N31: Ini-4rto | O31: 4 años | P31: Trujillo Guerra Marlene/Ini-4rto/4 años | Q31: 80 | S31: Jackelyn Juro Dueñas
B32: MINA | C32: HUARI | D32: SAN PEDRO DE CHANA | E32: WISHLLAC | F32: 690 | G32: Inicial - Jardín | H32: 1675040 | I32: 759493 | J32: 45959 | K32: Evangelista Caqui Clerinda | L32: 71935349 | M32: Evangelista Caqui Clerinda | N32: Ini-5nto | O32: 5 años | P32: Evangelista Caqui Clerinda/Ini-5nto/5 años | Q32: 100 | S32: Jackelyn Juro Dueñas
B33: MINA | C33: HUARI | D33: HUACHIS | E33: SAN CRISTOBAL DE TAMBO | F33: 688 | G33: Inicial - Jardín | H33: 1675024 | I33: 759474 | J33: 45937 | K33: Jemina Gadea Principe | L33: 76366959 | M33: Obregon Gadea Mia Isabella | O33: única | P33: Obregon Gadea Mia Isabella/única | Q33: 20 | S33: Jackelyn Juro Dueñas
B34: MINA | C34: HUARI | D34: HUACHIS | E34: SAN CRISTOBAL DE TAMBO | F34: 688 | G34: Inicial - Jardín | H34: 1675024 | I34: 759474 | J34: 45937 | K34: Ebilia Aquino Loarte | L34: 72118797 | M34: Melgarejo Aquino Liam Jayden | O34: única | P34: Melgarejo Aquino Liam Jayden/única | Q34: 20 | S34: Jackelyn Juro Dueñas
B35: MINA | C35: HUARI | D35: HUACHIS | E35: SAN CRISTOBAL DE TAMBO | F35: 688 | G35: Inicial - Jardín | H35: 1675024 | I35: 759474 | J35: 45937 | K35: Flor Rosales Carhuapoma | L35: 46514681 | M35: Aquino Rosales Danna Alisson | O35: única | P35: Aquino Rosales Danna Alisson/única | Q35: 20 | S35: Jackelyn Juro Dueñas
B36: MINA | C36: HUARI | D36: HUACHIS | E36: SAN CRISTOBAL DE TAMBO | F36: 688 | G36: Inicial - Jardín | H36: 1675024 | I36: 759474 | J36: 45937 | K36: Yolanda Suarez Huerta | L36: 47151224 | M36: Aquino Suarez Gael Loan | O36: única | P36: Aquino Suarez Gael Loan/única | Q36: 20 | S36: Jackelyn Juro Dueñas
B37: MINA | C37: HUARI | D37: HUACHIS | E37: SAN CRISTOBAL DE TAMBO | F37: 688 | G37: Inicial - Jardín | H37: 1675024 | I37: 759474 | J37: 45937 | K37: Rosaida Francisco Arquiñigo | L37: 71944773 | M37: Melgarejo Francisco Yamilet Kaida | O37: única | P37: Melgarejo Francisco Yamilet Kaida/única | Q37: 20 | S37: Jackelyn Juro Dueñas
B38: MINA | C38: HUARI | D38: HUACHIS | E38: SAN CRISTOBAL DE TAMBO | F38: 688 | G38: Inicial - Jardín | H38: 1675024 | I38: 759474 | J38: 45937 | K38: Ayde Aquino Loarte | L38: 73468926 | M38: Garay Aquino Eriksen Oliver | O38: única | P38: Garay Aquino Eriksen Oliver/única | Q38: 20 | S38: Jackelyn Juro Dueñas
B39: MINA | C39: HUARI | D39: HUACHIS | E39: SAN CRISTOBAL DE TAMBO | F39: 688 | G39: Inicial - Jardín | H39: 1675024 | I39: 759474 | J39: 45954 | K39: Jemina Gadea Principe | L39: 76366959 | M39: Obregon Gadea Mia Isabella | O39: única | P39: Obregon Gadea Mia Isabella/única | Q39: 50 | S39: Jackelyn Juro Dueñas
B40: MINA | C40: HUARI | D40: HUACHIS | E40: SAN CRISTOBAL DE TAMBO | F40: 688 | G40: Inicial - Jardín | H40: 1675024 | I40: 759474 | J40: 45954 | K40: Ebilia Aquino Loarte | L40: 72118797 | M40: Melgarejo Aquino Liam Jayden | O40: única | P40: Melgarejo Aquino Liam Jayden/única | Q40: 50 | S40: Jackelyn Juro Dueñas
B41: MINA | C41: HUARI | D41: HUACHIS | E41: SAN CRISTOBAL DE TAMBO | F41: 688 | G41: Inicial - Jardín | H41: 1675024 | I41: 759474 | J41: 45954 | K41: Flor Rosales Carhuapoma | L41: 46514681 | M41: Aquino Rosales Danna Alisson | O41: única | P41: Aquino Rosales Danna Alisson/única | Q41: 50 | S41: Jackelyn Juro Dueñas
B42: MINA | C42: HUARI | D42: HUACHIS | E42: SAN CRISTOBAL DE TAMBO | F42: 688 | G42: Inicial - Jardín | H42: 1675024 | I42: 759474 | J42: 45954 | K42: Yolanda Suarez Huerta | L42: 47151224 | M42: Aquino Suarez Gael Loan | O42: única | P42: Aquino Suarez Gael Loan/única | Q42: 50 | S42: Jackelyn Juro Dueñas
B43: MINA | C43: HUARI | D43: HUACHIS | E43: SAN CRISTOBAL DE TAMBO | F43: 688 | G43: Inicial - Jardín | H43: 1675024 | I43: 759474 | J43: 45954 | K43: Rosaida Francisco Arquiñigo | L43: 71944773 | M43: Melgarejo Francisco Yamilet Kaida | O43: única | P43: Melgarejo Francisco Yamilet Kaida/única | Q43: 50 | S43: Jackelyn Juro Dueñas
B44: MINA | C44: HUARI | D44: HUACHIS | E44: SAN CRISTOBAL DE TAMBO | F44: 688 | G44: Inicial - Jardín | H44: 1675024 | I44: 759474 | J44: 45960 | K44: Jemina Gadea Principe | L44: 76366959 | M44: Obregon Gadea Mia Isabella | O44: única | P44: Obregon Gadea Mia Isabella/única | Q44: 80 | S44: Jackelyn Juro Dueñas
... B53: MINA | C53: HUARI | D53: HUACHIS | E53: SAN CRISTOBAL DE TAMBO | F53: 688 | G53: Inicial - Jardín | H53: 1675024 | I53: 759474 | J53: 45968 | K53: Rosaida Francisco Arquiñigo | L53: 71944773 | M53: Melgarejo Francisco Yamilet Kaida | O53: única | P53: Melgarejo Francisco Yamilet Kaida/única | Q53: 100 | S53: Jackelyn Juro Dueñas
B54: MINA | C54: HUARI | D54: SAN PEDRO DE CHANA | E54: VISTOSO | F54: 112 | G54: Inicial - Jardín | H54: 1558782 | I54: 536228 | J54: 45932 | K54: Castro Diaz Ines | L54: 9656050 | M54: Aquino Castro Samara | N54: Ini-5nto | O54: 5 años | P54: Aquino Castro Samara/Ini-5nto/5 años | Q54: 40 | S54: Jackelyn Juro Dueñas
B55: MINA | C55: HUARI | D55: SAN PEDRO DE CHANA | E55: VISTOSO | F55: 112 | G55: Inicial - Jardín | H55: 1558782 | I55: 536228 | J55: 45932 | K55: Aquino Castro Zarela | L55: 73413898 | M55: Aquino Chavez Emely | N55: Ini-3ero | O55: 3 años | P55: Aquino Chavez Emely/Ini-3ero/3 años | Q55: 40 | S55: Jackelyn Juro Dueñas
B56: MINA | C56: HUARI | D56: SAN PEDRO DE CHANA | E56: VISTOSO | F56: 112 | G56: Inicial - Jardín | H56: 1558782 | I56: 536228 | J56: 45958 | K56: Castro Diaz Ines | L56: 9656050 | M56: Aquino Castro Samara | N56: Ini-5nto | O56: 5 años | P56: Aquino Castro Samara/Ini-5nto/5 años | Q56: 80 | S56: Jackelyn Juro Dueñas
B57: MINA | C57: HUARI | D57: SAN PEDRO DE CHANA | E57: VISTOSO | F57: 112 | G57: Inicial - Jardín | H57: 1558782 | I57: 536228 | J57: 45958 | K57: Aquino Castro Zarela | L57: 73413898 | M57: Aquino Chavez Emely | N57: Ini-3ero | O57: 3 años | P57: Aquino Chavez Emely/Ini-3ero/3 años | Q57: 80 | S57: Jackelyn Juro Dueñas
B58: MINA | C58: HUARI | D58: SAN PEDRO DE CHANA | E58: VISTOSO | F58: 112 | G58: Inicial - Jardín | H58: 1558782 | I58: 536228 | J58: 45973 | K58: Castro Diaz Ines | L58: 9656050 | M58: Aquino Castro Samara | N58: Ini-5nto | O58: 5 años | P58: Aquino Castro Samara/Ini-5nto/5 años | Q58: 100 | S58: Jackelyn Juro Dueñas
B59: MINA | C59: HUARI | D59: SAN PEDRO DE CHANA | E59: VISTOSO | F59: 112 | G59: Inicial - Jardín | H59: 1558782 | I59: 536228 | J59: 45973 | K59: Aquino Castro Zarela | L59: 73413898 | M59: Aquino Chavez Emely | N59: Ini-3ero | O59: 3 años | P59: Aquino Chavez Emely/Ini-3ero/3 años | Q59: 100 | S59: Jackelyn Juro Dueñas
B60: MINA | C60: HUARI | D60: SAN PEDRO DE CHANA | E60: HUANCAYOC | F60: 470 | G60: Inicial - Jardín | H60: 1607118 | I60: 671730 | J60: 45960 | K60: Ramirez Rivera Diana | L60: 72125097 | M60: Espinoza Ramirez Khaleesi | N60: Ini-4rto | O60: 4 años | P60: Espinoza Ramirez Khaleesi/Ini-4rto/4 años | Q60: 50 | S60: Jackelyn Juro Dueñas
B61: MINA | C61: HUARI | D61: SAN PEDRO DE CHANA | E61: HUANCAYOC | F61: 470 | G61: Inicial - Jardín | H61: 1607118 | I61: 671730 | J61: 45980 | K61: Ramirez Rivera Diana | L61: 72125097 | M61: Espinoza Ramirez Khaleesi | N61: Ini-4rto | O61: 4 años | P61: Espinoza Ramirez Khaleesi/Ini-4rto/4 años | Q61: 100 | S61: Jackelyn Juro Dueñas
B62: MINA | C62: HUARI | D62: SAN PEDRO DE CHANA | E62: HUANCAYOC | F62: 470 | G62: Inicial - Jardín | H62: 1607118 | I62: 671730 | J62: 45960 | K62: Castro Obregón Noemi | L62: 44300320 | M62: Cindi | N62: Ini-5nto | O62: 5 años | P62: Cindi/Ini-5nto/5 años | Q62: 50 | S62: Jackelyn Juro Dueñas
B63: MINA | C63: HUARI | D63: SAN PEDRO DE CHANA | E63: HUANCAYOC | F63: 470 | G63: Inicial - Jardín | H63: 1607118 | I63: 671730 | J63: 45960 | K63: Trujillo Guerra Elena | L63: 73863257 | M63: Brisaida Aguirre Trujillo | N63: Ini-5nto | O63: 5 años | P63: Brisaida Aguirre Trujillo/Ini-5nto/5 años | Q63: 50 | S63: Jackelyn Juro Dueñas

Sheet Enc. Familias
B1: UGT | C1: Provincia | D1: Distrito | E1: Centro Poblado | F1: Institución educativa | G1: Nivel modular | H1: Cod modular | I1: Cod local | J1: Apellidos y nombres | K1: 🅱️ Normaliza nombres | L1: Relación con estudiante | M1: Edad | N1: Fecha de aplicación | O1: Corte de evaluación | P1: TRUE - Cuando me enojo con mis hijos/as, me doy cuenta de cómo me siento. | Q1: FALSE - A veces me pregunto si lo que hago como mamá o papá está bien para mis hijos/as. | R1: FALSE - Cuando estoy cansado/a o de mal humor, me cuesta tener paciencia con mis hijos/as.Cuando estoy cansado/a o de mal humor, me cuesta tener paciencia con mis hijos/as. | S1: TRUE - Cuando algo está difícil, trato de estar tranquilo/a antes de corregir a mis hijos/as. | T1: TRUE - Me doy cuenta cuando mi hijo/a está triste, aunque no lo diga. | U1: TRUE - En casa hablamos sobre cómo se siente cada uno. | V1: TRUE - En casa decimos lo que hacemos bien y también lo que podemos mejorar. | W1: TRUE - Cuando mi hijo/a se equivoca, le explico qué pasó y cómo puede hacerlo mejor. | X1: TRUE - Cuando hay decisiones importantes, las conversamos entre adultos en la casa. | Y1: TRUE - En mi casa, hombres y mujeres compartimos tareas como limpiar o cuidar a los niños/as. | Z1: FALSE - En mi comunidad, se espera que las niñas ayuden más en la casa que los niños. | AA1: FALSE - A veces pienso que los hombres no deben llorar ni mostrar tristeza. | AB1: TRUE - En mi familia, no siempre hablamos sobre cómo nos sentimos, pero lo estamos intentando. | AC1: FALSE - Cuando hay reunión en la escuela, casi siempre va la mamá, aunque también hay papás interesados. | AD1: 🅱️ Autoconciencia y Autorregulación Emocional | AE1: 🅱️ Toma de Decisiones Responsables | AF1: 🅱️ Habilidades Relacionales | AG1: ¿Qué te ayuda a ti, como mamá/papá, a estar bien? | AH1: Comentarios | AI1: Facilitador/a
B2: SAN MARCOS | C2: HUARI | D2: SAN MARCOS | E2: SANTA CRUZ DE MOSNA | F2: 435 | G2: Inicial - Jardín | H2: 1515246 | I2: 608381 | J2: PAOLA VICTORIA TOLENTITNO | K2: {=TRIM(UPPER(J2:J1076))} -> PAOLA VICTORIA TOLENTITNO | L2: Madre | M2: 36 | N2: 45834 | O2: Pre test (diagnóstico) | P2: 5 | Q2: 5 | R2: 5 | S2: 5 | T2: 3 | U2: 3 | V2: 3 | W2: 5 | X2: 3 | Y2: 3 | Z2: 3 | AA2: 5 | AB2: 3 | AC2: 3 | AD2: {=IF(J2:J1076="","", P2:P1076+(6-Q2:Q1076)+(6-R2:R1076)+S2:S1076+(6- AA2:AA1076))} -> 13 | AE2: {=IF(J2:J1076="","",W2:W1076+X2:X1076+Y2:Y1076+(5-Z2:Z1076)+(6-AC2:AC1076))} -> 16 | AF2: {=IF(J2:J1076="","",T2:T1076+U2:U1076+V2:V1076+AB2:AB1076)} -> 12 | AI2: Stephany Decheco Vera
B3: SAN MARCOS | C3: HUARI | D3: SAN MARCOS | E3: SANTA CRUZ DE MOSNA | F3: 435 | G3: Inicial - Jardín | H3: 1515246 | I3: 608381 | J3: SONIA RIMAC BALABARCA | K3: SONIA RIMAC BALABARCA | L3: Madre | M3: 26 | N3: 45834 | O3: Pre test (diagnóstico) | P3: 3 | Q3: 3 | R3: 4 | S3: 4 | T3: 3 | U3: 3 | V3: 3 | W3: 4 | X3: 5 | Y3: 5 | Z3: 3 | AA3: 3 | AB3: 3 | AC3: 5 | AD3: 15 | AE3: 17 | AF3: 12 | AG3: Tener tiempo de descanso y de juego con mis hijos | AI3: Stephany Decheco Vera
B4: SAN MARCOS | C4: HUARI | D4: SAN MARCOS | E4: SANTA CRUZ DE MOSNA | F4: 435 | G4: Inicial - Jardín | H4: 1515246 | I4: 608381 | J4: GLORIA CERPA POMA | K4: GLORIA CERPA POMA | L4: Madre | M4: 40 | N4: 45834 | O4: Pre test (diagnóstico) | P4: 2 | Q4: 2 | R4: 4 | S4: 4 | T4: 4 | U4: 4 | V4: 4 | W4: 4 | X4: 3 | Y4: 3 | Z4: 4 | AA4: 2 | AB4: 4 | AC4: 3 | AD4: 16 | AE4: 14 | AF4: 16 | AI4: Stephany Decheco Vera
B5: SAN MARCOS | C5: HUARI | D5: SAN MARCOS | E5: SANTA CRUZ DE MOSNA | F5: 435 | G5: Inicial - Jardín | H5: 1515246 | I5: 608381 | J5: YENI MINAYA MIRANDA | K5: YENI MINAYA MIRANDA | L5: Madre | M5: 34 | N5: 45834 | O5: Pre test (diagnóstico) | P5: 4 | Q5: 4 | R5: 4 | S5: 4 | T5: 4 | U5: 4 | V5: 4 | W5: 4 | X5: 4 | Y5: 4 | Z5: 4 | AA5: 4 | AB5: 4 | AC5: 4 | AD5: 14 | AE5: 15 | AF5: 16 | AG5: Tomar decisiones con mi familia e hijos | AI5: Stephany Decheco Vera
B6: SAN MARCOS | C6: HUARI | D6: SAN MARCOS | E6: SANTA CRUZ DE MOSNA | F6: 435 | G6: Inicial - Jardín | H6: 1515246 | I6: 608381 | L6: Madre | N6: 45834 | O6: Pre test (diagnóstico) | P6: 4 | Q6: 4 | R6: 4 | S6: 4 | T6: 4 | U6: 4 | V6: 4 | W6: 4 | X6: 3 | Y6: 3 | Z6: 4 | AA6: 4 | AB6: 4 | AC6: 3 | AG6: Estar atento de mis hijos | AI6: Stephany Decheco Vera
B7: SAN MARCOS | C7: HUARI | D7: SAN MARCOS | E7: SANTA CRUZ DE MOSNA | F7: 435 | G7: Inicial - Jardín | H7: 1515246 | I7: 608381 | J7: NARCIZA CUEVA TREJO | K7: NARCIZA CUEVA TREJO | L7: Madre | M7: 30 | N7: 45834 | O7: Pre test (diagnóstico) | P7: 3 | Q7: 3 | R7: 3 | S7: 3 | T7: 2 | U7: 4 | V7: 4 | W7: 3 | X7: 3 | Y7: 3 | Z7: 2 | AA7: 3 | AB7: 2 | AC7: 3 | AD7: 15 | AE7: 15 | AF7: 12 | AI7: Stephany Decheco Vera
B8: SAN MARCOS | C8: HUARI | D8: SAN MARCOS | E8: PUJUN | F8: 109 | G8: Inicial - Jardín | H8: 1551753 | I8: 631664 | J8: HILARIA ESPINOZA SALVADOR | K8: HILARIA ESPINOZA SALVADOR | L8: Madre | M8: 48 | N8: 45834 | O8: Pre test (diagnóstico) | P8: 2 | Q8: 2 | R8: 5 | S8: 5 | T8: 2 | U8: 1 | V8: 1 | W8: 5 | X8: 5 | Y8: 5 | Z8: 2 | AA8: 2 | AB8: 2 | AC8: 5 | AD8: 16 | AE8: 19 | AF8: 6 | AG8: Explicar a mi hijo sobre las normas | AI8: Stephany Decheco Vera
B9: SAN MARCOS | C9: HUARI | D9: SAN MARCOS | E9: SANTA CRUZ DE MOSNA | F9: 435 | G9: Inicial - Jardín | H9: 1515246 | I9: 608381 | J9: PAOLA GARCIA VERGARA | K9: PAOLA GARCIA VERGARA | L9: Madre | M9: 24 | N9: 45834 | O9: Pre test (diagnóstico) | P9: 4 | Q9: 4 | R9: 4 | S9: 4 | T9: 4 | U9: 4 | V9: 4 | W9: 4 | X9: 4 | Y9: 4 | Z9: 4 | AA9: 4 | AB9: 4 | AC9: 4 | AD9: 14 | AE9: 15 | AF9: 16 | AG9: Ver crecer feliz a mi hijo | AI9: Stephany Decheco Vera
B10: SAN MARCOS | C10: HUARI | D10: SAN MARCOS | E10: SANTA CRUZ DE MOSNA | F10: 435 | G10: Inicial - Jardín | H10: 1515246 | I10: 608381 | J10: KELY MERCEDES VARGAS SOLIS | K10: KELY MERCEDES VARGAS SOLIS | L10: Madre | M10: 26 | N10: 45834 | O10: Pre test (diagnóstico) | P10: 4 | Q10: 4 | R10: 4 | S10: 4 | T10: 4 | U10: 4 | V10: 4 | W10: 4 | X10: 4 | Y10: 4 | Z10: 4 | AA10: 4 | AB10: 4 | AC10: 4 | AD10: 14 | AE10: 15 | AF10: 16 | AG10: Ver que mi hijo esta creciendo bien integralmente | AI10: Stephany Decheco Vera
B11: SAN MARCOS | C11: HUARI | D11: SAN MARCOS | E11: SANTA CRUZ DE MOSNA | F11: 435 | G11: Inicial - Jardín | H11: 1515246 | I11: 608381 | J11: LETICIA FRIDA SOLORZANO SIFUENTES | K11: LETICIA FRIDA SOLORZANO SIFUENTES | L11: Madre | M11: 24 | N11: 45834 | O11: Pre test (diagnóstico) | P11: 4 | Q11: 4 | R11: 4 | S11: 4 | T11: 5 | U11: 4 | V11: 4 | W11: 4 | X11: 4 | Y11: 4 | Z11: 5 | AA11: 4 | AB11: 5 | AC11: 4 | AD11: 14 | AE11: 14 | AF11: 18 | AG11: Ver que mi hijo se encuentra bien integralmente | AI11: Stephany Decheco Vera
B12: SAN MARCOS | C12: HUARI | D12: SAN MARCOS | E12: SANTA CRUZ DE MOSNA | F12: 435 | G12: Inicial - Jardín | H12: 1515246 | I12: 608381 | J12: ELENA SIGUEÑAS ABARCA | K12: ELENA SIGUEÑAS ABARCA | L12: Madre | M12: 41 | N12: 45834 | O12: Pre test (diagnóstico) | P12: 4 | Q12: 4 | R12: 3 | S12: 3 | T12: 4 | U12: 4 | V12: 4 | W12: 3 | X12: 4 | Y12: 4 | Z12: 4 | AA12: 4 | AB12: 4 | AC12: 4 | AD12: 14 | AE12: 14 | AF12: 16 | AG12: Tomar acuerdos para el bien de mi hijo | AI12: Stephany Decheco Vera
B13: SAN MARCOS | C13: HUARI | D13: SAN MARCOS | E13: SANTA CRUZ DE MOSNA | F13: 435 | G13: Inicial - Jardín | H13: 1515246 | I13: 608381 | J13: ANAYELI ABARCA DAMIAN | K13: ANAYELI ABARCA DAMIAN | L13: Madre | M13: 23 | N13: 45834 | O13: Pre test (diagnóstico) | P13: 4 | Q13: 4 | R13: 5 | S13: 5 | T13: 5 | U13: 5 | V13: 5 | W13: 5 | X13: 5 | Y13: 5 | Z13: 5 | AA13: 4 | AB13: 5 | AC13: 5 | AD13: 14 | AE13: 16 | AF13: 20 | AG13: Compartir tiempo en familia | AI13: Stephany Decheco Vera
B14: SAN MARCOS | C14: HUARI | D14: SAN MARCOS | E14: SANTA CRUZ DE MOSNA | F14: 435 | G14: Inicial - Jardín | H14: 1515246 | I14: 608381 | J14: MARÍA PAUCAR DAMIAN | K14: MARÍA PAUCAR DAMIAN | L14: Madre | M14: 46 | N14: 45834 | O14: Pre test (diagnóstico) | P14: 4 | Q14: 4 | R14: 4 | S14: 4 | T14: 5 | U14: 4 | V14: 4 | W14: 4 | X14: 4 | Y14: 4 | Z14: 5 | AA14: 4 | AB14: 5 | AC14: 4 | AD14: 14 | AE14: 14 | AF14: 18 | AG14: Tener respeto y establecer acuerdos en familia | AI14: Stephany Decheco Vera
B15: SAN MARCOS | C15: HUARI | D15: SAN MARCOS | E15: SANTA CRUZ DE MOSNA | F15: 435 | G15: Inicial - Jardín | H15: 1515246 | I15: 608381 | J15: RODOLFO AMADO CADILLO | K15: RODOLFO AMADO CADILLO | L15: Padre | M15: 36 | N15: 45834 | O15: Pre test (diagnóstico) | P15: 4 | Q15: 4 | R15: 4 | S15: 4 | T15: 4 | U15: 4 | V15: 4 | W15: 4 | X15: 3 | Y15: 3 | Z15: 4 | AA15: 4 | AB15: 4 | AC15: 3 | AD15: 14 | AE15: 14 | AF15: 16 | AI15: Stephany Decheco Vera
B16: SAN MARCOS | C16: HUARI | D16: SAN MARCOS | E16: SANTA CRUZ DE MOSNA | F16: 435 | G16: Inicial - Jardín | H16: 1515246 | I16: 608381 | J16: AIDA FLOR RIVERA VALENZUELA | K16: AIDA FLOR RIVERA VALENZUELA | L16: Madre | M16: 24 | N16: 45834 | O16: Pre test (diagnóstico) | P16: 5 | Q16: 5 | R16: 4 | S16: 4 | T16: 4 | U16: 4 | V16: 4 | W16: 4 | X16: 4 | Y16: 4 | Z16: 4 | AA16: 5 | AB16: 4 | AC16: 4 | AD16: 13 | AE16: 15 | AF16: 16 | AG16: Ver que mi hijo se encuentra bien integralmente | AI16: Stephany Decheco Vera
B17: MINA | C17: HUARI | D17: SAN MARCOS | E17: CARHUAYOC | F17: 248 | G17: Inicial - Jardín | H17: 0509711 | I17: 025227 | J17: MAXIMO CUYA NARRO | K17: MAXIMO CUYA NARRO | L17: Padre | M17: 30 | N17: 45833 | O17: Pre test (diagnóstico) | P17: 4 | Q17: 4 | R17: 5 | S17: 5 | T17: 1 | U17: 4 | V17: 4 | W17: 5 | X17: 3 | Y17: 3 | Z17: 1 | AA17: 4 | AB17: 1 | AC17: 3 | AD17: 14 | AE17: 18 | AF17: 10 | AI17: Stephany Decheco Vera
B18: MINA | C18: HUARI | D18: SAN MARCOS | E18: CARHUAYOC | F18: 248 | G18: Inicial - Jardín | H18: 0509711 | I18: 025227 | J18: DELIA SALVADOR VALENCIA | K18: DELIA SALVADOR VALENCIA | L18: Madre | M18: 34 | N18: 45833 | O18: Pre test (diagnóstico) | P18: 3 | Q18: 3 | R18: 3 | S18: 3 | T18: 5 | U18: 4 | V18: 4 | W18: 3 | X18: 4 | Y18: 4 | Z18: 5 | AA18: 3 | AB18: 5 | AC18: 4 | AD18: 15 | AE18: 13 | AF18: 18 | AG18: Dialogar y salir en familia a despejar la mente, además de orar a Dios | AI18: Stephany Decheco Vera
B19: MINA | C19: HUARI | D19: SAN MARCOS | E19: CARHUAYOC | F19: 248 | G19: Inicial - Jardín | H19: 0509711 | I19: 025227 | J19: MARIBEL HARO SALAZAR | K19: MARIBEL HARO SALAZAR | L19: Madre | M19: 30 | N19: 45833 | O19: Pre test (diagnóstico) | P19: 4 | Q19: 4 | R19: 4 | S19: 4 | T19: 4 | U19: 4 | V19: 4 | W19: 4 | X19: 3 | Y19: 3 | Z19: 4 | AA19: 4 | AB19: 4 | AC19: 3 | AD19: 14 | AE19: 14 | AF19: 16 | AI19: Stephany Decheco Vera
B20: MINA | C20: HUARI | D20: SAN MARCOS | E20: CARHUAYOC | F20: 248 | G20: Inicial - Jardín | H20: 0509711 | I20: 025227 | J20: BRAYAN CARHUAPOMA TARAZONA | K20: BRAYAN CARHUAPOMA TARAZONA | L20: Padre | M20: 24 | N20: 45833 | O20: Pre test (diagnóstico) | P20: 3 | Q20: 3 | R20: 3 | S20: 3 | T20: 4 | U20: 4 | V20: 4 | W20: 3 | X20: 5 | Y20: 5 | Z20: 4 | AA20: 3 | AB20: 4 | AC20: 5 | AD20: 15 | AE20: 15 | AF20: 16 | AI20: Stephany Decheco Vera
B21: MINA | C21: HUARI | D21: SAN MARCOS | E21: CARHUAYOC | F21: 248 | G21: Inicial - Jardín | H21: 0509711 | I21: 025227 | J21: SARA LOPEZ VARGAS | K21: SARA LOPEZ VARGAS | L21: Madre | M21: 35 | N21: 45833 | O21: Pre test (diagnóstico) | P21: 3 | Q21: 3 | R21: 3 | S21: 3 | T21: 3 | U21: 3 | V21: 3 | W21: 3 | X21: 3 | Y21: 3 | Z21: 3 | AA21: 3 | AB21: 3 | AC21: 3 | AD21: 15 | AE21: 14 | AF21: 12 | AI21: Stephany Decheco Vera
B22: MINA | C22: HUARI | D22: SAN MARCOS | E22: CARHUAYOC | F22: 248 | G22: Inicial - Jardín | H22: 0509711 | I22: 025227 | J22: HILARIA SANTA ESPINOZA GUERRA | K22: HILARIA SANTA ESPINOZA GUERRA | L22: Madre | M22: 40 | N22: 45833 | O22: Pre test (diagnóstico) | P22: 3 | Q22: 3 | R22: 3 | S22: 3 | T22: 4 | U22: 4 | V22: 4 | W22: 3 | X22: 4 | Y22: 4 | Z22: 4 | AA22: 3 | AB22: 4 | AC22: 4 | AD22: 15 | AE22: 14 | AF22: 16 | AG22: Hablar con mis hijos para tomar buenas decisiones | AI22: Stephany Decheco Vera
B23: MINA | C23: HUARI | D23: SAN MARCOS | E23: CARHUAYOC | F23: 248 | G23: Inicial - Jardín | H23: 0509711 | I23: 025227 | J23: MARICRUZ ROMERO CASTRO | K23: MARICRUZ ROMERO CASTRO | L23: Madre | M23: 32 | N23: 45833 | O23: Pre test (diagnóstico) | P23: 5 | Q23: 5 | R23: 3 | S23: 3 | T23: 5 | U23: 5 | V23: 5 | W23: 3 | X23: 4 | Y23: 4 | Z23: 5 | AA23: 5 | AB23: 5 | AC23: 4 | AD23: 13 | AE23: 13 | AF23: 20 | AG23: Me ayuda que mis hijos vean que yo estoy bien | AI23: Stephany Decheco Vera
B24: MINA | C24: HUARI | D24: SAN MARCOS | E24: CARHUAYOC | F24: 248 | G24: Inicial - Jardín | H24: 0509711 | I24: 025227 | J24: NANCY GUERRA RAMIREZ | K24: NANCY GUERRA RAMIREZ | L24: Madre | M24: 35 | N24: 45833 | O24: Pre test (diagnóstico) | P24: 5 | Q24: 5 | R24: 5 | S24: 5 | T24: 4 | U24: 4 | V24: 4 | W24: 5 | X24: 5 | Y24: 5 | Z24: 4 | AA24: 5 | AB24: 4 | AC24: 5 | AD24: 13 | AE24: 17 | AF24: 16 | AG24: Me ayuda reflexionar y conversar con mis hijos | AI24: Stephany Decheco Vera
B25: MINA | C25: HUARI | D25: SAN MARCOS | E25: CARHUAYOC | F25: 248 | G25: Inicial - Jardín | H25: 0509711 | I25: 025227 | J25: ELENA EDITA DAVILA LOARTE | K25: ELENA EDITA DAVILA LOARTE | L25: Madre | M25: 35 | N25: 45833 | O25: Pre test (diagnóstico) | P25: 4 | Q25: 4 | R25: 4 | S25: 4 | T25: 4 | U25: 5 | V25: 5 | W25: 4 | X25: 5 | Y25: 5 | Z25: 4 | AA25: 4 | AB25: 4 | AC25: 5 | AD25: 14 | AE25: 16 | AF25: 18 | AI25: Stephany Decheco Vera
B26: MINA | C26: HUARI | D26: SAN MARCOS | E26: CARHUAYOC | F26: 248 | G26: Inicial - Jardín | H26: 0509711 | I26: 025227 | J26: LIDIA ZORRILA FONSECA | K26: LIDIA ZORRILA FONSECA | L26: Madre | M26: 36 | N26: 45833 | O26: Pre test (diagnóstico) | P26: 1 | Q26: 1 | R26: 4 | S26: 4 | T26: 4 | U26: 4 | V26: 4 | W26: 4 | X26: 4 | Y26: 4 | Z26: 4 | AA26: 1 | AB26: 4 | AC26: 4 | AD26: 17 | AE26: 15 | AF26: 16 | AG26: Me ayuda estar feliz y conversar con mis hijos | AI26: Stephany Decheco Vera
B27: MINA | C27: HUARI | D27: SAN MARCOS | E27: CARHUAYOC | F27: 248 | G27: Inicial - Jardín | H27: 0509711 | I27: 025227 | J27: JUAN DAVID QUISPE VARGAS | K27: JUAN DAVID QUISPE VARGAS | L27: Padre | M27: 32 | N27: 45833 | O27: Pre test (diagnóstico) | P27: 4 | Q27: 4 | R27: 4 | S27: 4 | T27: 4 | U27: 3 | V27: 3 | W27: 4 | X27: 4 | Y27: 4 | Z27: 4 | AA27: 4 | AB27: 4 | AC27: 4 | AD27: 14 | AE27: 15 | AF27: 14 | AG27: Saber que mis hijos estan sanos, tener un trabajo seguro y estar bien con mi familia | AI27: Stephany Decheco Vera
B28: MINA | C28: HUARI | D28: SAN MARCOS | E28: CARHUAYOC | F28: 248 | G28: Inicial - Jardín | H28: 0509711 | I28: 025227 | J28: SANDRA GOMEZ HILARIO | K28: SANDRA GOMEZ HILARIO | L28: Madre | M28: 34 | N28: 45833 | O28: Pre test (diagnóstico) | P28: 3 | Q28: 3 | R28: 3 | S28: 3 | T28: 5 | U28: 3 | V28: 3 | W28: 3 | X28: 3 | Y28: 3 | Z28: 5 | AA28: 3 | AB28: 5 | AC28: 3 | AD28: 15 | AE28: 12 | AF28: 16 | AG28: La unión de mi familia con buenos tratos | AI28: Stephany Decheco Vera
B29: MINA | C29: HUARI | D29: SAN MARCOS | E29: CARHUAYOC | F29: 248 | G29: Inicial - Jardín | H29: 0509711 | I29: 025227 | J29: OLINDA RAMOS GARGATE | K29: OLINDA RAMOS GARGATE | L29: Madre | M29: 28 | N29: 45833 | O29: Pre test (diagnóstico) | P29: 4 | Q29: 4 | R29: 4 | S29: 4 | T29: 4 | U29: 5 | V29: 5 | W29: 4 | X29: 5 | Y29: 5 | Z29: 4 | AA29: 4 | AB29: 4 | AC29: 5 | AD29: 14 | AE29: 16 | AF29: 18 | AG29: paciencia y hablarles con amor para que puedan entender | AI29: Stephany Decheco Vera
B30: MINA | C30: HUARI | D30: SAN MARCOS | E30: CARHUAYOC | F30: 248 | G30: Inicial - Jardín | H30: 0509711 | I30: 025227 | J30: TEODORA ARAUJO SOLIS | K30: TEODORA ARAUJO SOLIS | L30: Otro | M30: 53 | N30: 45833 | O30: Pre test (diagnóstico) | P30: 3 | Q30: 3 | R30: 4 | S30: 4 | T30: 4 | U30: 4 | V30: 4 | W30: 4 | X30: 4 | Y30: 4 | Z30: 4 | AA30: 3 | AB30: 4 | AC30: 4 | AD30: 15 | AE30: 15 | AF30: 16 | AG30: Jugar, explicar y preguntar cómo le esta yendo | AI30: Stephany Decheco Vera
B31: MINA | C31: HUARI | D31: SAN MARCOS | E31: CARHUAYOC | F31: 248 | G31: Inicial - Jardín | H31: 0509711 | I31: 025227 | J31: JAKELINE GUERRA ALFARO | K31: JAKELINE GUERRA ALFARO | L31: Madre | M31: 32 | N31: 45833 | O31: Pre test (diagnóstico) | P31: 5 | Q31: 5 | R31: 5 | S31: 5 | T31: 5 | U31: 5 | V31: 5 | W31: 5 | X31: 5 | Y31: 5 | AA31: 5 | AB31: 5 | AC31: 5 | AD31: 13 | AE31: 21 | AF31: 20 | AG31: Tratar de comprender cada situación | AI31: Stephany Decheco Vera
B32: MINA | C32: HUARI | D32: SAN MARCOS | E32: CARHUAYOC | F32: 248 | G32: Inicial - Jardín | H32: 0509711 | I32: 025227 | J32: YANIRA RAMOS GUERRA | K32: YANIRA RAMOS GUERRA | L32: Madre | M32: 39 | N32: 45833 | O32: Pre test (diagnóstico) | P32: 5 | Q32: 5 | R32: 4 | S32: 4 | T32: 5 | U32: 5 | V32: 5 | W32: 4 | X32: 5 | Y32: 5 | Z32: 5 | AA32: 5 | AB32: 5 | AC32: 5 | AD32: 13 | AE32: 15 | AF32: 20 | AI32: Stephany Decheco Vera
B33: MINA | C33: HUARI | D33: SAN MARCOS | E33: CARHUAYOC | F33: 248 | G33: Inicial - Jardín | H33: 0509711 | I33: 025227 | J33: ELISA GUERRA LAGUNA | K33: ELISA GUERRA LAGUNA | L33: Madre | M33: 30 | N33: 45833 | O33: Pre test (diagnóstico) | P33: 4 | Q33: 4 | R33: 5 | S33: 5 | T33: 5 | U33: 5 | V33: 5 | W33: 5 | X33: 4 | Y33: 4 | Z33: 5 | AA33: 4 | AB33: 5 | AC33: 4 | AD33: 14 | AE33: 15 | AF33: 20 | AG33: Estar bien con mi hijo, tratar de ayudar en sus emociones, la buena comunicación y confianza | AI33: Stephany Decheco Vera
B34: MINA | C34: HUARI | D34: SAN MARCOS | E34: CARHUAYOC | F34: 248 | G34: Inicial - Jardín | H34: 0509711 | I34: 025227 | J34: ROMELIA DIAZ ARQUINIZO | K34: ROMELIA DIAZ ARQUINIZO | L34: Madre | M34: 29 | N34: 45833 | O34: Pre test (diagnóstico) | P34: 4 | Q34: 4 | R34: 4 | S34: 4 | T34: 5 | U34: 4 | V34: 4 | W34: 4 | X34: 4 | Y34: 4 | Z34: 5 | AA34: 4 | AB34: 5 | AC34: 4 | AD34: 14 | AE34: 14 | AF34: 18 | AG34: Que mis hijos crezcan con valores y educados | AI34: Stephany Decheco Vera
B35: MINA | C35: HUARI | D35: SAN MARCOS | E35: CARHUAYOC | F35: 248 | G35: Inicial - Jardín | H35: 0509711 | I35: 025227 | J35: YISSELA TICLO GUERRA | K35: YISSELA TICLO GUERRA | L35: Madre | M35: 25 | N35: 45833 | O35: Pre test (diagnóstico) | P35: 4 | Q35: 4 | R35: 4 | S35: 4 | T35: 5 | U35: 3 | V35: 3 | W35: 4 | X35: 4 | Y35: 4 | Z35: 5 | AA35: 4 | AB35: 5 | AC35: 4 | AD35: 14 | AE35: 14 | AF35: 16 | AG35: Ser más responsable como mamá | AI35: Stephany Decheco Vera
B36: MINA | C36: HUARI | D36: SAN MARCOS | E36: CARHUAYOC | F36: 248 | G36: Inicial - Jardín | H36: 0509711 | I36: 025227 | J36: DIONY YLLARY MARQUEZ CHAVEZ | K36: DIONY YLLARY MARQUEZ CHAVEZ | L36: Otro | M36: 19 | N36: 45833 | O36: Pre test (diagnóstico) | P36: 4 | Q36: 4 | R36: 4 | S36: 4 | T36: 5 | U36: 3 | V36: 3 | W36: 4 | X36: 4 | Y36: 4 | Z36: 5 | AA36: 4 | AB36: 5 | AC36: 4 | AD36: 14 | AE36: 14 | AF36: 16 | AG36: Como hermana me gusta hablar con él, saber cómo esta | AI36: Stephany Decheco Vera
B37: MINA | C37: HUARI | D37: SAN MARCOS | E37: CARHUAYOC | F37: 248 | G37: Inicial - Jardín | H37: 0509711 | I37: 025227 | J37: VIOLETA AMADO SALAZAR | K37: VIOLETA AMADO SALAZAR | L37: Madre | M37: 37 | N37: 45833 | O37: Pre test (diagnóstico) | P37: 5 | Q37: 5 | R37: 4 | S37: 4 | T37: 5 | U37: 5 | V37: 5 | W37: 4 | X37: 5 | Y37: 5 | Z37: 5 | AA37: 5 | AB37: 5 | AC37: 5 | AD37: 13 | AE37: 15 | AF37: 20 | AG37: Conversar | AI37: Stephany Decheco Vera
B38: MINA | C38: HUARI | D38: SAN MARCOS | E38: CARHUAYOC | F38: 248 | G38: Inicial - Jardín | H38: 0509711 | I38: 025227 | J38: FELENA MALLQUI ARAUJO | K38: FELENA MALLQUI ARAUJO | L38: Madre | M38: 36 | N38: 45833 | O38: Pre test (diagnóstico) | P38: 4 | Q38: 4 | R38: 3 | S38: 3 | T38: 4 | U38: 4 | V38: 4 | W38: 3 | X38: 4 | Y38: 4 | Z38: 4 | AA38: 4 | AB38: 4 | AC38: 4 | AD38: 14 | AE38: 14 | AF38: 16 | AG38: Tratar de calmarme y corregirle | AI38: Stephany Decheco Vera
B39: MINA | C39: HUARI | D39: SAN MARCOS | E39: CARHUAYOC | F39: 248 | G39: Inicial - Jardín | H39: 0509711 | I39: 025227 | J39: ARAUJO GUERRA LUCINDA | K39: ARAUJO GUERRA LUCINDA | L39: Madre | M39: 26 | N39: 45833 | O39: Pre test (diagnóstico) | P39: 4 | Q39: 4 | R39: 4 | S39: 4 | T39: 4 | U39: 2 | V39: 2 | W39: 4 | X39: 2 | Y39: 2 | Z39: 4 | AA39: 4 | AB39: 4 | AC39: 2 | AD39: 14 | AE39: 13 | AF39: 12 | AG39: Tratar bien y jugar con mis hijos | AI39: Stephany Decheco Vera
B40: MINA | C40: HUARI | D40: SAN MARCOS | E40: CARHUAYOC | F40: 248 | G40: Inicial - Jardín | H40: 0509711 | I40: 025227 | J40: DEYSI SALAZAR VALVERDE | K40: DEYSI SALAZAR VALVERDE | L40: Madre | M40: 29 | N40: 45833 | O40: Pre test (diagnóstico) | P40: 5 | Q40: 5 | R40: 4 | S40: 4 | T40: 5 | U40: 5 | V40: 5 | W40: 4 | X40: 5 | Y40: 5 | Z40: 5 | AA40: 5 | AB40: 5 | AC40: 5 | AD40: 13 | AE40: 15 | AF40: 20 | AG40: Contar con el apoyo de mi familiar, y frente a cualquier problema resolverlo conversando con mi hija | AI40: Stephany Decheco Vera
B41: MINA | C41: HUARI | D41: SAN MARCOS | E41: CARHUAYOC | F41: 248 | G41: Inicial - Jardín | H41: 0509711 | I41: 025227 | J41: FELICITAS ACEVEDO TRUJILLO | K41: FELICITAS ACEVEDO TRUJILLO | L41: Madre | M41: 36 | N41: 45833 | O41: Pre test (diagnóstico) | P41: 4 | Q41: 4 | R41: 5 | S41: 5 | T41: 5 | U41: 4 | V41: 4 | W41: 5 | X41: 5 | Y41: 5 | Z41: 5 | AA41: 4 | AB41: 5 | AC41: 5 | AD41: 14 | AE41: 16 | AF41: 18 | AG41: Manejar con calma cualquier situación | AI41: Stephany Decheco Vera
B42: MINA | C42: HUARI | D42: SAN MARCOS | E42: CARHUAYOC | F42: 248 | G42: Inicial - Jardín | H42: 0509711 | I42: 025227 | J42: SANDRA CLAUDIO FERNANDEZ | K42: SANDRA CLAUDIO FERNANDEZ | L42: Madre | M42: 24 | N42: 45833 | O42: Pre test (diagnóstico) | P42: 4 | Q42: 4 | R42: 4 | S42: 4 | T42: 4 | U42: 4 | V42: 4 | W42: 4 | X42: 4 | Y42: 4 | Z42: 4 | AA42: 4 | AB42: 4 | AC42: 4 | AD42: 14 | AE42: 15 | AF42: 16 | AG42: Como mamá que mis hjos esten bien es lo que me hace sentir bien | AI42: Stephany Decheco Vera
B43: MINA | C43: HUARI | D43: SAN MARCOS | E43: CARHUAYOC | F43: 248 | G43: Inicial - Jardín | H43: 0509711 | I43: 025227 | J43: JASMINA PALACIOS GAMARRA | K43: JASMINA PALACIOS GAMARRA | L43: Madre | M43: 27 | N43: 45833 | O43: Pre test (diagnóstico) | P43: 4 | Q43: 4 | R43: 3 | S43: 3 | T43: 4 | U43: 3 | V43: 3 | W43: 3 | X43: 4 | Y43: 4 | Z43: 4 | AA43: 4 | AB43: 4 | AC43: 4 | AD43: 14 | AE43: 14 | AF43: 14 | AG43: Que mis hijos estén bien, y que practiquen los valores y el respeto entre nosotros como familia | AI43: Stephany Decheco Vera
B44: MINA | C44: HUARI | D44: SAN MARCOS | E44: CARHUAYOC | F44: 248 | G44: Inicial - Jardín | H44: 0509711 | I44: 025227 | J44: ESTHER RAMIREZ PRUDENCIO | K44: ESTHER RAMIREZ PRUDENCIO | L44: Madre | M44: 25 | N44: 45833 | O44: Pre test (diagnóstico) | P44: 5 | Q44: 5 | R44: 3 | S44: 3 | T44: 4 | U44: 3 | V44: 3 | W44: 3 | X44: 3 | Y44: 3 | Z44: 4 | AA44: 5 | AB44: 4 | AC44: 3 | AD44: 13 | AE44: 13 | AF44: 14 | AG44: Que mi hijo esté bien y practique los valores que le enseñamos | AI44: Stephany Decheco Vera
... B48: MINA | C48: HUARI | D48: SAN MARCOS | E48: CARHUAYOC | F48: 248 | G48: Inicial - Jardín | H48: 0509711 | I48: 025227 | J48: SARITA GARAY ESPINOZA | K48: SARITA GARAY ESPINOZA | L48: Madre | M48: 23 | N48: 45833 | O48: Pre test (diagnóstico) | P48: 4 | Q48: 4 | R48: 5 | S48: 5 | T48: 4 | U48: 4 | V48: 4 | W48: 5 | X48: 4 | Y48: 4 | Z48: 4 | AA48: 4 | AB48: 4 | AC48: 4 | AD48: 14 | AE48: 16 | AF48: 16 | AG48: Dialogar ante cualquier situación que ocurra y pensar en una solución que no perjudique a los niños | AI48: Stephany Decheco Vera
B49: MINA | C49: HUARI | D49: SAN MARCOS | E49: CARHUAYOC | F49: 248 | G49: Inicial - Jardín | H49: 0509711 | I49: 025227 | J49: NANCY CADILLO PAREDA | K49: NANCY CADILLO PAREDA | L49: Madre | M49: 35 | N49: 45833 | O49: Pre test (diagnóstico) | P49: 1 | Q49: 1 | R49: 2 | S49: 2 | T49: 3 | U49: 3 | V49: 3 | W49: 2 | X49: 4 | Y49: 4 | Z49: 3 | AA49: 1 | AB49: 3 | AC49: 4 | AD49: 17 | AE49: 14 | AF49: 12 | AI49: Stephany Decheco Vera
B50: MINA | C50: HUARI | D50: SAN MARCOS | E50: CARHUAYOC | F50: 248 | G50: Inicial - Jardín | H50: 0509711 | I50: 025227 | J50: VICTOR ADRIANO LEÓN | K50: VICTOR ADRIANO LEÓN | L50: Padre | M50: 40 | N50: 45833 | O50: Pre test (diagnóstico) | P50: 4 | Q50: 4 | R50: 4 | S50: 4 | T50: 4 | U50: 4 | V50: 4 | W50: 4 | X50: 4 | Y50: 4 | Z50: 4 | AA50: 4 | AB50: 4 | AC50: 4 | AD50: 14 | AE50: 15 | AF50: 16 | AG50: Conversar con mis hijos y familia | AI50: Stephany Decheco Vera
B51: MINA | C51: HUARI | D51: SAN MARCOS | E51: CARHUAYOC | F51: 248 | G51: Inicial - Jardín | H51: 0509711 | I51: 025227 | J51: WAGNER FERNANDEZ AIRA | K51: WAGNER FERNANDEZ AIRA | L51: Padre | M51: 39 | N51: 45833 | O51: Pre test (diagnóstico) | P51: 4 | Q51: 4 | R51: 4 | S51: 4 | T51: 4 | U51: 4 | V51: 4 | W51: 4 | X51: 4 | Y51: 4 | Z51: 4 | AA51: 4 | AB51: 4 | AC51: 4 | AD51: 14 | AE51: 15 | AF51: 16 | AG51: Conversar con mis hijos y familia | AI51: Stephany Decheco Vera
B52: MINA | C52: HUARI | D52: SAN MARCOS | E52: CARHUAYOC | F52: 248 | G52: Inicial - Jardín | H52: 0509711 | I52: 025227 | J52: BELINDA GARAY LEYVA | K52: BELINDA GARAY LEYVA | L52: Madre | M52: 36 | N52: 45833 | O52: Pre test (diagnóstico) | P52: 4 | Q52: 4 | R52: 4 | S52: 4 | T52: 5 | U52: 4 | V52: 4 | W52: 4 | X52: 5 | Y52: 5 | Z52: 5 | AA52: 4 | AB52: 5 | AC52: 5 | AD52: 14 | AE52: 15 | AF52: 18 | AG52: Que me informen los comportamientos de mi hijo en el colegio | AI52: Stephany Decheco Vera
B53: MINA | C53: HUARI | D53: SAN MARCOS | E53: CARHUAYOC | F53: 248 | G53: Inicial - Jardín | H53: 0509711 | I53: 025227 | J53: NAUN YESMER QUISPE UGARTE | K53: NAUN YESMER QUISPE UGARTE | L53: Padre | M53: 32 | N53: 45833 | O53: Pre test (diagnóstico) | P53: 5 | Q53: 5 | R53: 5 | S53: 5 | T53: 5 | U53: 5 | V53: 5 | W53: 5 | X53: 5 | Y53: 5 | Z53: 5 | AA53: 5 | AB53: 5 | AC53: 5 | AD53: 13 | AE53: 16 | AF53: 20 | AG53: Comunicación en familia | AI53: Stephany Decheco Vera
B54: MINA | C54: HUARI | D54: SAN MARCOS | E54: CARHUAYOC | F54: 248 | G54: Inicial - Jardín | H54: 0509711 | I54: 025227 | J54: ELMER ZORRILLA GUERRA | K54: ELMER ZORRILLA GUERRA | L54: Padre | M54: 36 | N54: 45833 | O54: Pre test (diagnóstico) | P54: 4 | Q54: 4 | R54: 4 | S54: 4 | T54: 4 | U54: 4 | V54: 4 | W54: 4 | X54: 4 | Y54: 4 | Z54: 4 | AA54: 4 | AB54: 4 | AC54: 4 | AD54: 14 | AE54: 15 | AF54: 16 | AG54: Estar feliz con mi hijo y enseñarle a ser responsable en sus actos | AI54: Stephany Decheco Vera
B55: MINA | C55: HUARI | D55: SAN MARCOS | E55: CARHUAYOC | F55: 248 | G55: Inicial - Jardín | H55: 0509711 | I55: 025227 | J55: SUSA GARAY FERNANDEZ | K55: SUSA GARAY FERNANDEZ | L55: Madre | M55: 32 | N55: 45833 | O55: Pre test (diagnóstico) | P55: 4 | Q55: 4 | R55: 3 | S55: 3 | T55: 5 | U55: 5 | V55: 5 | W55: 3 | X55: 4 | Y55: 4 | Z55: 5 | AA55: 4 | AB55: 5 | AC55: 4 | AD55: 14 | AE55: 13 | AF55: 20 | AG55: Que mi hija este bien y que tenga buenas notas, me hace sentir orgullosa | AI55: Stephany Decheco Vera
B56: MINA | C56: HUARI | D56: SAN MARCOS | E56: CARHUAYOC | F56: 248 | G56: Inicial - Jardín | H56: 0509711 | I56: 025227 | J56: VIONE CATIRE ENRIQUE | K56: VIONE CATIRE ENRIQUE | L56: Madre | M56: 30 | N56: 45833 | O56: Pre test (diagnóstico) | P56: 2 | Q56: 2 | R56: 2 | S56: 2 | T56: 5 | U56: 1 | V56: 1 | W56: 2 | X56: 3 | Y56: 3 | Z56: 5 | AA56: 2 | AB56: 5 | AC56: 3 | AD56: 16 | AE56: 11 | AF56: 12 | AG56: Que mis hijos se sientan bien | AI56: Stephany Decheco Vera
B57: MINA | C57: HUARI | D57: SAN MARCOS | E57: CARHUAYOC | F57: 248 | G57: Inicial - Jardín | H57: 0509711 | I57: 025227 | J57: MILAGRITOS EUDALIA VILLANUEVA MARIÑO | K57: MILAGRITOS EUDALIA VILLANUEVA MARIÑO | L57: Madre | M57: 28 | N57: 45833 | O57: Pre test (diagnóstico) | P57: 4 | Q57: 4 | R57: 3 | S57: 3 | T57: 5 | U57: 3 | V57: 3 | W57: 3 | X57: 5 | Y57: 5 | Z57: 5 | AA57: 4 | AB57: 5 | AC57: 5 | AD57: 14 | AE57: 14 | AF57: 16 | AG57: Me ayuda a estar tranquila sin estrés, siento que podría ser mejor mamá y me ayudaria contar con apoyo psicológico | AI57: Stephany Decheco Vera
B58: MINA | C58: HUARI | D58: SAN MARCOS | E58: CARHUAYOC | F58: 248 | G58: Inicial - Jardín | H58: 0509711 | I58: 025227 | J58: DAVILA LOARTE | K58: DAVILA LOARTE | L58: Madre | M58: 25 | N58: 45833 | O58: Pre test (diagnóstico) | P58: 4 | Q58: 4 | R58: 4 | S58: 4 | T58: 4 | U58: 4 | V58: 4 | W58: 4 | X58: 4 | Y58: 4 | Z58: 4 | AA58: 4 | AB58: 4 | AC58: 4 | AD58: 14 | AE58: 15 | AF58: 16 | AG58: Ver a mi hijo feliz en su día a día | AI58: Stephany Decheco Vera
B59: MINA | C59: HUARI | D59: SAN MARCOS | E59: CARHUAYOC | F59: 248 | G59: Inicial - Jardín | H59: 0509711 | I59: 025227 | J59: MIGUEL CHAVEZ DAVILA | K59: MIGUEL CHAVEZ DAVILA | L59: Padre | M59: 32 | N59: 45833 | O59: Pre test (diagnóstico) | P59: 4 | Q59: 4 | R59: 3 | S59: 3 | T59: 5 | U59: 4 | V59: 4 | W59: 3 | X59: 4 | Y59: 4 | Z59: 5 | AA59: 4 | AB59: 5 | AC59: 4 | AD59: 14 | AE59: 13 | AF59: 18 | AG59: Controlar mis emociones, analizar antes de actuar ya que considero que somos el reflejo ante niños/as | AI59: Stephany Decheco Vera
B60: MINA | C60: HUARI | D60: SAN MARCOS | E60: CARHUAYOC | F60: 248 | G60: Inicial - Jardín | H60: 0509711 | I60: 025227 | J60: MARUJA GUERRA HUERTA | K60: MARUJA GUERRA HUERTA | L60: Madre | M60: 33 | N60: 45833 | O60: Pre test (diagnóstico) | P60: 4 | Q60: 4 | R60: 4 | S60: 4 | T60: 4 | U60: 5 | V60: 5 | W60: 4 | X60: 4 | Y60: 4 | Z60: 4 | AA60: 4 | AB60: 4 | AC60: 4 | AD60: 14 | AE60: 15 | AF60: 18 | AG60: El bienestar de mis hijos | AI60: Stephany Decheco Vera
B61: MINA | C61: HUARI | D61: SAN MARCOS | E61: CARHUAYOC | F61: 248 | G61: Inicial - Jardín | H61: 0509711 | I61: 025227 | J61: WILMER RIOS DIANES | K61: WILMER RIOS DIANES | L61: Padre | M61: 38 | N61: 45833 | O61: Pre test (diagnóstico) | P61: 4 | Q61: 4 | R61: 3 | S61: 3 | T61: 3 | U61: 4 | V61: 4 | W61: 3 | X61: 4 | Y61: 4 | Z61: 3 | AA61: 4 | AB61: 3 | AC61: 4 | AD61: 14 | AE61: 15 | AF61: 14 | AG61: Practicar los valores en casa e incluclar la responsabilidad poco a poco según la edad del niño | AI61: Stephany Decheco Vera
... B89: SAN MARCOS | C89: HUARI | D89: SAN MARCOS | E89: PUJUN | F89: 109 | G89: Inicial - Jardín | H89: 1551753 | I89: 631664 | J89: SOLIS RIVERA | K89: SOLIS RIVERA | L89: Otro | M89: 88 | N89: 45839 | O89: Pre test (diagnóstico) | P89: 4 | Q89: 4 | R89: 1 | S89: 1 | T89: 4 | U89: 4 | V89: 4 | W89: 1 | X89: 4 | Y89: 4 | Z89: 4 | AA89: 4 | AB89: 4 | AC89: 4 | AD89: 14 | AE89: 12 | AF89: 16 | AG89: Jugar con mi nieto | AI89: Stephany Decheco Vera
B90: SAN MARCOS | C90: HUARI | D90: SAN MARCOS | E90: PUJUN | F90: 109 | G90: Inicial - Jardín | H90: 1551753 | I90: 631664 | J90: RRIMOLDA ESPINOZA MALQUI | K90: RRIMOLDA ESPINOZA MALQUI | L90: Otro | M90: 49 | N90: 45839 | O90: Pre test (diagnóstico) | P90: 4 | Q90: 4 | R90: 4 | S90: 4 | T90: 4 | U90: 3 | V90: 4 | W90: 4 | X90: 4 | Y90: 4 | Z90: 4 | AA90: 4 | AB90: 4 | AC90: 4 | AD90: 14 | AE90: 15 | AF90: 15 | AI90: Stephany Decheco Vera
B91: SAN MARCOS | C91: HUARI | D91: SAN MARCOS | E91: PUJUN | F91: 109 | G91: Inicial - Jardín | H91: 1551753 | I91: 631664 | J91: ELIZABETH ARAUJO COTRINA | K91: ELIZABETH ARAUJO COTRINA | L91: Madre | M91: 24 | N91: 45839 | O91: Pre test (diagnóstico) | P91: 5 | Q91: 5 | R91: 5 | S91: 5 | T91: 4 | U91: 5 | V91: 5 | W91: 5 | X91: 5 | Y91: 5 | Z91: 4 | AA91: 5 | AB91: 4 | AC91: 5 | AD91: 13 | AE91: 17 | AF91: 18 | AG91: Comunicarnos toda la familia y respirar profundamente | AI91: Stephany Decheco Vera
B92: SAN MARCOS | C92: HUARI | D92: SAN MARCOS | E92: PUJUN | F92: 109 | G92: Inicial - Jardín | H92: 1551753 | I92: 631664 | J92: MENDIETA GUIZABALO GUADALUPE | K92: MENDIETA GUIZABALO GUADALUPE | L92: Madre | M92: 29 | N92: 45839 | O92: Pre test (diagnóstico) | P92: 4 | Q92: 4 | R92: 4 | S92: 4 | T92: 4 | U92: 4 | V92: 4 | W92: 4 | X92: 4 | Z92: 4 | AA92: 4 | AB92: 4 | AC92: 4 | AD92: 14 | AE92: 11 | AF92: 16 | AG92: Tomar decisiones entre ambos para estar bien | AI92: Stephany Decheco Vera
B93: SAN MARCOS | C93: HUARI | D93: SAN MARCOS | E93: PUJUN | F93: 109 | G93: Inicial - Jardín | H93: 1551753 | I93: 631664 | J93: MELISA SALAZAR LAGUNA | K93: MELISA SALAZAR LAGUNA | L93: Madre | M93: 22 | N93: 45839 | O93: Pre test (diagnóstico) | P93: 5 | Q93: 5 | R93: 4 | S93: 4 | T93: 4 | U93: 3 | V93: 3 | W93: 4 | X93: 4 | Y93: 4 | Z93: 4 | AA93: 5 | AB93: 4 | AC93: 4 | AD93: 13 | AE93: 15 | AF93: 14 | AG93: Tranquilizarme cuando estoy enojada con mi hijo y luego hablarle a mi hijo lo que hizo está mal | AI93: Stephany Decheco Vera
B94: SAN MARCOS | C94: HUARI | D94: SAN MARCOS | E94: OPAYACO/OPAYACU | F94: 099 | G94: Inicial - Jardín | H94: 1551738 | I94: 631640 | J94: MARCELINA DOMINGUEZ PALACIOS | K94: MARCELINA DOMINGUEZ PALACIOS | L94: Madre | M94: 41 | N94: 45833 | O94: Pre test (diagnóstico) | P94: 3 | Q94: 3 | R94: 3 | S94: 3 | T94: 4 | U94: 4 | V94: 4 | W94: 3 | X94: 4 | Y94: 4 | Z94: 4 | AA94: 3 | AB94: 4 | AC94: 4 | AD94: 15 | AE94: 14 | AF94: 16 | AG94: Que mis hijos sean felices y ayudarlos con las tareas que le dejan en el colegio | AI94: Stephany Decheco Vera
B95: SAN MARCOS | C95: HUARI | D95: SAN MARCOS | E95: OPAYACO/OPAYACU | F95: 099 | G95: Inicial - Jardín | H95: 1551738 | I95: 631640 | J95: JUSTINA OBREGON FLORES | K95: JUSTINA OBREGON FLORES | L95: Madre | M95: 34 | N95: 45833 | O95: Pre test (diagnóstico) | P95: 4 | Q95: 4 | R95: 2 | S95: 2 | T95: 3 | U95: 3 | V95: 3 | W95: 2 | X95: 4 | Y95: 4 | Z95: 3 | AA95: 4 | AB95: 3 | AC95: 4 | AD95: 14 | AE95: 14 | AF95: 12 | AG95: Ser una madre compensiva, entendiendo a los niños y a la familia | AI95: Stephany Decheco Vera
B96: SAN MARCOS | C96: HUARI | D96: SAN MARCOS | E96: OPAYACO/OPAYACU | F96: 099 | G96: Inicial - Jardín | H96: 1551738 | I96: 631640 | J96: YANETH MILAGROS ALVARO CHAVEZ | K96: YANETH MILAGROS ALVARO CHAVEZ | L96: Madre | M96: 33 | N96: 45833 | O96: Pre test (diagnóstico) | P96: 3 | Q96: 3 | R96: 3 | S96: 3 | T96: 4 | U96: 4 | V96: 4 | W96: 3 | X96: 3 | Y96: 3 | Z96: 4 | AA96: 3 | AB96: 4 | AC96: 3 | AD96: 15 | AE96: 13 | AF96: 16 | AG96: Como mamá me ayuda conversar con mis hijos, tener confianza y ser como una amiga para ellos | AI96: Stephany Decheco Vera
B97: SAN MARCOS | C97: HUARI | D97: SAN MARCOS | E97: OPAYACO/OPAYACU | F97: 099 | G97: Inicial - Jardín | H97: 1551738 | I97: 631640 | J97: GUISELA SAYDA ALVARO CHAVEZ | K97: GUISELA SAYDA ALVARO CHAVEZ | L97: Madre | M97: 32 | N97: 45833 | O97: Pre test (diagnóstico) | P97: 4 | Q97: 4 | R97: 3 | S97: 3 | T97: 3 | U97: 3 | V97: 3 | W97: 3 | X97: 4 | Y97: 4 | Z97: 3 | AA97: 4 | AB97: 3 | AC97: 4 | AD97: 14 | AE97: 15 | AF97: 12 | AG97: Llevarme bien con los hijos para estar bien | AI97: Stephany Decheco Vera
B98: SAN MARCOS | C98: HUARI | D98: SAN MARCOS | E98: OPAYACO/OPAYACU | F98: 099 | G98: Inicial - Jardín | H98: 1551738 | I98: 631640 | J98: YOMIRA HUAYTA VARGAS | K98: YOMIRA HUAYTA VARGAS | L98: Madre | M98: 29 | N98: 45833 | O98: Pre test (diagnóstico) | P98: 4 | Q98: 4 | R98: 3 | S98: 3 | T98: 4 | U98: 3 | V98: 3 | W98: 3 | X98: 3 | Y98: 3 | Z98: 4 | AA98: 4 | AB98: 4 | AC98: 3 | AD98: 14 | AE98: 13 | AF98: 14 | AG98: Cuando mi hija me obedece me hace sentir aliviada y tranquila | AI98: Stephany Decheco Vera
B99: SAN MARCOS | C99: HUARI | D99: SAN MARCOS | E99: OPAYACO/OPAYACU | F99: 099 | G99: Inicial - Jardín | H99: 1551738 | I99: 631640 | J99: SANTA NIEVES RIVAS RAMIREZ | K99: SANTA NIEVES RIVAS RAMIREZ | L99: Madre | M99: 27 | N99: 45833 | O99: Pre test (diagnóstico) | P99: 4 | Q99: 4 | R99: 4 | S99: 4 | T99: 4 | U99: 4 | V99: 4 | W99: 4 | X99: 4 | Y99: 4 | Z99: 4 | AA99: 4 | AB99: 4 | AC99: 4 | AD99: 14 | AE99: 15 | AF99: 16 | AG99: El dialogo con todos los integrantes de mi familia | AI99: Stephany Decheco Vera
B100: SAN MARCOS | C100: HUARI | D100: SAN MARCOS | E100: OPAYACO/OPAYACU | F100: 099 | G100: Inicial - Jardín | H100: 1551738 | I100: 631640 | J100: YENY ROJAS BAZAM | K100: YENY ROJAS BAZAM | L100: Madre | M100: 30 | N100: 45833 | O100: Pre test (diagnóstico) | P100: 4 | Q100: 4 | R100: 4 | S100: 4 | T100: 4 | U100: 4 | V100: 4 | W100: 4 | X100: 5 | Y100: 5 | Z100: 4 | AA100: 4 | AB100: 4 | AC100: 5 | AD100: 14 | AE100: 16 | AF100: 16 | AG100: Me ayuda ser una madre comprensiva, no alterarme con mis hijos | AI100: Stephany Decheco Vera
B101: SAN MARCOS | C101: HUARI | D101: SAN MARCOS | E101: OPAYACO/OPAYACU | F101: 099 | G101: Inicial - Jardín | H101: 1551738 | I101: 631640 | J101: ROSA BLAS VILLANUEVA | K101: ROSA BLAS VILLANUEVA | L101: Madre | M101: 30 | N101: 45833 | O101: Pre test (diagnóstico) | P101: 4 | Q101: 4 | R101: 3 | S101: 3 | T101: 3 | U101: 3 | V101: 3 | W101: 3 | X101: 4 | Y101: 4 | Z101: 3 | AA101: 4 | AB101: 3 | AC101: 4 | AD101: 14 | AE101: 15 | AF101: 12 | AI101: Stephany Decheco Vera
B102: SAN MARCOS | C102: HUARI | D102: SAN MARCOS | E102: OPAYACO/OPAYACU | F102: 099 | G102: Inicial - Jardín | H102: 1551738 | I102: 631640 | J102: VICTORIA OBREGON FLORES | K102: VICTORIA OBREGON FLORES | L102: Madre | M102: 33 | N102: 45833 | O102: Pre test (diagnóstico) | P102: 3 | Q102: 3 | R102: 4 | S102: 4 | T102: 4 | U102: 2 | V102: 2 | W102: 4 | X102: 4 | Y102: 4 | Z102: 4 | AA102: 3 | AB102: 4 | AC102: 4 | AD102: 15 | AE102: 15 | AF102: 12 | AG102: Ser una madre comprensiva | AI102: Stephany Decheco Vera
B103: SAN MARCOS | C103: HUARI | D103: SAN MARCOS | E103: OPAYACO/OPAYACU | F103: 099 | G103: Inicial - Jardín | H103: 1551738 | I103: 631640 | J103: EDITA GARAY FERNANDEZ | K103: EDITA GARAY FERNANDEZ | L103: Madre | M103: 31 | N103: 45833 | O103: Pre test (diagnóstico) | P103: 4 | Q103: 4 | R103: 4 | S103: 4 | T103: 4 | U103: 5 | V103: 5 | W103: 4 | X103: 4 | Y103: 4 | Z103: 4 | AA103: 4 | AB103: 4 | AC103: 4 | AD103: 14 | AE103: 15 | AF103: 18 | AG103: Cuando estoy con mis hijos me siento feliz | AI103: Stephany Decheco Vera
B104: SAN MARCOS | C104: HUARI | D104: SAN MARCOS | E104: OPAYACO/OPAYACU | F104: 099 | G104: Inicial - Jardín | H104: 1551738 | I104: 631640 | J104: ROCIO MOSQUERA VEGA | K104: ROCIO MOSQUERA VEGA | L104: Madre | M104: 29 | N104: 45833 | O104: Pre test (diagnóstico) | P104: 4 | Q104: 4 | R104: 5 | S104: 5 | T104: 5 | U104: 4 | V104: 4 | W104: 5 | X104: 5 | Y104: 5 | Z104: 5 | AA104: 4 | AB104: 5 | AC104: 5 | AD104: 14 | AE104: 16 | AF104: 18 | AG104: La confianza de mi hija con nosotros su familia y que aprenda los valores | AI104: Stephany Decheco Vera
B105: SAN MARCOS | C105: HUARI | D105: SAN MARCOS | E105: OPAYACO/OPAYACU | F105: 099 | G105: Inicial - Jardín | H105: 1551738 | I105: 631640 | J105: ZAIDA MELISSA CABRERA LOARTE | K105: ZAIDA MELISSA CABRERA LOARTE | L105: Madre | M105: 18 | N105: 45833 | O105: Pre test (diagnóstico) | P105: 2 | Q105: 2 | R105: 5 | S105: 5 | T105: 4 | U105: 4 | V105: 4 | W105: 5 | X105: 4 | Y105: 4 | Z105: 4 | AA105: 2 | AB105: 4 | AC105: 4 | AD105: 16 | AE105: 16 | AF105: 16 | AG105: Me ayuda estar bien con mi hija | AI105: Stephany Decheco Vera
B106: SAN MARCOS | C106: HUARI | D106: SAN MARCOS | E106: OPAYACO/OPAYACU | F106: 099 | G106: Inicial - Jardín | H106: 1551738 | I106: 631640 | J106: ZOIDA HIDALGO POSTOR | K106: ZOIDA HIDALGO POSTOR | L106: Madre | M106: 38 | N106: 45833 | O106: Pre test (diagnóstico) | P106: 3 | Q106: 3 | R106: 3 | S106: 3 | T106: 4 | U106: 4 | V106: 4 | W106: 3 | X106: 2 | Y106: 2 | Z106: 4 | AA106: 3 | AB106: 4 | AC106: 2 | AD106: 15 | AE106: 12 | AF106: 16 | AG106: Ser muy calmada y tolerante | AI106: Stephany Decheco Vera
B107: SAN MARCOS | C107: HUARI | D107: SAN MARCOS | E107: OPAYACO/OPAYACU | F107: 099 | G107: Inicial - Jardín | H107: 1551738 | I107: 631640 | J107: SANTA ANAYA | K107: SANTA ANAYA | L107: Otro | M107: 52 | N107: 45833 | O107: Pre test (diagnóstico) | P107: 3 | Q107: 3 | R107: 3 | S107: 3 | T107: 5 | U107: 2 | V107: 2 | W107: 3 | X107: 1 | Y107: 1 | Z107: 5 | AA107: 3 | AB107: 5 | AC107: 1 | AD107: 15 | AE107: 10 | AF107: 14 | AG107: Estar con mi nieta Yarelis | AI107: Stephany Decheco Vera
B108: SAN MARCOS | C108: HUARI | D108: SAN MARCOS | E108: OPAYACO/OPAYACU | F108: 099 | G108: Inicial - Jardín | H108: 1551738 | I108: 631640 | J108: EDITH CASTRO VERAMENDI | K108: EDITH CASTRO VERAMENDI | L108: Madre | M108: 38 | N108: 45833 | O108: Pre test (diagnóstico) | P108: 4 | Q108: 4 | R108: 3 | S108: 3 | T108: 5 | U108: 4 | V108: 4 | W108: 3 | X108: 5 | Y108: 5 | Z108: 5 | AA108: 4 | AB108: 5 | AC108: 5 | AD108: 14 | AE108: 14 | AF108: 18 | AG108: Me ayuda como mamá conversar con mis hijas y esposo de lo que pasa en mi familia | AI108: Stephany Decheco Vera
B109: SAN MARCOS | C109: HUARI | D109: SAN MARCOS | E109: OPAYACO/OPAYACU | F109: 099 | G109: Inicial - Jardín | H109: 1551738 | I109: 631640 | J109: VALENTINA ROJAS LOARTE | K109: VALENTINA ROJAS LOARTE | L109: Madre | M109: 42 | N109: 45833 | O109: Pre test (diagnóstico) | P109: 1 | Q109: 1 | R109: 4 | S109: 4 | T109: 5 | U109: 4 | V109: 4 | W109: 4 | X109: 5 | Y109: 5 | Z109: 5 | AA109: 1 | AB109: 5 | AC109: 5 | AD109: 17 | AE109: 15 | AF109: 18 | AG109: Tener bastante comunicación entre mi hijo y pareja y así dar solución a cualquier cosa | AI109: Stephany Decheco Vera
B110: MINA | C110: HUARI | D110: SAN PEDRO DE CHANA | E110: WISHLLAC | F110: 690 | G110: Inicial - Jardín | H110: 1675040 | I110: 759493 | J110: YANETH AGUIRRE VEGA | K110: YANETH AGUIRRE VEGA | L110: Madre | M110: 24 | N110: 45833 | O110: Pre test (diagnóstico) | P110: 5 | Q110: 5 | R110: 3 | S110: 3 | T110: 4 | U110: 5 | V110: 5 | W110: 3 | X110: 4 | Y110: 4 | Z110: 4 | AA110: 5 | AB110: 4 | AC110: 4 | AD110: 13 | AE110: 14 | AF110: 18 | AG110: Yo mesiento orgullosa porque con mi hijo yo juego diario hacemos bromas | AI110: Jackelyn Juro Dueñas
B111: MINA | C111: HUARI | D111: SAN PEDRO DE CHANA | E111: WISHLLAC | F111: 690 | G111: Inicial - Jardín | H111: 1675040 | I111: 759493 | J111: EUGENIO CASTRO OBREGÓN | K111: EUGENIO CASTRO OBREGÓN | L111: Otro | M111: 58 | N111: 45833 | O111: Pre test (diagnóstico) | P111: 1 | Q111: 1 | R111: 1 | S111: 1 | T111: 4 | U111: 4 | V111: 4 | W111: 1 | X111: 4 | Y111: 4 | Z111: 4 | AA111: 1 | AB111: 4 | AC111: 4 | AD111: 17 | AE111: 12 | AF111: 16 | AG111: Conversa con la familia, hace jugar al niño | AI111: Jackelyn Juro Dueñas
B112: MINA | C112: HUARI | D112: SAN PEDRO DE CHANA | E112: WISHLLAC | F112: 690 | G112: Inicial - Jardín | H112: 1675040 | I112: 759493 | J112: GUISELA FERNANDEZ FLORES | K112: GUISELA FERNANDEZ FLORES | L112: Madre | M112: 29 | N112: 45833 | O112: Pre test (diagnóstico) | P112: 4 | Q112: 4 | R112: 3 | S112: 3 | T112: 2 | U112: 5 | V112: 5 | W112: 3 | X112: 1 | Y112: 1 | Z112: 2 | AA112: 4 | AB112: 2 | AC112: 1 | AD112: 14 | AE112: 13 | AF112: 14 | AI112: Jackelyn Juro Dueñas
B113: MINA | C113: HUARI | D113: SAN PEDRO DE CHANA | E113: WISHLLAC | F113: 690 | G113: Inicial - Jardín | H113: 1675040 | I113: 759493 | J113: ZONIA MARGOT RIVERA CALDERÓN | K113: ZONIA MARGOT RIVERA CALDERÓN | L113: Madre | M113: 43 | N113: 45833 | O113: Pre test (diagnóstico) | P113: 4 | Q113: 4 | R113: 3 | S113: 3 | T113: 1 | U113: 5 | V113: 5 | W113: 3 | X113: 1 | Y113: 1 | Z113: 1 | AA113: 4 | AB113: 1 | AC113: 1 | AD113: 14 | AE113: 14 | AF113: 12 | AI113: Jackelyn Juro Dueñas
B114: MINA | C114: HUARI | D114: SAN PEDRO DE CHANA | E114: WISHLLAC | F114: 690 | G114: Inicial - Jardín | H114: 1675040 | I114: 759493 | J114: CLERINDA EVANGELISTA CAQUI | K114: CLERINDA EVANGELISTA CAQUI | L114: Madre | M114: 29 | N114: 45833 | O114: Pre test (diagnóstico) | P114: 4 | Q114: 4 | R114: 3 | S114: 3 | T114: 4 | U114: 3 | V114: 3 | W114: 3 | X114: 4 | Y114: 4 | Z114: 4 | AA114: 4 | AB114: 4 | AC114: 4 | AD114: 14 | AE114: 14 | AF114: 14 | AG114: Hablar con mis hijos ponernos de acuerdo de todo. | AI114: Jackelyn Juro Dueñas
B115: MINA | C115: HUARI | D115: SAN PEDRO DE CHANA | E115: WISHLLAC | F115: 690 | G115: Inicial - Jardín | H115: 1675040 | I115: 759493 | J115: YULI VANEZA HERRADA EULOGIO | K115: YULI VANEZA HERRADA EULOGIO | L115: Madre | M115: 35 | N115: 45833 | O115: Pre test (diagnóstico) | P115: 4 | Q115: 4 | R115: 3 | S115: 3 | T115: 4 | U115: 2 | V115: 2 | W115: 3 | X115: 3 | Y115: 3 | Z115: 4 | AA115: 4 | AB115: 4 | AC115: 3 | AD115: 14 | AE115: 13 | AF115: 12 | AG115: Hablar con mis familiares porque se encuentran lejos, escuchar música | AI115: Jackelyn Juro Dueñas
B116: MINA | C116: HUARI | D116: SAN PEDRO DE CHANA | E116: WISHLLAC | F116: 690 | G116: Inicial - Jardín | H116: 1675040 | I116: 759493 | J116: YANET LUZ RAMIREZ ANAYA | K116: YANET LUZ RAMIREZ ANAYA | L116: Madre | M116: 21 | N116: 45833 | O116: Pre test (diagnóstico) | P116: 4 | Q116: 4 | R116: 4 | S116: 4 | T116: 4 | U116: 4 | V116: 4 | W116: 4 | X116: 4 | Y116: 4 | Z116: 4 | AA116: 4 | AB116: 4 | AC116: 4 | AD116: 14 | AE116: 15 | AF116: 16 | AG116: A mi me ayuda a estar bien, escuchar música, estar con mi familia y mi hijo, etc. | AI116: Jackelyn Juro Dueñas
B117: MINA | C117: HUARI | D117: SAN PEDRO DE CHANA | E117: WISHLLAC | F117: 690 | G117: Inicial - Jardín | H117: 1675040 | I117: 759493 | J117: FERIOL CASTRO GARAY | K117: FERIOL CASTRO GARAY | L117: Padre | M117: 45 | N117: 45833 | O117: Pre test (diagnóstico) | P117: 1 | Q117: 1 | R117: 3 | S117: 3 | T117: 4 | U117: 4 | V117: 4 | W117: 3 | X117: 4 | Y117: 4 | Z117: 4 | AA117: 1 | AB117: 4 | AC117: 4 | AD117: 17 | AE117: 14 | AF117: 16 | AI117: Jackelyn Juro Dueñas
B118: MINA | C118: HUARI | D118: SAN PEDRO DE CHANA | E118: WISHLLAC | F118: 690 | G118: Inicial - Jardín | H118: 1675040 | I118: 759493 | J118: GUILLERMO QUISPE | K118: GUILLERMO QUISPE | L118: Padre | M118: 42 | N118: 45833 | O118: Pre test (diagnóstico) | P118: 3 | Q118: 3 | R118: 4 | S118: 4 | T118: 3 | U118: 3 | V118: 3 | W118: 4 | X118: 4 | Y118: 4 | Z118: 3 | AA118: 3 | AB118: 3 | AC118: 4 | AD118: 15 | AE118: 16 | AF118: 12 | AG118: Relacionado con mi familia a dar consejos claros y precisos con mis hijos, escuchar música, hacer deporte y conversar con mi hijo. | AI118: Jackelyn Juro Dueñas
B119: MINA | C119: HUARI | D119: SAN PEDRO DE CHANA | E119: WISHLLAC | F119: 690 | G119: Inicial - Jardín | H119: 1675040 | I119: 759493 | J119: YOLINO OBREGÓN RENTERA | K119: YOLINO OBREGÓN RENTERA | L119: Padre | M119: 27 | N119: 45833 | O119: Pre test (diagnóstico) | P119: 4 | Q119: 4 | R119: 3 | S119: 3 | T119: 4 | U119: 3 | V119: 3 | W119: 3 | X119: 4 | Y119: 4 | Z119: 4 | AA119: 4 | AB119: 4 | AC119: 4 | AD119: 14 | AE119: 14 | AF119: 14 | AG119: Conversar siempre con los hijos, darle consejos y cariño. | AI119: Jackelyn Juro Dueñas
B120: MINA | C120: HUARI | D120: SAN PEDRO DE CHANA | E120: WISHLLAC | F120: 690 | G120: Inicial - Jardín | H120: 1675040 | I120: 759493 | J120: MANESCO GARGATE OBREGÓN | K120: MANESCO GARGATE OBREGÓN | L120: Padre | M120: 40 | N120: 45833 | O120: Pre test (diagnóstico) | P120: 3 | Q120: 3 | R120: 4 | S120: 4 | T120: 4 | U120: 3 | V120: 3 | W120: 4 | X120: 4 | Y120: 4 | Z120: 4 | AA120: 3 | AB120: 4 | AC120: 4 | AD120: 15 | AE120: 15 | AF120: 14 | AG120: A mi como papá me ayuda darle consejos y hacer chiste con mi hija, conversar siempre para que te entienda más o hacerle caso. | AI120: Jackelyn Juro Dueñas
B121: MINA | C121: HUARI | D121: SAN PEDRO DE CHANA | E121: WISHLLAC | F121: 690 | G121: Inicial - Jardín | H121: 1675040 | I121: 759493 | J121: YANETH AGUIRRE VEGA | K121: YANETH AGUIRRE VEGA | L121: Madre | M121: 24 | N121: 45959 | O121: Post test (cierre) | P121: 5 | Q121: 5 | R121: 4 | S121: 4 | T121: 4 | U121: 5 | V121: 5 | W121: 4 | X121: 5 | Y121: 5 | Z121: 4 | AA121: 5 | AB121: 4 | AC121: 5 | AD121: 13 | AE121: 16 | AF121: 18 | AI121: Jackelyn Juro Dueñas
B122: MINA | C122: HUARI | D122: SAN PEDRO DE CHANA | E122: WISHLLAC | F122: 690 | G122: Inicial - Jardín | H122: 1675040 | I122: 759493 | J122: EUGENIO CASTRO OBREGÓN | K122: EUGENIO CASTRO OBREGÓN | L122: Otro | M122: 58 | N122: 45959 | O122: Post test (cierre) | P122: 4 | Q122: 4 | R122: 4 | S122: 4 | T122: 5 | U122: 4 | V122: 4 | W122: 4 | X122: 4 | Y122: 4 | Z122: 5 | AA122: 4 | AB122: 5 | AC122: 4 | AD122: 14 | AE122: 14 | AF122: 18 | AI122: Jackelyn Juro Dueñas
B123: MINA | C123: HUARI | D123: SAN PEDRO DE CHANA | E123: WISHLLAC | F123: 690 | G123: Inicial - Jardín | H123: 1675040 | I123: 759493 | J123: GUISELA FERNANDEZ FLORES | K123: GUISELA FERNANDEZ FLORES | L123: Madre | M123: 29 | N123: 45959 | O123: Post test (cierre) | P123: 5 | Q123: 5 | R123: 4 | S123: 4 | T123: 4 | U123: 5 | V123: 5 | W123: 4 | X123: 4 | Y123: 4 | Z123: 4 | AA123: 5 | AB123: 4 | AC123: 4 | AD123: 13 | AE123: 15 | AF123: 18 | AI123: Jackelyn Juro Dueñas
B124: MINA | C124: HUARI | D124: SAN PEDRO DE CHANA | E124: WISHLLAC | F124: 690 | G124: Inicial - Jardín | H124: 1675040 | I124: 759493 | J124: ZONIA MARGOT RIVERA CALDERÓN | K124: ZONIA MARGOT RIVERA CALDERÓN | L124: Madre | M124: 43 | N124: 45959 | O124: Post test (cierre) | P124: 5 | Q124: 5 | R124: 4 | S124: 4 | T124: 3 | U124: 5 | V124: 5 | W124: 4 | X124: 3 | Y124: 3 | Z124: 3 | AA124: 5 | AB124: 3 | AC124: 3 | AD124: 13 | AE124: 15 | AF124: 16 | AI124: Jackelyn Juro Dueñas
B125: MINA | C125: HUARI | D125: SAN PEDRO DE CHANA | E125: WISHLLAC | F125: 690 | G125: Inicial - Jardín | H125: 1675040 | I125: 759493 | J125: CLERINDA EVANGELISTA CAQUI | K125: CLERINDA EVANGELISTA CAQUI | L125: Madre | M125: 29 | N125: 45959 | O125: Post test (cierre) | P125: 4 | Q125: 4 | R125: 4 | S125: 4 | T125: 4 | U125: 4 | V125: 4 | W125: 4 | X125: 5 | Y125: 5 | Z125: 4 | AA125: 4 | AB125: 4 | AC125: 5 | AD125: 14 | AE125: 16 | AF125: 16 | AI125: Jackelyn Juro Dueñas
B126: MINA | C126: HUARI | D126: SAN PEDRO DE CHANA | E126: WISHLLAC | F126: 690 | G126: Inicial - Jardín | H126: 1675040 | I126: 759493 | J126: YULI VANEZA HERRADA EULOGIO | K126: YULI VANEZA HERRADA EULOGIO | L126: Madre | M126: 35 | N126: 45959 | O126: Post test (cierre) | P126: 4 | Q126: 4 | R126: 4 | S126: 4 | T126: 4 | U126: 3 | V126: 3 | W126: 4 | X126: 5 | Y126: 5 | Z126: 4 | AA126: 4 | AB126: 4 | AC126: 5 | AD126: 14 | AE126: 16 | AF126: 14 | AI126: Jackelyn Juro Dueñas
B127: MINA | C127: HUARI | D127: SAN PEDRO DE CHANA | E127: WISHLLAC | F127: 690 | G127: Inicial - Jardín | H127: 1675040 | I127: 759493 | J127: YANET LUZ RAMIREZ ANAYA | K127: YANET LUZ RAMIREZ ANAYA | L127: Madre | M127: 21 | N127: 45959 | O127: Post test (cierre) | P127: 5 | Q127: 5 | R127: 4 | S127: 4 | T127: 4 | U127: 4 | V127: 4 | W127: 4 | X127: 4 | Y127: 4 | Z127: 4 | AA127: 5 | AB127: 4 | AC127: 4 | AD127: 13 | AE127: 15 | AF127: 16 | AI127: Jackelyn Juro Dueñas
B128: MINA | C128: HUARI | D128: SAN PEDRO DE CHANA | E128: WISHLLAC | F128: 690 | G128: Inicial - Jardín | H128: 1675040 | I128: 759493 | J128: FERIOL CASTRO GARAY | K128: FERIOL CASTRO GARAY | L128: Padre | M128: 45 | N128: 45959 | O128: Post test (cierre) | P128: 5 | Q128: 5 | R128: 4 | S128: 4 | T128: 4 | U128: 5 | V128: 5 | W128: 4 | X128: 4 | Y128: 4 | Z128: 4 | AA128: 5 | AB128: 4 | AC128: 4 | AD128: 13 | AE128: 15 | AF128: 18 | AI128: Jackelyn Juro Dueñas
B129: MINA | C129: HUARI | D129: SAN PEDRO DE CHANA | E129: WISHLLAC | F129: 690 | G129: Inicial - Jardín | H129: 1675040 | I129: 759493 | J129: GUILLERMO QUISPE | K129: GUILLERMO QUISPE | L129: Padre | M129: 42 | N129: 45959 | O129: Post test (cierre) | P129: 5 | Q129: 5 | R129: 4 | S129: 4 | T129: 4 | U129: 5 | V129: 5 | W129: 4 | X129: 4 | Y129: 4 | Z129: 4 | AA129: 5 | AB129: 4 | AC129: 4 | AD129: 13 | AE129: 15 | AF129: 18 | AI129: Jackelyn Juro Dueñas
B130: MINA | C130: HUARI | D130: SAN PEDRO DE CHANA | E130: WISHLLAC | F130: 690 | G130: Inicial - Jardín | H130: 1675040 | I130: 759493 | J130: MANESCO GARGATE OBREGÓN | K130: MANESCO GARGATE OBREGÓN | L130: Padre | M130: 40 | N130: 45959 | O130: Post test (cierre) | P130: 4 | Q130: 4 | R130: 3 | S130: 3 | T130: 5 | U130: 3 | V130: 3 | W130: 3 | X130: 4 | Y130: 4 | Z130: 5 | AA130: 4 | AB130: 5 | AC130: 4 | AD130: 14 | AE130: 13 | AF130: 16 | AI130: Jackelyn Juro Dueñas
...

Sheet 🅱️Enc. Familias
H2: {=SUM(IF(H4:H1578="",0,1))} -> 181 | I2: PADRES CON NOMBRE ESCRITO IGUAL
A3: ID | B3: ='Enc. Familias'!J1 -> Apellidos y nombres | C3: =COUNTA(C4:C1578) -> 1075 | J3: MISMO TEST? | K3: LISTAR COINCIDENCIAS | L3: PUEDEN SER IGUALES? (MISMO COLEGIO, EDAD, DIFERENTE TEST, COINCIDENCIAS EN NOMBRE) | M3: ID NUEVO BASED ON NAME | O3: PROCESA NOMBRE | R3: =CONCATENATE(S5:V9) -> 233 | AB3: =COUNTA(AB4:AB1578)/2&" POR EVALUAR" -> 28 POR EVALUAR | AK3: {='Enc. Familias'!P1:AG1} -> TRUE - Cuando me enojo con mis hijos/as, me doy cuenta de cómo me siento. | AL3: FALSE - A veces me pregunto si lo que hago como mamá o papá está bien para mis hijos/as. | AM3: FALSE - Cuando estoy cansado/a o de mal humor, me cuesta tener paciencia con mis hijos/as.Cuando estoy cansado/a o de mal humor, me cuesta tener paciencia con mis hijos/as. | AN3: TRUE - Cuando algo está difícil, trato de estar tranquilo/a antes de corregir a mis hijos/as. | AO3: TRUE - Me doy cuenta cuando mi hijo/a está triste, aunque no lo diga. | AP3: TRUE - En casa hablamos sobre cómo se siente cada uno. | AQ3: TRUE - En casa decimos lo que hacemos bien y también lo que podemos mejorar. | AR3: TRUE - Cuando mi hijo/a se equivoca, le explico qué pasó y cómo puede hacerlo mejor. | AS3: TRUE - Cuando hay decisiones importantes, las conversamos entre adultos en la casa. | AT3: TRUE - En mi casa, hombres y mujeres compartimos tareas como limpiar o cuidar a los niños/as. | AU3: FALSE - En mi comunidad, se espera que las niñas ayuden más en la casa que los niños. | AV3: FALSE - A veces pienso que los hombres no deben llorar ni mostrar tristeza. | AW3: TRUE - En mi familia, no siempre hablamos sobre cómo nos sentimos, pero lo estamos intentando. | AX3: FALSE - Cuando hay reunión en la escuela, casi siempre va la mamá, aunque también hay papás interesados. | AY3: 🅱️ Autoconciencia y Autorregulación Emocional | AZ3: 🅱️ Toma de Decisiones Responsables | BA3: 🅱️ Habilidades Relacionales | BB3: ¿Qué te ayuda a ti, como mamá/papá, a estar bien?
A4: 1 | B4: {=SORT(CHOOSECOLS('Enc. Familias'!G2:O1578,2,4,6,7,-1),2,false)} -> 0360305 | C4: ZUÑIGA FLORES ANDREA | D4: Madre | E4: 26 | F4: Pre test (diagnóstico) | K4: =IFERROR(__xludf.DUMMYFUNCTION("TRIM(JOIN("" "",UNIQUE(TOCOL(ARRAYFORMULA(IF( SPLIT(C4,"" "")=TOCOL(SPLIT(C3,"" "")),SPLIT(C4,"" "")&"" "",""""))))))"),"") | L4: =IF(((G4<>"")*(I4<>"")*(K4<>"")*( J4=FALSE)*( H4=""))>=1,"EVALUAR","")&IF(L5="EVALUAR","->WITH THIS","") | M4: =IF(H4="",A4,A3) -> 1 | S4: 1 | T4: 23 | U4: 2 | V4: 3 | AA4: =IFERROR(__xludf.DUMMYFUNCTION("FILTER(B4:F1578,L4:L1578<>"""")"),"1505023") -> 1505023 | AB4: =IFERROR(__xludf.DUMMYFUNCTION("""COMPUTED_VALUE"""),"YUDITH IRMA DAMIAN VALVERDE") -> YUDITH IRMA DAMIAN VALVERDE | AC4: =IFERROR(__xludf.DUMMYFUNCTION("""COMPUTED_VALUE"""),"Madre") -> Madre | AD4: =IFERROR(__xludf.DUMMYFUNCTION("""COMPUTED_VALUE"""),30.0) -> 30 | AE4: =IFERROR(__xludf.DUMMYFUNCTION("""COMPUTED_VALUE"""),"Pre test (diagnóstico)") -> Pre test (diagnóstico) | AK4: {=SORT(UNIQUE('Enc. Familias'!P2:P1578))} -> 1 | AL4: {=SORT(UNIQUE('Enc. Familias'!Q2:Q1578))} -> 1 | AM4: {=SORT(UNIQUE('Enc. Familias'!R2:R1578))} -> 1 | AN4: {=SORT(UNIQUE('Enc. Familias'!S2:S1578))} -> 1 | AO4: {=SORT(UNIQUE('Enc. Familias'!T2:T1578))} -> 1 | AP4: {=SORT(UNIQUE('Enc. Familias'!U2:U1578))} -> 1 | AQ4: {=SORT(UNIQUE('Enc. Familias'!V2:V1578))} -> 1 | AR4: {=SORT(UNIQUE('Enc. Familias'!W2:W1578))} -> 1 | ... AX4: {=SORT(UNIQUE('Enc. Familias'!AC2:AC1578))} -> 1 | AY4: {=SORT(UNIQUE('Enc. Familias'!AG2:AG1578))} -> A conversar con mi hija, preguntar como se siente
A5: =1+A4 -> 2 | B5: 1551555 | C5: ZUBIETA CERRATE, CAROLINA | D5: Madre | E5: 39 | F5: Post test (cierre) | G5: =IF(E4=E5,"misma edad","") | H5: =IF(C5=C4,"mismo nombre","") | I5: =IF(B4=B5,"mismo colegio","") | J5: =F5=F4 -> FALSE | K5: =IFERROR(__xludf.DUMMYFUNCTION("TRIM(JOIN("" "",UNIQUE(TOCOL(ARRAYFORMULA(IF( SPLIT(C5,"" "")=TOCOL(SPLIT(C4,"" "")),SPLIT(C5,"" "")&"" "",""""))))))"),"") | L5: =IF(((G5<>"")*(I5<>"")*(K5<>"")*( J5=FALSE)*( H5=""))>=1,"EVALUAR","")&IF(L6="EVALUAR","->WITH THIS","") | M5: =IF(H5="",A5,A4) -> 2 | R5: 12 | S5: {=IF(R5:R9=S4:V4,R5:R9,"")} | AA5: =IFERROR(__xludf.DUMMYFUNCTION("""COMPUTED_VALUE"""),"1505023") -> 1505023 | AB5: =IFERROR(__xludf.DUMMYFUNCTION("""COMPUTED_VALUE"""),"YUDITH DAMIAN VALVERDE") -> YUDITH DAMIAN VALVERDE | AC5: =IFERROR(__xludf.DUMMYFUNCTION("""COMPUTED_VALUE"""),"Madre") -> Madre | AD5: =IFERROR(__xludf.DUMMYFUNCTION("""COMPUTED_VALUE"""),30.0) -> 30 | AE5: =IFERROR(__xludf.DUMMYFUNCTION("""COMPUTED_VALUE"""),"Post test (cierre)") -> Post test (cierre) | AF5: =IFERROR(__xludf.DUMMYFUNCTION("TRIM(JOIN("" "",UNIQUE(TOCOL(ARRAYFORMULA(IF( SPLIT(AB5,"" "")=TOCOL(SPLIT(AB4,"" "")),SPLIT(AB5,"" "")&"" "",""""))))))"),"YUDITH DAMIAN VALVERDE") -> YUDITH DAMIAN VALVERDE | AK5: 2 | AL5: 2 | AM5: 2 | AN5: 2 | AO5: 2 | AP5: 2 | AQ5: 2 | AR5: 2 | AS5: 2 | AT5: 2 | AU5: 1 | AV5: 2 | AW5: 2 | AX5: 2 | AY5: -
A6: =1+A5 -> 3 | B6: 1597566 | C6: ZORRILLA BAZAN BEATRIZ | D6: Madre | E6: 39 | F6: Pre test (diagnóstico) | G6: =IF(E5=E6,"misma edad","") -> misma edad | H6: =IF(C6=C5,"mismo nombre","") | I6: =IF(B5=B6,"mismo colegio","") | J6: =F6=F5 -> FALSE | K6: =IFERROR(__xludf.DUMMYFUNCTION("TRIM(JOIN("" "",UNIQUE(TOCOL(ARRAYFORMULA(IF( SPLIT(C6,"" "")=TOCOL(SPLIT(C5,"" "")),SPLIT(C6,"" "")&"" "",""""))))))"),"") | L6: =IF(((G6<>"")*(I6<>"")*(K6<>"")*( J6=FALSE)*( H6=""))>=1,"EVALUAR","")&IF(L7="EVALUAR","->WITH THIS","") | M6: =IF(H6="",A6,A5) -> 3 | R6: 2 | U6: 2 | AA6: =IFERROR(__xludf.DUMMYFUNCTION("""COMPUTED_VALUE"""),"0509711") -> 0509711 | AB6: =IFERROR(__xludf.DUMMYFUNCTION("""COMPUTED_VALUE"""),"YANIRA RAMOS GUERRA") -> YANIRA RAMOS GUERRA | AC6: =IFERROR(__xludf.DUMMYFUNCTION("""COMPUTED_VALUE"""),"Madre") -> Madre | AD6: =IFERROR(__xludf.DUMMYFUNCTION("""COMPUTED_VALUE"""),39.0) -> 39 | AE6: =IFERROR(__xludf.DUMMYFUNCTION("""COMPUTED_VALUE"""),"Pre test (diagnóstico)") -> Pre test (diagnóstico) | AF6: =IFERROR(__xludf.DUMMYFUNCTION("TRIM(JOIN("" "",UNIQUE(TOCOL(ARRAYFORMULA(IF( SPLIT(AB6,"" "")=TOCOL(SPLIT(AB5,"" "")),SPLIT(AB6,"" "")&"" "",""""))))))"),"") | AK6: 3 | AL6: 3 | AM6: 3 | AN6: 3 | AO6: 3 | AP6: 3 | AQ6: 3 | AR6: 3 | AS6: 3 | AT6: 3 | AU6: 2 | AV6: 3 | AW6: 3 | AX6: 3 | AY6: A atender a mis hijos y poder ayudarlos y calmarlos cuando esten haciendo sus berrinches
A7: =1+A6 -> 4 | B7: 1597566 | C7: ZORRILLA BAZAN BEATRIZ | D7: Madre | E7: 39 | F7: Post test (cierre) | G7: =IF(E6=E7,"misma edad","") -> misma edad | H7: =IF(C7=C6,"mismo nombre","") -> mismo nombre | I7: =IF(B6=B7,"mismo colegio","") -> mismo colegio | J7: =F7=F6 -> FALSE | K7: =IFERROR(__xludf.DUMMYFUNCTION("TRIM(JOIN("" "",UNIQUE(TOCOL(ARRAYFORMULA(IF( SPLIT(C7,"" "")=TOCOL(SPLIT(C6,"" "")),SPLIT(C7,"" "")&"" "",""""))))))"),"ZORRILLA BAZAN BEATRIZ") -> ZORRILLA BAZAN BEATRIZ | L7: =IF(((G7<>"")*(I7<>"")*(K7<>"")*( J7=FALSE)*( H7=""))>=1,"EVALUAR","")&IF(L8="EVALUAR","->WITH THIS","") | M7: =IF(H7="",A7,A6) -> 3 | R7: 3 | V7: 3 | AA7: =IFERROR(__xludf.DUMMYFUNCTION("""COMPUTED_VALUE"""),"0509711") -> 0509711 | AB7: =IFERROR(__xludf.DUMMYFUNCTION("""COMPUTED_VALUE"""),"YANINA RAMOS GUERRA") -> YANINA RAMOS GUERRA | AC7: =IFERROR(__xludf.DUMMYFUNCTION("""COMPUTED_VALUE"""),"Madre") -> Madre | AD7: =IFERROR(__xludf.DUMMYFUNCTION("""COMPUTED_VALUE"""),39.0) -> 39 | AE7: =IFERROR(__xludf.DUMMYFUNCTION("""COMPUTED_VALUE"""),"Post test (cierre)") -> Post test (cierre) | AF7: =IFERROR(__xludf.DUMMYFUNCTION("TRIM(JOIN("" "",UNIQUE(TOCOL(ARRAYFORMULA(IF( SPLIT(AB7,"" "")=TOCOL(SPLIT(AB6,"" "")),SPLIT(AB7,"" "")&"" "",""""))))))"),"RAMOS GUERRA") -> RAMOS GUERRA | AK7: 4 | AL7: 4 | AM7: 4 | AN7: 4 | AO7: 4 | AP7: 4 | AQ7: 4 | AR7: 4 | AS7: 4 | AT7: 4 | AU7: 3 | AV7: 4 | AW7: 4 | AX7: 4 | AY7: A conversar con mi familia, jugar con mis hijas y salir a distraerme al campo.
A8: =1+A7 -> 5 | B8: 0415869 | C8: ZORAIDA PADILLA JARA | D8: Madre | E8: 32 | F8: Post test (cierre) | G8: =IF(E7=E8,"misma edad","") | H8: =IF(C8=C7,"mismo nombre","") | I8: =IF(B7=B8,"mismo colegio","") | J8: =F8=F7 -> TRUE | K8: =IFERROR(__xludf.DUMMYFUNCTION("TRIM(JOIN("" "",UNIQUE(TOCOL(ARRAYFORMULA(IF( SPLIT(C8,"" "")=TOCOL(SPLIT(C7,"" "")),SPLIT(C8,"" "")&"" "",""""))))))"),"") | L8: =IF(((G8<>"")*(I8<>"")*(K8<>"")*( J8=FALSE)*( H8=""))>=1,"EVALUAR","")&IF(L9="EVALUAR","->WITH THIS","") | M8: =IF(H8="",A8,A7) -> 5 | R8: 3 | V8: 3 | AA8: =IFERROR(__xludf.DUMMYFUNCTION("""COMPUTED_VALUE"""),"0509711") -> 0509711 | AB8: =IFERROR(__xludf.DUMMYFUNCTION("""COMPUTED_VALUE"""),"WILMER RIOS DIANES") -> WILMER RIOS DIANES | AC8: =IFERROR(__xludf.DUMMYFUNCTION("""COMPUTED_VALUE"""),"Padre") -> Padre | AD8: =IFERROR(__xludf.DUMMYFUNCTION("""COMPUTED_VALUE"""),38.0) -> 38 | AE8: =IFERROR(__xludf.DUMMYFUNCTION("""COMPUTED_VALUE"""),"Pre test (diagnóstico)") -> Pre test (diagnóstico) | AF8: =IFERROR(__xludf.DUMMYFUNCTION("TRIM(JOIN("" "",UNIQUE(TOCOL(ARRAYFORMULA(IF( SPLIT(AB8,"" "")=TOCOL(SPLIT(AB7,"" "")),SPLIT(AB8,"" "")&"" "",""""))))))"),"") | AK8: 5 | AL8: 5 | AM8: 5 | AN8: 5 | AO8: 5 | AP8: 5 | AQ8: 5 | AR8: 5 | AS8: 5 | AT8: 5 | AU8: 4 | AV8: 5 | AW8: 5 | AX8: 5 | AY8: A enseñarle que tengo paciencia y manejar las emociones.
A9: =1+A8 -> 6 | B9: 1505023 | C9: ZORAIDA JESUS TRINIDAD | D9: Madre | E9: 45 | F9: Pre test (diagnóstico) | G9: =IF(E8=E9,"misma edad","") | H9: =IF(C9=C8,"mismo nombre","") | I9: =IF(B8=B9,"mismo colegio","") | J9: =F9=F8 -> FALSE | K9: =IFERROR(__xludf.DUMMYFUNCTION("TRIM(JOIN("" "",UNIQUE(TOCOL(ARRAYFORMULA(IF( SPLIT(C9,"" "")=TOCOL(SPLIT(C8,"" "")),SPLIT(C9,"" "")&"" "",""""))))))"),"ZORAIDA") -> ZORAIDA | L9: =IF(((G9<>"")*(I9<>"")*(K9<>"")*( J9=FALSE)*( H9=""))>=1,"EVALUAR","")&IF(L10="EVALUAR","->WITH THIS","") | M9: =IF(H9="",A9,A8) -> 6 | R9: 434 | AA9: =IFERROR(__xludf.DUMMYFUNCTION("""COMPUTED_VALUE"""),"0509711") -> 0509711 | AB9: =IFERROR(__xludf.DUMMYFUNCTION("""COMPUTED_VALUE"""),"WILMER RIOS CHAVEZ | ANGELICA DIAZ LLIUYA") -> WILMER RIOS CHAVEZ | ANGELICA DIAZ LLIUYA | AC9: =IFERROR(__xludf.DUMMYFUNCTION("""COMPUTED_VALUE"""),"Padre") -> Padre | AD9: =IFERROR(__xludf.DUMMYFUNCTION("""COMPUTED_VALUE"""),38.0) -> 38 | AE9: =IFERROR(__xludf.DUMMYFUNCTION("""COMPUTED_VALUE"""),"Post test (cierre)") -> Post test (cierre) | AF9: =IFERROR(__xludf.DUMMYFUNCTION("TRIM(JOIN("" "",UNIQUE(TOCOL(ARRAYFORMULA(IF( SPLIT(AB9,"" "")=TOCOL(SPLIT(AB8,"" "")),SPLIT(AB9,"" "")&"" "",""""))))))"),"WILMER RIOS") -> WILMER RIOS | AR9: 8 | AU9: 5 | AY9: A estar bien con mi familia y tomar buenas decisiones.
A10: =1+A9 -> 7 | B10: 1505023 | C10: ZORAIDA JESUS TRINIDAD | D10: Madre | E10: 45 | F10: Post test (cierre) | G10: =IF(E9=E10,"misma edad","") -> misma edad | H10: =IF(C10=C9,"mismo nombre","") -> mismo nombre | I10: =IF(B9=B10,"mismo colegio","") -> mismo colegio | J10: =F10=F9 -> FALSE | K10: =IFERROR(__xludf.DUMMYFUNCTION("TRIM(JOIN("" "",UNIQUE(TOCOL(ARRAYFORMULA(IF( SPLIT(C10,"" "")=TOCOL(SPLIT(C9,"" "")),SPLIT(C10,"" "")&"" "",""""))))))"),"ZORAIDA JESUS TRINIDAD") -> ZORAIDA JESUS TRINIDAD | L10: =IF(((G10<>"")*(I10<>"")*(K10<>"")*( J10=FALSE)*( H10=""))>=1,"EVALUAR","")&IF(L11="EVALUAR","->WITH THIS","") | M10: =IF(H10="",A10,A9) -> 6 | AA10: =IFERROR(__xludf.DUMMYFUNCTION("""COMPUTED_VALUE"""),"0509711") -> 0509711 | AB10: =IFERROR(__xludf.DUMMYFUNCTION("""COMPUTED_VALUE"""),"WAGNER FERNANDEZ AIRA | FLOR HUERTA MALLQUI") -> WAGNER FERNANDEZ AIRA | FLOR HUERTA MALLQUI | AC10: =IFERROR(__xludf.DUMMYFUNCTION("""COMPUTED_VALUE"""),"Madre") -> Madre | AD10: =IFERROR(__xludf.DUMMYFUNCTION("""COMPUTED_VALUE"""),39.0) -> 39 | AE10: =IFERROR(__xludf.DUMMYFUNCTION("""COMPUTED_VALUE"""),"Post test (cierre)") -> Post test (cierre) | AF10: =IFERROR(__xludf.DUMMYFUNCTION("TRIM(JOIN("" "",UNIQUE(TOCOL(ARRAYFORMULA(IF( SPLIT(AB10,"" "")=TOCOL(SPLIT(AB9,"" "")),SPLIT(AB10,"" "")&"" "",""""))))))"),"|") -> | | AY10: A estar bien y a ser feliz.
A11: =1+A10 -> 8 | B11: 1675040 | C11: ZONIA MARGOT RIVERA CALDERÓN | D11: Madre | E11: 43 | F11: Pre test (diagnóstico) | G11: =IF(E10=E11,"misma edad","") | H11: =IF(C11=C10,"mismo nombre","") | I11: =IF(B10=B11,"mismo colegio","") | J11: =F11=F10 -> FALSE | K11: =IFERROR(__xludf.DUMMYFUNCTION("TRIM(JOIN("" "",UNIQUE(TOCOL(ARRAYFORMULA(IF( SPLIT(C11,"" "")=TOCOL(SPLIT(C10,"" "")),SPLIT(C11,"" "")&"" "",""""))))))"),"") | L11: =IF(((G11<>"")*(I11<>"")*(K11<>"")*( J11=FALSE)*( H11=""))>=1,"EVALUAR","")&IF(L12="EVALUAR","->WITH THIS","") | M11: =IF(H11="",A11,A10) -> 8 | O11: =IFERROR(__xludf.DUMMYFUNCTION("ARRAYFORMULA(IF( TOCOL(SPLIT(C21,"" ""))=(SPLIT(C20,"" "")),TOCOL(SPLIT(C21,"" ""))&"" "",""""))"),"YUPA ") -> YUPA | P11: =IFERROR(__xludf.DUMMYFUNCTION("""COMPUTED_VALUE"""),"") | Q11: =IFERROR(__xludf.DUMMYFUNCTION("""COMPUTED_VALUE"""),"") | AA11: =IFERROR(__xludf.DUMMYFUNCTION("""COMPUTED_VALUE"""),"0509711") -> 0509711 | AB11: =IFERROR(__xludf.DUMMYFUNCTION("""COMPUTED_VALUE"""),"WAGNER FERNANDEZ AIRA") -> WAGNER FERNANDEZ AIRA | AC11: =IFERROR(__xludf.DUMMYFUNCTION("""COMPUTED_VALUE"""),"Padre") -> Padre | AD11: =IFERROR(__xludf.DUMMYFUNCTION("""COMPUTED_VALUE"""),39.0) -> 39 | AE11: =IFERROR(__xludf.DUMMYFUNCTION("""COMPUTED_VALUE"""),"Pre test (diagnóstico)") -> Pre test (diagnóstico) | AF11: =IFERROR(__xludf.DUMMYFUNCTION("TRIM(JOIN("" "",UNIQUE(TOCOL(ARRAYFORMULA(IF( SPLIT(AB11,"" "")=TOCOL(SPLIT(AB10,"" "")),SPLIT(AB11,"" "")&"" "",""""))))))"),"WAGNER FERNANDEZ AIRA") -> WAGNER FERNANDEZ AIRA | AY11: A estar de acuerdo mutuamente ambos como pareja y que nuestros hijos crezcas respetuosos y sanitos y felices
A12: =1+A11 -> 9 | B12: 1675040 | C12: ZONIA MARGOT RIVERA CALDERÓN | D12: Madre | E12: 43 | F12: Post test (cierre) | G12: =IF(E11=E12,"misma edad","") -> misma edad | H12: =IF(C12=C11,"mismo nombre","") -> mismo nombre | I12: =IF(B11=B12,"mismo colegio","") -> mismo colegio | J12: =F12=F11 -> FALSE | K12: =IFERROR(__xludf.DUMMYFUNCTION("TRIM(JOIN("" "",UNIQUE(TOCOL(ARRAYFORMULA(IF( SPLIT(C12,"" "")=TOCOL(SPLIT(C11,"" "")),SPLIT(C12,"" "")&"" "",""""))))))"),"ZONIA MARGOT RIVERA CALDERÓN") -> ZONIA MARGOT RIVERA CALDERÓN | L12: =IF(((G12<>"")*(I12<>"")*(K12<>"")*( J12=FALSE)*( H12=""))>=1,"EVALUAR","")&IF(L13="EVALUAR","->WITH THIS","") | M12: =IF(H12="",A12,A11) -> 8 | O12: =IFERROR(__xludf.DUMMYFUNCTION("""COMPUTED_VALUE"""),"") | P12: =IFERROR(__xludf.DUMMYFUNCTION("""COMPUTED_VALUE"""),"PADILLA ") -> PADILLA | Q12: =IFERROR(__xludf.DUMMYFUNCTION("""COMPUTED_VALUE"""),"") | AA12: =IFERROR(__xludf.DUMMYFUNCTION("""COMPUTED_VALUE"""),"0509711") -> 0509711 | AB12: =IFERROR(__xludf.DUMMYFUNCTION("""COMPUTED_VALUE"""),"SUSA GARAY FERNANDEZ | FRANKLYN GARAY ESPINOZA") -> SUSA GARAY FERNANDEZ | FRANKLYN GARAY ESPINOZA | AC12: =IFERROR(__xludf.DUMMYFUNCTION("""COMPUTED_VALUE"""),"Padre") -> Padre | AD12: =IFERROR(__xludf.DUMMYFUNCTION("""COMPUTED_VALUE"""),32.0) -> 32 | AE12: =IFERROR(__xludf.DUMMYFUNCTION("""COMPUTED_VALUE"""),"Post test (cierre)") -> Post test (cierre) | AF12: =IFERROR(__xludf.DUMMYFUNCTION("TRIM(JOIN("" "",UNIQUE(TOCOL(ARRAYFORMULA(IF( SPLIT(AB12,"" "")=TOCOL(SPLIT(AB11,"" "")),SPLIT(AB12,"" "")&"" "",""""))))))"),"FERNANDEZ") -> FERNANDEZ | AY12: A estar en comunicación con todos y entendernos, la comprensión, el amor, la paz.
A13: =1+A12 -> 10 | B13: 1551738 | C13: ZOIDA HIDALGO POSTOR | D13: Madre | E13: 38 | F13: Pre test (diagnóstico) | G13: =IF(E12=E13,"misma edad","") | H13: =IF(C13=C12,"mismo nombre","") | I13: =IF(B12=B13,"mismo colegio","") | J13: =F13=F12 -> FALSE | K13: =IFERROR(__xludf.DUMMYFUNCTION("TRIM(JOIN("" "",UNIQUE(TOCOL(ARRAYFORMULA(IF( SPLIT(C13,"" "")=TOCOL(SPLIT(C12,"" "")),SPLIT(C13,"" "")&"" "",""""))))))"),"") | L13: =IF(((G13<>"")*(I13<>"")*(K13<>"")*( J13=FALSE)*( H13=""))>=1,"EVALUAR","")&IF(L14="EVALUAR","->WITH THIS","") | M13: =IF(H13="",A13,A12) -> 10 | O13: =IFERROR(__xludf.DUMMYFUNCTION("""COMPUTED_VALUE"""),"") | P13: =IFERROR(__xludf.DUMMYFUNCTION("""COMPUTED_VALUE"""),"") | Q13: =IFERROR(__xludf.DUMMYFUNCTION("""COMPUTED_VALUE"""),"ELVA ") -> ELVA | AA13: =IFERROR(__xludf.DUMMYFUNCTION("""COMPUTED_VALUE"""),"0509711") -> 0509711 | AB13: =IFERROR(__xludf.DUMMYFUNCTION("""COMPUTED_VALUE"""),"SUSA GARAY FERNANDEZ") -> SUSA GARAY FERNANDEZ | AC13: =IFERROR(__xludf.DUMMYFUNCTION("""COMPUTED_VALUE"""),"Madre") -> Madre | AD13: =IFERROR(__xludf.DUMMYFUNCTION("""COMPUTED_VALUE"""),32.0) -> 32 | AE13: =IFERROR(__xludf.DUMMYFUNCTION("""COMPUTED_VALUE"""),"Pre test (diagnóstico)") -> Pre test (diagnóstico) | AF13: =IFERROR(__xludf.DUMMYFUNCTION("TRIM(JOIN("" "",UNIQUE(TOCOL(ARRAYFORMULA(IF( SPLIT(AB13,"" "")=TOCOL(SPLIT(AB12,"" "")),SPLIT(AB13,"" "")&"" "",""""))))))"),"SUSA GARAY FERNANDEZ") -> SUSA GARAY FERNANDEZ | AY13: A mi como madre de ayuda a estar bien que mi hija se encuentre bien emocionalmente, fisicamente y psicológicamente
A14: =1+A13 -> 11 | B14: 0415869 | C14: ZAROLITA SOLANO ESPIRITU | D14: Madre | E14: 33 | F14: Pre test (diagnóstico) | G14: =IF(E13=E14,"misma edad","") | H14: =IF(C14=C13,"mismo nombre","") | I14: =IF(B13=B14,"mismo colegio","") | J14: =F14=F13 -> TRUE | K14: =IFERROR(__xludf.DUMMYFUNCTION("TRIM(JOIN("" "",UNIQUE(TOCOL(ARRAYFORMULA(IF( SPLIT(C14,"" "")=TOCOL(SPLIT(C13,"" "")),SPLIT(C14,"" "")&"" "",""""))))))"),"") | L14: =IF(((G14<>"")*(I14<>"")*(K14<>"")*( J14=FALSE)*( H14=""))>=1,"EVALUAR","")&IF(L15="EVALUAR","->WITH THIS","") | M14: =IF(H14="",A14,A13) -> 11 | AA14: =IFERROR(__xludf.DUMMYFUNCTION("""COMPUTED_VALUE"""),"1551738") -> 1551738 | AB14: =IFERROR(__xludf.DUMMYFUNCTION("""COMPUTED_VALUE"""),"SANTA ANAYA PEÑA") -> SANTA ANAYA PEÑA | AC14: =IFERROR(__xludf.DUMMYFUNCTION("""COMPUTED_VALUE"""),"Otro") -> Otro | AD14: =IFERROR(__xludf.DUMMYFUNCTION("""COMPUTED_VALUE"""),52.0) -> 52 | AE14: =IFERROR(__xludf.DUMMYFUNCTION("""COMPUTED_VALUE"""),"Post test (cierre)") -> Post test (cierre) | AF14: =IFERROR(__xludf.DUMMYFUNCTION("TRIM(JOIN("" "",UNIQUE(TOCOL(ARRAYFORMULA(IF( SPLIT(AB14,"" "")=TOCOL(SPLIT(AB13,"" "")),SPLIT(AB14,"" "")&"" "",""""))))))"),"") | AY14: A mi como mi mamá me ayudó a escuchar musica a acomodar mis cosas, ver un poco de tv y jugar con mi hija y mi pareja
A15: =1+A14 -> 12 | B15: 0750026 | C15: ZAMBRANO VERAMENDI, HUGO | D15: Padre | E15: 43 | F15: Post test (cierre) | G15: =IF(E14=E15,"misma edad","") | H15: =IF(C15=C14,"mismo nombre","") | I15: =IF(B14=B15,"mismo colegio","") | J15: =F15=F14 -> FALSE | K15: =IFERROR(__xludf.DUMMYFUNCTION("TRIM(JOIN("" "",UNIQUE(TOCOL(ARRAYFORMULA(IF( SPLIT(C15,"" "")=TOCOL(SPLIT(C14,"" "")),SPLIT(C15,"" "")&"" "",""""))))))"),"") | L15: =IF(((G15<>"")*(I15<>"")*(K15<>"")*( J15=FALSE)*( H15=""))>=1,"EVALUAR","")&IF(L16="EVALUAR","->WITH THIS","") | M15: =IF(H15="",A15,A14) -> 12 | AA15: =IFERROR(__xludf.DUMMYFUNCTION("""COMPUTED_VALUE"""),"1551738") -> 1551738 | AB15: =IFERROR(__xludf.DUMMYFUNCTION("""COMPUTED_VALUE"""),"SANTA ANAYA") -> SANTA ANAYA | AC15: =IFERROR(__xludf.DUMMYFUNCTION("""COMPUTED_VALUE"""),"Otro") -> Otro | AD15: =IFERROR(__xludf.DUMMYFUNCTION("""COMPUTED_VALUE"""),52.0) -> 52 | AE15: =IFERROR(__xludf.DUMMYFUNCTION("""COMPUTED_VALUE"""),"Pre test (diagnóstico)") -> Pre test (diagnóstico) | AF15: =IFERROR(__xludf.DUMMYFUNCTION("TRIM(JOIN("" "",UNIQUE(TOCOL(ARRAYFORMULA(IF( SPLIT(AB15,"" "")=TOCOL(SPLIT(AB14,"" "")),SPLIT(AB15,"" "")&"" "",""""))))))"),"SANTA ANAYA") -> SANTA ANAYA | AY15: A mi como papá me ayuda darle consejos y hacer chiste con mi hija, conversar siempre para que te entienda más o hacerle caso.
A16: =1+A15 -> 13 | B16: 0750026 | C16: ZAMBRANO SILVERIO, EDITH | D16: Madre | F16: Post test (cierre) | G16: =IF(E15=E16,"misma edad","") | H16: =IF(C16=C15,"mismo nombre","") | I16: =IF(B15=B16,"mismo colegio","") -> mismo colegio | J16: =F16=F15 -> TRUE | K16: =IFERROR(__xludf.DUMMYFUNCTION("TRIM(JOIN("" "",UNIQUE(TOCOL(ARRAYFORMULA(IF( SPLIT(C16,"" "")=TOCOL(SPLIT(C15,"" "")),SPLIT(C16,"" "")&"" "",""""))))))"),"ZAMBRANO") -> ZAMBRANO | L16: =IF(((G16<>"")*(I16<>"")*(K16<>"")*( J16=FALSE)*( H16=""))>=1,"EVALUAR","")&IF(L17="EVALUAR","->WITH THIS","") | M16: =IF(H16="",A16,A15) -> 13 | AA16: =IFERROR(__xludf.DUMMYFUNCTION("""COMPUTED_VALUE"""),"1551738") -> 1551738 | AB16: =IFERROR(__xludf.DUMMYFUNCTION("""COMPUTED_VALUE"""),"ROSA BLAS VILLANUEVA | FELICIANO ROJAS SANCHEZ") -> ROSA BLAS VILLANUEVA | FELICIANO ROJAS SANCHEZ | AC16: =IFERROR(__xludf.DUMMYFUNCTION("""COMPUTED_VALUE"""),"Padre") -> Padre | AD16: =IFERROR(__xludf.DUMMYFUNCTION("""COMPUTED_VALUE"""),30.0) -> 30 | AE16: =IFERROR(__xludf.DUMMYFUNCTION("""COMPUTED_VALUE"""),"Post test (cierre)") -> Post test (cierre) | AF16: =IFERROR(__xludf.DUMMYFUNCTION("TRIM(JOIN("" "",UNIQUE(TOCOL(ARRAYFORMULA(IF( SPLIT(AB16,"" "")=TOCOL(SPLIT(AB15,"" "")),SPLIT(AB16,"" "")&"" "",""""))))))"),"") | AY16: A mi lo que me ayuda a estar bien como mamá es im hijo que es mi mayor motivación y felciidad entre tristezas y llantos. El es mi mayor regalo que tengo.
A17: =1+A16 -> 14 | B17: 0750026 | C17: ZAMBRANO SALINAS, BONNY | D17: Madre | E17: 32 | F17: Post test (cierre) | G17: =IF(E16=E17,"misma edad","") | H17: =IF(C17=C16,"mismo nombre","") | I17: =IF(B16=B17,"mismo colegio","") -> mismo colegio | J17: =F17=F16 -> TRUE | K17: =IFERROR(__xludf.DUMMYFUNCTION("TRIM(JOIN("" "",UNIQUE(TOCOL(ARRAYFORMULA(IF( SPLIT(C17,"" "")=TOCOL(SPLIT(C16,"" "")),SPLIT(C17,"" "")&"" "",""""))))))"),"ZAMBRANO") -> ZAMBRANO | L17: =IF(((G17<>"")*(I17<>"")*(K17<>"")*( J17=FALSE)*( H17=""))>=1,"EVALUAR","")&IF(L18="EVALUAR","->WITH THIS","") | M17: =IF(H17="",A17,A16) -> 14 | AA17: =IFERROR(__xludf.DUMMYFUNCTION("""COMPUTED_VALUE"""),"1551738") -> 1551738 | AB17: =IFERROR(__xludf.DUMMYFUNCTION("""COMPUTED_VALUE"""),"ROSA BLAS VILLANUEVA") -> ROSA BLAS VILLANUEVA | AC17: =IFERROR(__xludf.DUMMYFUNCTION("""COMPUTED_VALUE"""),"Madre") -> Madre | AD17: =IFERROR(__xludf.DUMMYFUNCTION("""COMPUTED_VALUE"""),30.0) -> 30 | AE17: =IFERROR(__xludf.DUMMYFUNCTION("""COMPUTED_VALUE"""),"Pre test (diagnóstico)") -> Pre test (diagnóstico) | AF17: =IFERROR(__xludf.DUMMYFUNCTION("TRIM(JOIN("" "",UNIQUE(TOCOL(ARRAYFORMULA(IF( SPLIT(AB17,"" "")=TOCOL(SPLIT(AB16,"" "")),SPLIT(AB17,"" "")&"" "",""""))))))"),"ROSA BLAS VILLANUEVA") -> ROSA BLAS VILLANUEVA | AY17: A mí me ayuda a estar bien cuando mi hijo llega contento y feliz, contándome lo que ha aprendido en el colegio
A18: =1+A17 -> 15 | B18: 1551738 | C18: ZAIDA MELISSA CABRERA LOARTE | D18: Madre | E18: 18 | F18: Pre test (diagnóstico) | G18: =IF(E17=E18,"misma edad","") | H18: =IF(C18=C17,"mismo nombre","") | I18: =IF(B17=B18,"mismo colegio","") | J18: =F18=F17 -> FALSE | K18: =IFERROR(__xludf.DUMMYFUNCTION("TRIM(JOIN("" "",UNIQUE(TOCOL(ARRAYFORMULA(IF( SPLIT(C18,"" "")=TOCOL(SPLIT(C17,"" "")),SPLIT(C18,"" "")&"" "",""""))))))"),"") | L18: =IF(((G18<>"")*(I18<>"")*(K18<>"")*( J18=FALSE)*( H18=""))>=1,"EVALUAR","")&IF(L19="EVALUAR","->WITH THIS","") | M18: =IF(H18="",A18,A17) -> 15 | AA18: =IFERROR(__xludf.DUMMYFUNCTION("""COMPUTED_VALUE"""),"1515246") -> 1515246 | AB18: =IFERROR(__xludf.DUMMYFUNCTION("""COMPUTED_VALUE"""),"RODOLFO AMADO CADILLO | JANETH BAÑEZ NAVARRO") -> RODOLFO AMADO CADILLO | JANETH BAÑEZ NAVARRO | AC18: =IFERROR(__xludf.DUMMYFUNCTION("""COMPUTED_VALUE"""),"Padre") -> Padre | AD18: =IFERROR(__xludf.DUMMYFUNCTION("""COMPUTED_VALUE"""),36.0) -> 36 | AE18: =IFERROR(__xludf.DUMMYFUNCTION("""COMPUTED_VALUE"""),"Post test (cierre)") -> Post test (cierre) | AF18: =IFERROR(__xludf.DUMMYFUNCTION("TRIM(JOIN("" "",UNIQUE(TOCOL(ARRAYFORMULA(IF( SPLIT(AB18,"" "")=TOCOL(SPLIT(AB17,"" "")),SPLIT(AB18,"" "")&"" "",""""))))))"),"") | AY18: A mi me ayuda a estar bien los abrazos de mi hijo y cuando mi hijo es obediente y caballero con el resto.
A19: =1+A18 -> 16 | B19: 1558782 | C19: ZACARIAS PINEDA OCAÑA | D19: Padre | E19: 39 | F19: Pre test (diagnóstico) | G19: =IF(E18=E19,"misma edad","") | H19: =IF(C19=C18,"mismo nombre","") | I19: =IF(B18=B19,"mismo colegio","") | J19: =F19=F18 -> TRUE | K19: =IFERROR(__xludf.DUMMYFUNCTION("TRIM(JOIN("" "",UNIQUE(TOCOL(ARRAYFORMULA(IF( SPLIT(C19,"" "")=TOCOL(SPLIT(C18,"" "")),SPLIT(C19,"" "")&"" "",""""))))))"),"") | L19: =IF(((G19<>"")*(I19<>"")*(K19<>"")*( J19=FALSE)*( H19=""))>=1,"EVALUAR","")&IF(L20="EVALUAR","->WITH THIS","") | M19: =IF(H19="",A19,A18) -> 16 | O19: {=UNIQUE(TOCOL(O11:Q13))} -> YUPA | AA19: =IFERROR(__xludf.DUMMYFUNCTION("""COMPUTED_VALUE"""),"1515246") -> 1515246 | AB19: =IFERROR(__xludf.DUMMYFUNCTION("""COMPUTED_VALUE"""),"RODOLFO AMADO CADILLO") -> RODOLFO AMADO CADILLO | AC19: =IFERROR(__xludf.DUMMYFUNCTION("""COMPUTED_VALUE"""),"Padre") -> Padre | AD19: =IFERROR(__xludf.DUMMYFUNCTION("""COMPUTED_VALUE"""),36.0) -> 36 | AE19: =IFERROR(__xludf.DUMMYFUNCTION("""COMPUTED_VALUE"""),"Pre test (diagnóstico)") -> Pre test (diagnóstico) | AF19: =IFERROR(__xludf.DUMMYFUNCTION("TRIM(JOIN("" "",UNIQUE(TOCOL(ARRAYFORMULA(IF( SPLIT(AB19,"" "")=TOCOL(SPLIT(AB18,"" "")),SPLIT(AB19,"" "")&"" "",""""))))))"),"RODOLFO AMADO CADILLO") -> RODOLFO AMADO CADILLO | AY19: A mi me ayuda a estar bien que mis hijos esten bien
A20: =1+A19 -> 17 | B20: 1100635 | C20: YUPA PADILLA ELVA | D20: Madre | E20: 30 | F20: Pre test (diagnóstico) | G20: =IF(E19=E20,"misma edad","") | H20: =IF(C20=C19,"mismo nombre","") | I20: =IF(B19=B20,"mismo colegio","") | J20: =F20=F19 -> TRUE | K20: =IFERROR(__xludf.DUMMYFUNCTION("TRIM(JOIN("" "",UNIQUE(TOCOL(ARRAYFORMULA(IF( SPLIT(C20,"" "")=TOCOL(SPLIT(C19,"" "")),SPLIT(C20,"" "")&"" "",""""))))))"),"") | L20: =IF(((G20<>"")*(I20<>"")*(K20<>"")*( J20=FALSE)*( H20=""))>=1,"EVALUAR","")&IF(L21="EVALUAR","->WITH THIS","") | M20: =IF(H20="",A20,A19) -> 17 | AA20: =IFERROR(__xludf.DUMMYFUNCTION("""COMPUTED_VALUE"""),"1551720") -> 1551720 | AB20: =IFERROR(__xludf.DUMMYFUNCTION("""COMPUTED_VALUE"""),"OSORIO BRIOSO ALICIA EDITHA") -> OSORIO BRIOSO ALICIA EDITHA | AC20: =IFERROR(__xludf.DUMMYFUNCTION("""COMPUTED_VALUE"""),"Madre") -> Madre | AD20: =IFERROR(__xludf.DUMMYFUNCTION("""COMPUTED_VALUE"""),39.0) -> 39 | AE20: =IFERROR(__xludf.DUMMYFUNCTION("""COMPUTED_VALUE"""),"Pre test (diagnóstico)") -> Pre test (diagnóstico) | AF20: =IFERROR(__xludf.DUMMYFUNCTION("TRIM(JOIN("" "",UNIQUE(TOCOL(ARRAYFORMULA(IF( SPLIT(AB20,"" "")=TOCOL(SPLIT(AB19,"" "")),SPLIT(AB20,"" "")&"" "",""""))))))"),"") | AY20: A mí me ayuda a estar bien ver a mi hijo feliz y que esté avanzando en su estudio sacando buenas notas
A21: =1+A20 -> 18 | B21: 1100635 | C21: YUPA PADILLA ELVA | D21: Madre | E21: 30 | F21: Post test (cierre) | G21: =IF(E20=E21,"misma edad","") -> misma edad | H21: =IF(C21=C20,"mismo nombre","") -> mismo nombre | I21: =IF(B20=B21,"mismo colegio","") -> mismo colegio | J21: =F21=F20 -> FALSE | K21: =IFERROR(__xludf.DUMMYFUNCTION("TRIM(JOIN("" "",UNIQUE(TOCOL(ARRAYFORMULA(IF( SPLIT(C21,"" "")=TOCOL(SPLIT(C20,"" "")),SPLIT(C21,"" "")&"" "",""""))))))"),"YUPA PADILLA ELVA") -> YUPA PADILLA ELVA | L21: =IF(((G21<>"")*(I21<>"")*(K21<>"")*( J21=FALSE)*( H21=""))>=1,"EVALUAR","")&IF(L22="EVALUAR","->WITH THIS","") | M21: =IF(H21="",A21,A20) -> 17 | O21: PADILLA | AA21: =IFERROR(__xludf.DUMMYFUNCTION("""COMPUTED_VALUE"""),"1551720") -> 1551720 | AB21: =IFERROR(__xludf.DUMMYFUNCTION("""COMPUTED_VALUE"""),"OSORIO BRIOSO ALICIA") -> OSORIO BRIOSO ALICIA | AC21: =IFERROR(__xludf.DUMMYFUNCTION("""COMPUTED_VALUE"""),"Madre") -> Madre | AD21: =IFERROR(__xludf.DUMMYFUNCTION("""COMPUTED_VALUE"""),39.0) -> 39 | AE21: =IFERROR(__xludf.DUMMYFUNCTION("""COMPUTED_VALUE"""),"Post test (cierre)") -> Post test (cierre) | AF21: =IFERROR(__xludf.DUMMYFUNCTION("TRIM(JOIN("" "",UNIQUE(TOCOL(ARRAYFORMULA(IF( SPLIT(AB21,"" "")=TOCOL(SPLIT(AB20,"" "")),SPLIT(AB21,"" "")&"" "",""""))))))"),"OSORIO BRIOSO ALICIA") -> OSORIO BRIOSO ALICIA | AY21: A mi me ayuda a estar bien, escuchar música, estar con mi familia y mi hijo, etc.
A22: =1+A21 -> 19 | B22: 1558782 | C22: YUPA FONSECA ANA | D22: Madre | E22: 27 | F22: Pre test (diagnóstico) | G22: =IF(E21=E22,"misma edad","") | H22: =IF(C22=C21,"mismo nombre","") | I22: =IF(B21=B22,"mismo colegio","") | J22: =F22=F21 -> FALSE | K22: =IFERROR(__xludf.DUMMYFUNCTION("TRIM(JOIN("" "",UNIQUE(TOCOL(ARRAYFORMULA(IF( SPLIT(C22,"" "")=TOCOL(SPLIT(C21,"" "")),SPLIT(C22,"" "")&"" "",""""))))))"),"YUPA") -> YUPA | L22: =IF(((G22<>"")*(I22<>"")*(K22<>"")*( J22=FALSE)*( H22=""))>=1,"EVALUAR","")&IF(L23="EVALUAR","->WITH THIS","") | M22: =IF(H22="",A22,A21) -> 19 | O22: ELVA | AA22: =IFERROR(__xludf.DUMMYFUNCTION("""COMPUTED_VALUE"""),"1042829") -> 1042829 | AB22: =IFERROR(__xludf.DUMMYFUNCTION("""COMPUTED_VALUE"""),"NURIA RUTH MINAYA PADILLA") -> NURIA RUTH MINAYA PADILLA | AC22: =IFERROR(__xludf.DUMMYFUNCTION("""COMPUTED_VALUE"""),"Madre") -> Madre | AD22: =IFERROR(__xludf.DUMMYFUNCTION("""COMPUTED_VALUE"""),36.0) -> 36 | AE22: =IFERROR(__xludf.DUMMYFUNCTION("""COMPUTED_VALUE"""),"Pre test (diagnóstico)") -> Pre test (diagnóstico) | AF22: =IFERROR(__xludf.DUMMYFUNCTION("TRIM(JOIN("" "",UNIQUE(TOCOL(ARRAYFORMULA(IF( SPLIT(AB22,"" "")=TOCOL(SPLIT(AB21,"" "")),SPLIT(AB22,"" "")&"" "",""""))))))"),"") | AY22: A mi me ayuda a que mi hijo esté protegido y feliz y se sienta que mamá está con él
A23: =1+A22 -> 20 | B23: 0415745 | C23: YULY PAMELA MUÑOZ VALENZUELA | D23: Madre | E23: 33 | F23: Post test (cierre) | G23: =IF(E22=E23,"misma edad","") | H23: =IF(C23=C22,"mismo nombre","") | I23: =IF(B22=B23,"mismo colegio","") | J23: =F23=F22 -> FALSE | K23: =IFERROR(__xludf.DUMMYFUNCTION("TRIM(JOIN("" "",UNIQUE(TOCOL(ARRAYFORMULA(IF( SPLIT(C23,"" "")=TOCOL(SPLIT(C22,"" "")),SPLIT(C23,"" "")&"" "",""""))))))"),"") | L23: =IF(((G23<>"")*(I23<>"")*(K23<>"")*( J23=FALSE)*( H23=""))>=1,"EVALUAR","")&IF(L24="EVALUAR","->WITH THIS","") | M23: =IF(H23="",A23,A22) -> 20 | AA23: =IFERROR(__xludf.DUMMYFUNCTION("""COMPUTED_VALUE"""),"1042829") -> 1042829 | AB23: =IFERROR(__xludf.DUMMYFUNCTION("""COMPUTED_VALUE"""),"NURIA MINAYA PADILLA") -> NURIA MINAYA PADILLA | AC23: =IFERROR(__xludf.DUMMYFUNCTION("""COMPUTED_VALUE"""),"Madre") -> Madre | AD23: =IFERROR(__xludf.DUMMYFUNCTION("""COMPUTED_VALUE"""),36.0) -> 36 | AE23: =IFERROR(__xludf.DUMMYFUNCTION("""COMPUTED_VALUE"""),"Post test (cierre)") -> Post test (cierre) | AF23: =IFERROR(__xludf.DUMMYFUNCTION("TRIM(JOIN("" "",UNIQUE(TOCOL(ARRAYFORMULA(IF( SPLIT(AB23,"" "")=TOCOL(SPLIT(AB22,"" "")),SPLIT(AB23,"" "")&"" "",""""))))))"),"NURIA MINAYA PADILLA") -> NURIA MINAYA PADILLA | AY23: A mí me ayuda bastante conversar, platicar en familia sobre nuestros hijos como estan o se encuentran.
A24: =1+A23 -> 21 | B24: 0415869 | C24: YULISSA MAJIPO PIZANGO | D24: Madre | E24: 24 | F24: Post test (cierre) | G24: =IF(E23=E24,"misma edad","") | H24: =IF(C24=C23,"mismo nombre","") | I24: =IF(B23=B24,"mismo colegio","") | J24: =F24=F23 -> TRUE | K24: =IFERROR(__xludf.DUMMYFUNCTION("TRIM(JOIN("" "",UNIQUE(TOCOL(ARRAYFORMULA(IF( SPLIT(C24,"" "")=TOCOL(SPLIT(C23,"" "")),SPLIT(C24,"" "")&"" "",""""))))))"),"") | L24: =IF(((G24<>"")*(I24<>"")*(K24<>"")*( J24=FALSE)*( H24=""))>=1,"EVALUAR","")&IF(L25="EVALUAR","->WITH THIS","") | M24: =IF(H24="",A24,A23) -> 21 | AA24: =IFERROR(__xludf.DUMMYFUNCTION("""COMPUTED_VALUE"""),"0509711") -> 0509711 | AB24: =IFERROR(__xludf.DUMMYFUNCTION("""COMPUTED_VALUE"""),"NAUN YESMER QUISPE UGARTE | LESLIE LISSELY VARGAS RAMIREZ") -> NAUN YESMER QUISPE UGARTE | LESLIE LISSELY VARGAS RAMIREZ | AC24: =IFERROR(__xludf.DUMMYFUNCTION("""COMPUTED_VALUE"""),"Madre") -> Madre | AD24: =IFERROR(__xludf.DUMMYFUNCTION("""COMPUTED_VALUE"""),32.0) -> 32 | AE24: =IFERROR(__xludf.DUMMYFUNCTION("""COMPUTED_VALUE"""),"Post test (cierre)") -> Post test (cierre) | AF24: =IFERROR(__xludf.DUMMYFUNCTION("TRIM(JOIN("" "",UNIQUE(TOCOL(ARRAYFORMULA(IF( SPLIT(AB24,"" "")=TOCOL(SPLIT(AB23,"" "")),SPLIT(AB24,"" "")&"" "",""""))))))"),"") | AY24: A mi me ayuda como mama a estar bien cuando mis hijos estan bien de salud y me los tratan bien en el jardin
A25: =1+A24 -> 22 | B25: 0415745 | C25: YULISA ESTACIO SALCEDO | D25: Madre | E25: 33 | F25: Pre test (diagnóstico) | G25: =IF(E24=E25,"misma edad","") | H25: =IF(C25=C24,"mismo nombre","") | I25: =IF(B24=B25,"mismo colegio","") | J25: =F25=F24 -> FALSE | K25: =IFERROR(__xludf.DUMMYFUNCTION("TRIM(JOIN("" "",UNIQUE(TOCOL(ARRAYFORMULA(IF( SPLIT(C25,"" "")=TOCOL(SPLIT(C24,"" "")),SPLIT(C25,"" "")&"" "",""""))))))"),"") | L25: =IF(((G25<>"")*(I25<>"")*(K25<>"")*( J25=FALSE)*( H25=""))>=1,"EVALUAR","")&IF(L26="EVALUAR","->WITH THIS","") | M25: =IF(H25="",A25,A24) -> 22 | AA25: =IFERROR(__xludf.DUMMYFUNCTION("""COMPUTED_VALUE"""),"0509711") -> 0509711 | AB25: =IFERROR(__xludf.DUMMYFUNCTION("""COMPUTED_VALUE"""),"NAUN YESMER QUISPE UGARTE") -> NAUN YESMER QUISPE UGARTE | AC25: =IFERROR(__xludf.DUMMYFUNCTION("""COMPUTED_VALUE"""),"Padre") -> Padre | AD25: =IFERROR(__xludf.DUMMYFUNCTION("""COMPUTED_VALUE"""),32.0) -> 32 | AE25: =IFERROR(__xludf.DUMMYFUNCTION("""COMPUTED_VALUE"""),"Pre test (diagnóstico)") -> Pre test (diagnóstico) | AF25: =IFERROR(__xludf.DUMMYFUNCTION("TRIM(JOIN("" "",UNIQUE(TOCOL(ARRAYFORMULA(IF( SPLIT(AB25,"" "")=TOCOL(SPLIT(AB24,"" "")),SPLIT(AB25,"" "")&"" "",""""))))))"),"NAUN YESMER QUISPE UGARTE") -> NAUN YESMER QUISPE UGARTE | AY25: A mi me ayuda como mamá que mi hijo tenga sus emociones y sus sentimientos que seas compartidos
A26: =1+A25 -> 23 | B26: 1675040 | C26: YULI VANEZA HERRADA EULOGIO | D26: Madre | E26: 35 | F26: Pre test (diagnóstico) | G26: =IF(E25=E26,"misma edad","") | H26: =IF(C26=C25,"mismo nombre","") | I26: =IF(B25=B26,"mismo colegio","") | J26: =F26=F25 -> TRUE | K26: =IFERROR(__xludf.DUMMYFUNCTION("TRIM(JOIN("" "",UNIQUE(TOCOL(ARRAYFORMULA(IF( SPLIT(C26,"" "")=TOCOL(SPLIT(C25,"" "")),SPLIT(C26,"" "")&"" "",""""))))))"),"") | L26: =IF(((G26<>"")*(I26<>"")*(K26<>"")*( J26=FALSE)*( H26=""))>=1,"EVALUAR","")&IF(L27="EVALUAR","->WITH THIS","") | M26: =IF(H26="",A26,A25) -> 23 | AA26: =IFERROR(__xludf.DUMMYFUNCTION("""COMPUTED_VALUE"""),"0509711") -> 0509711 | AB26: =IFERROR(__xludf.DUMMYFUNCTION("""COMPUTED_VALUE"""),"NANCY GUERRA RAMIREZ") -> NANCY GUERRA RAMIREZ | AC26: =IFERROR(__xludf.DUMMYFUNCTION("""COMPUTED_VALUE"""),"Madre") -> Madre | AD26: =IFERROR(__xludf.DUMMYFUNCTION("""COMPUTED_VALUE"""),35.0) -> 35 | AE26: =IFERROR(__xludf.DUMMYFUNCTION("""COMPUTED_VALUE"""),"Post test (cierre)") -> Post test (cierre) | AF26: =IFERROR(__xludf.DUMMYFUNCTION("TRIM(JOIN("" "",UNIQUE(TOCOL(ARRAYFORMULA(IF( SPLIT(AB26,"" "")=TOCOL(SPLIT(AB25,"" "")),SPLIT(AB26,"" "")&"" "",""""))))))"),"") | AY26: A mí me ayuda como mamá sentir bien que mi hijo llega alegre del colegio
A27: =1+A26 -> 24 | B27: 1675040 | C27: YULI VANEZA HERRADA EULOGIO | D27: Madre | E27: 35 | F27: Post test (cierre) | G27: =IF(E26=E27,"misma edad","") -> misma edad | H27: =IF(C27=C26,"mismo nombre","") -> mismo nombre | I27: =IF(B26=B27,"mismo colegio","") -> mismo colegio | J27: =F27=F26 -> FALSE | K27: =IFERROR(__xludf.DUMMYFUNCTION("TRIM(JOIN("" "",UNIQUE(TOCOL(ARRAYFORMULA(IF( SPLIT(C27,"" "")=TOCOL(SPLIT(C26,"" "")),SPLIT(C27,"" "")&"" "",""""))))))"),"YULI VANEZA HERRADA EULOGIO") -> YULI VANEZA HERRADA EULOGIO | L27: =IF(((G27<>"")*(I27<>"")*(K27<>"")*( J27=FALSE)*( H27=""))>=1,"EVALUAR","")&IF(L28="EVALUAR","->WITH THIS","") | M27: =IF(H27="",A27,A26) -> 23 | AA27: =IFERROR(__xludf.DUMMYFUNCTION("""COMPUTED_VALUE"""),"0509711") -> 0509711 | AB27: =IFERROR(__xludf.DUMMYFUNCTION("""COMPUTED_VALUE"""),"NANCY CADILLO PAREDA") -> NANCY CADILLO PAREDA | AC27: =IFERROR(__xludf.DUMMYFUNCTION("""COMPUTED_VALUE"""),"Madre") -> Madre | AD27: =IFERROR(__xludf.DUMMYFUNCTION("""COMPUTED_VALUE"""),35.0) -> 35 | AE27: =IFERROR(__xludf.DUMMYFUNCTION("""COMPUTED_VALUE"""),"Pre test (diagnóstico)") -> Pre test (diagnóstico) | AF27: =IFERROR(__xludf.DUMMYFUNCTION("TRIM(JOIN("" "",UNIQUE(TOCOL(ARRAYFORMULA(IF( SPLIT(AB27,"" "")=TOCOL(SPLIT(AB26,"" "")),SPLIT(AB27,"" "")&"" "",""""))))))"),"NANCY") -> NANCY | AY27: A mi me ayuda como mamá, ver crecer a mi hija y tener a mi familia unida
A28: =1+A27 -> 25 | B28: 1505023 | C28: YUDITH IRMA DAMIAN VALVERDE | D28: Madre | E28: 30 | F28: Pre test (diagnóstico) | G28: =IF(E27=E28,"misma edad","") | H28: =IF(C28=C27,"mismo nombre","") | I28: =IF(B27=B28,"mismo colegio","") | J28: =F28=F27 -> FALSE | K28: =IFERROR(__xludf.DUMMYFUNCTION("TRIM(JOIN("" "",UNIQUE(TOCOL(ARRAYFORMULA(IF( SPLIT(C28,"" "")=TOCOL(SPLIT(C27,"" "")),SPLIT(C28,"" "")&"" "",""""))))))"),"") | L28: =IF(((G28<>"")*(I28<>"")*(K28<>"")*( J28=FALSE)*( H28=""))>=1,"EVALUAR","")&IF(L29="EVALUAR","->WITH THIS","") -> ->WITH THIS | M28: =IF(H28="",A28,A27) -> 25 | AA28: =IFERROR(__xludf.DUMMYFUNCTION("""COMPUTED_VALUE"""),"0509711") -> 0509711 | AB28: =IFERROR(__xludf.DUMMYFUNCTION("""COMPUTED_VALUE"""),"MIGUEL CHAVEZ DAVILA | LIDIA MALLQUI ARAUJO") -> MIGUEL CHAVEZ DAVILA | LIDIA MALLQUI ARAUJO | AC28: =IFERROR(__xludf.DUMMYFUNCTION("""COMPUTED_VALUE"""),"Padre") -> Padre | AD28: =IFERROR(__xludf.DUMMYFUNCTION("""COMPUTED_VALUE"""),32.0) -> 32 | AE28: =IFERROR(__xludf.DUMMYFUNCTION("""COMPUTED_VALUE"""),"Post test (cierre)") -> Post test (cierre) | AF28: =IFERROR(__xludf.DUMMYFUNCTION("TRIM(JOIN("" "",UNIQUE(TOCOL(ARRAYFORMULA(IF( SPLIT(AB28,"" "")=TOCOL(SPLIT(AB27,"" "")),SPLIT(AB28,"" "")&"" "",""""))))))"),"") | AY28: A mi me ayuda conversar con mi hijo y ser empatica, ayudar las cosas que puede hacerle feliz, siempre estar con el ayudando en lo que necesite.
A29: =1+A28 -> 26 | B29: 1505023 | C29: YUDITH DAMIAN VALVERDE | D29: Madre | E29: 30 | F29: Post test (cierre) | G29: =IF(E28=E29,"misma edad","") -> misma edad | H29: =IF(C29=C28,"mismo nombre","") | I29: =IF(B28=B29,"mismo colegio","") -> mismo colegio | J29: =F29=F28 -> FALSE | K29: =IFERROR(__xludf.DUMMYFUNCTION("TRIM(JOIN("" "",UNIQUE(TOCOL(ARRAYFORMULA(IF( SPLIT(C29,"" "")=TOCOL(SPLIT(C28,"" "")),SPLIT(C29,"" "")&"" "",""""))))))"),"YUDITH DAMIAN VALVERDE") -> YUDITH DAMIAN VALVERDE | L29: =IF(((G29<>"")*(I29<>"")*(K29<>"")*( J29=FALSE)*( H29=""))>=1,"EVALUAR","")&IF(L30="EVALUAR","->WITH THIS","") -> EVALUAR | M29: =IF(H29="",A29,A28) -> 26 | AA29: =IFERROR(__xludf.DUMMYFUNCTION("""COMPUTED_VALUE"""),"0509711") -> 0509711 | AB29: =IFERROR(__xludf.DUMMYFUNCTION("""COMPUTED_VALUE"""),"MIGUEL CHAVEZ DAVILA") -> MIGUEL CHAVEZ DAVILA | AC29: =IFERROR(__xludf.DUMMYFUNCTION("""COMPUTED_VALUE"""),"Padre") -> Padre | AD29: =IFERROR(__xludf.DUMMYFUNCTION("""COMPUTED_VALUE"""),32.0) -> 32 | AE29: =IFERROR(__xludf.DUMMYFUNCTION("""COMPUTED_VALUE"""),"Pre test (diagnóstico)") -> Pre test (diagnóstico) | AF29: =IFERROR(__xludf.DUMMYFUNCTION("TRIM(JOIN("" "",UNIQUE(TOCOL(ARRAYFORMULA(IF( SPLIT(AB29,"" "")=TOCOL(SPLIT(AB28,"" "")),SPLIT(AB29,"" "")&"" "",""""))))))"),"MIGUEL CHAVEZ DAVILA") -> MIGUEL CHAVEZ DAVILA | AY29: A mí me ayuda cuando mi hijo es obediente, que le guste el estudio y que sea puntual en su estudio.
A30: =1+A29 -> 27 | B30: 1645506 | C30: YOVANA RAMIREZ ROSALES | D30: Madre | E30: 36 | F30: Pre test (diagnóstico) | G30: =IF(E29=E30,"misma edad","") | H30: =IF(C30=C29,"mismo nombre","") | I30: =IF(B29=B30,"mismo colegio","") | J30: =F30=F29 -> FALSE | K30: =IFERROR(__xludf.DUMMYFUNCTION("TRIM(JOIN("" "",UNIQUE(TOCOL(ARRAYFORMULA(IF( SPLIT(C30,"" "")=TOCOL(SPLIT(C29,"" "")),SPLIT(C30,"" "")&"" "",""""))))))"),"") | L30: =IF(((G30<>"")*(I30<>"")*(K30<>"")*( J30=FALSE)*( H30=""))>=1,"EVALUAR","")&IF(L31="EVALUAR","->WITH THIS","") | M30: =IF(H30="",A30,A29) -> 27 | AA30: =IFERROR(__xludf.DUMMYFUNCTION("""COMPUTED_VALUE"""),"1515246") -> 1515246 | AB30: =IFERROR(__xludf.DUMMYFUNCTION("""COMPUTED_VALUE"""),"MARÍA PAUCAR DAMIAN | NESTOR ELFRIN ARCE MEDINA") -> MARÍA PAUCAR DAMIAN | NESTOR ELFRIN ARCE MEDINA | AC30: =IFERROR(__xludf.DUMMYFUNCTION("""COMPUTED_VALUE"""),"Madre") -> Madre | AD30: =IFERROR(__xludf.DUMMYFUNCTION("""COMPUTED_VALUE"""),46.0) -> 46 | AE30: =IFERROR(__xludf.DUMMYFUNCTION("""COMPUTED_VALUE"""),"Post test (cierre)") -> Post test (cierre) | AF30: =IFERROR(__xludf.DUMMYFUNCTION("TRIM(JOIN("" "",UNIQUE(TOCOL(ARRAYFORMULA(IF( SPLIT(AB30,"" "")=TOCOL(SPLIT(AB29,"" "")),SPLIT(AB30,"" "")&"" "",""""))))))"),"") | AY30: A mí me ayuda la comunicación constante de como nos sentimos, así tomar decisiones las más correctas en la educación de mis hijas.
A31: =1+A30 -> 28 | B31: 1645506 | C31: YOVANA RAMIREZ ROSALES | D31: Madre | E31: 36 | F31: Post test (cierre) | G31: =IF(E30=E31,"misma edad","") -> misma edad | H31: =IF(C31=C30,"mismo nombre","") -> mismo nombre | I31: =IF(B30=B31,"mismo colegio","") -> mismo colegio | J31: =F31=F30 -> FALSE | K31: =IFERROR(__xludf.DUMMYFUNCTION("TRIM(JOIN("" "",UNIQUE(TOCOL(ARRAYFORMULA(IF( SPLIT(C31,"" "")=TOCOL(SPLIT(C30,"" "")),SPLIT(C31,"" "")&"" "",""""))))))"),"YOVANA RAMIREZ ROSALES") -> YOVANA RAMIREZ ROSALES | L31: =IF(((G31<>"")*(I31<>"")*(K31<>"")*( J31=FALSE)*( H31=""))>=1,"EVALUAR","")&IF(L32="EVALUAR","->WITH THIS","") | M31: =IF(H31="",A31,A30) -> 27 | AA31: =IFERROR(__xludf.DUMMYFUNCTION("""COMPUTED_VALUE"""),"1515246") -> 1515246 | AB31: =IFERROR(__xludf.DUMMYFUNCTION("""COMPUTED_VALUE"""),"MARÍA PAUCAR DAMIAN") -> MARÍA PAUCAR DAMIAN | AC31: =IFERROR(__xludf.DUMMYFUNCTION("""COMPUTED_VALUE"""),"Madre") -> Madre | AD31: =IFERROR(__xludf.DUMMYFUNCTION("""COMPUTED_VALUE"""),46.0) -> 46 | AE31: =IFERROR(__xludf.DUMMYFUNCTION("""COMPUTED_VALUE"""),"Pre test (diagnóstico)") -> Pre test (diagnóstico) | AF31: =IFERROR(__xludf.DUMMYFUNCTION("TRIM(JOIN("" "",UNIQUE(TOCOL(ARRAYFORMULA(IF( SPLIT(AB31,"" "")=TOCOL(SPLIT(AB30,"" "")),SPLIT(AB31,"" "")&"" "",""""))))))"),"MARÍA PAUCAR DAMIAN") -> MARÍA PAUCAR DAMIAN | AY31: A mí me ayuda mi hija, que se sienta feliz tanto en mi casa y con sus compañeros, y me encanta las cosas que aprende
A32: =1+A31 -> 29 | B32: 1042829 | C32: YOUI TADEO GAMARRA | D32: Madre | F32: Pre test (diagnóstico) | G32: =IF(E31=E32,"misma edad","") | H32: =IF(C32=C31,"mismo nombre","") | I32: =IF(B31=B32,"mismo colegio","") | J32: =F32=F31 -> FALSE | K32: =IFERROR(__xludf.DUMMYFUNCTION("TRIM(JOIN("" "",UNIQUE(TOCOL(ARRAYFORMULA(IF( SPLIT(C32,"" "")=TOCOL(SPLIT(C31,"" "")),SPLIT(C32,"" "")&"" "",""""))))))"),"") | L32: =IF(((G32<>"")*(I32<>"")*(K32<>"")*( J32=FALSE)*( H32=""))>=1,"EVALUAR","")&IF(L33="EVALUAR","->WITH THIS","") | M32: =IF(H32="",A32,A31) -> 29 | AA32: =IFERROR(__xludf.DUMMYFUNCTION("""COMPUTED_VALUE"""),"0415869") -> 0415869 | AB32: =IFERROR(__xludf.DUMMYFUNCTION("""COMPUTED_VALUE"""),"JUDITH HERRERA PADILLA") -> JUDITH HERRERA PADILLA | AC32: =IFERROR(__xludf.DUMMYFUNCTION("""COMPUTED_VALUE"""),"Madre") -> Madre | AD32: =IFERROR(__xludf.DUMMYFUNCTION("""COMPUTED_VALUE"""),37.0) -> 37 | AE32: =IFERROR(__xludf.DUMMYFUNCTION("""COMPUTED_VALUE"""),"Post test (cierre)") -> Post test (cierre) | AF32: =IFERROR(__xludf.DUMMYFUNCTION("TRIM(JOIN("" "",UNIQUE(TOCOL(ARRAYFORMULA(IF( SPLIT(AB32,"" "")=TOCOL(SPLIT(AB31,"" "")),SPLIT(AB32,"" "")&"" "",""""))))))"),"") | AY32: A mi me ayuda que mi familia este unida y hablarle mi pareja y yo a mi hijo sobre diferentes valores
A33: =1+A32 -> 30 | B33: 1551738 | C33: YOMIRA HUAYTA VARGAS | D33: Madre | E33: 29 | F33: Pre test (diagnóstico) | G33: =IF(E32=E33,"misma edad","") | H33: =IF(C33=C32,"mismo nombre","") | I33: =IF(B32=B33,"mismo colegio","") | J33: =F33=F32 -> TRUE | K33: =IFERROR(__xludf.DUMMYFUNCTION("TRIM(JOIN("" "",UNIQUE(TOCOL(ARRAYFORMULA(IF( SPLIT(C33,"" "")=TOCOL(SPLIT(C32,"" "")),SPLIT(C33,"" "")&"" "",""""))))))"),"") | L33: =IF(((G33<>"")*(I33<>"")*(K33<>"")*( J33=FALSE)*( H33=""))>=1,"EVALUAR","")&IF(L34="EVALUAR","->WITH THIS","") | M33: =IF(H33="",A33,A32) -> 30 | AA33: =IFERROR(__xludf.DUMMYFUNCTION("""COMPUTED_VALUE"""),"0415869") -> 0415869 | AB33: =IFERROR(__xludf.DUMMYFUNCTION("""COMPUTED_VALUE"""),"JUDITH HERRERA") -> JUDITH HERRERA | AC33: =IFERROR(__xludf.DUMMYFUNCTION("""COMPUTED_VALUE"""),"Madre") -> Madre | AD33: =IFERROR(__xludf.DUMMYFUNCTION("""COMPUTED_VALUE"""),37.0) -> 37 | AE33: =IFERROR(__xludf.DUMMYFUNCTION("""COMPUTED_VALUE"""),"Pre test (diagnóstico)") -> Pre test (diagnóstico) | AF33: =IFERROR(__xludf.DUMMYFUNCTION("TRIM(JOIN("" "",UNIQUE(TOCOL(ARRAYFORMULA(IF( SPLIT(AB33,"" "")=TOCOL(SPLIT(AB32,"" "")),SPLIT(AB33,"" "")&"" "",""""))))))"),"JUDITH HERRERA") -> JUDITH HERRERA | AY33: A mí me ayuda que mi hija llegue contenta a la casa y sea feliz
A34: =1+A33 -> 31 | B34: 1551738 | C34: YOMIRA HUAYTA VARGAS | D34: Madre | E34: 29 | F34: Post test (cierre) | G34: =IF(E33=E34,"misma edad","") -> misma edad | H34: =IF(C34=C33,"mismo nombre","") -> mismo nombre | I34: =IF(B33=B34,"mismo colegio","") -> mismo colegio | J34: =F34=F33 -> FALSE | K34: =IFERROR(__xludf.DUMMYFUNCTION("TRIM(JOIN("" "",UNIQUE(TOCOL(ARRAYFORMULA(IF( SPLIT(C34,"" "")=TOCOL(SPLIT(C33,"" "")),SPLIT(C34,"" "")&"" "",""""))))))"),"YOMIRA HUAYTA VARGAS") -> YOMIRA HUAYTA VARGAS | L34: =IF(((G34<>"")*(I34<>"")*(K34<>"")*( J34=FALSE)*( H34=""))>=1,"EVALUAR","")&IF(L35="EVALUAR","->WITH THIS","") | M34: =IF(H34="",A34,A33) -> 30 | AA34: =IFERROR(__xludf.DUMMYFUNCTION("""COMPUTED_VALUE"""),"0509711") -> 0509711 | AB34: =IFERROR(__xludf.DUMMYFUNCTION("""COMPUTED_VALUE"""),"JUAN DAVID QUISPE VARGAS | CLARA RIOS CHAVEZ") -> JUAN DAVID QUISPE VARGAS | CLARA RIOS CHAVEZ | AC34: =IFERROR(__xludf.DUMMYFUNCTION("""COMPUTED_VALUE"""),"Madre") -> Madre | AD34: =IFERROR(__xludf.DUMMYFUNCTION("""COMPUTED_VALUE"""),32.0) -> 32 | AE34: =IFERROR(__xludf.DUMMYFUNCTION("""COMPUTED_VALUE"""),"Post test (cierre)") -> Post test (cierre) | AF34: =IFERROR(__xludf.DUMMYFUNCTION("TRIM(JOIN("" "",UNIQUE(TOCOL(ARRAYFORMULA(IF( SPLIT(AB34,"" "")=TOCOL(SPLIT(AB33,"" "")),SPLIT(AB34,"" "")&"" "",""""))))))"),"") | AY34: A mí me ayuda que mi hijita no llore en su escuela, lo malo es que a veces sus compañeros le sacan sangre a mi hijita y luego me dicen que está enferma.
A35: =1+A34 -> 32 | B35: 1675040 | C35: YOLINO OBREGÓN RENTERA | D35: Padre | E35: 27 | F35: Pre test (diagnóstico) | G35: =IF(E34=E35,"misma edad","") | H35: =IF(C35=C34,"mismo nombre","") | I35: =IF(B34=B35,"mismo colegio","") | J35: =F35=F34 -> FALSE | K35: =IFERROR(__xludf.DUMMYFUNCTION("TRIM(JOIN("" "",UNIQUE(TOCOL(ARRAYFORMULA(IF( SPLIT(C35,"" "")=TOCOL(SPLIT(C34,"" "")),SPLIT(C35,"" "")&"" "",""""))))))"),"") | L35: =IF(((G35<>"")*(I35<>"")*(K35<>"")*( J35=FALSE)*( H35=""))>=1,"EVALUAR","")&IF(L36="EVALUAR","->WITH THIS","") | M35: =IF(H35="",A35,A34) -> 32 | AA35: =IFERROR(__xludf.DUMMYFUNCTION("""COMPUTED_VALUE"""),"0509711") -> 0509711 | AB35: =IFERROR(__xludf.DUMMYFUNCTION("""COMPUTED_VALUE"""),"JUAN DAVID QUISPE VARGAS") -> JUAN DAVID QUISPE VARGAS | AC35: =IFERROR(__xludf.DUMMYFUNCTION("""COMPUTED_VALUE"""),"Padre") -> Padre | AD35: =IFERROR(__xludf.DUMMYFUNCTION("""COMPUTED_VALUE"""),32.0) -> 32 | AE35: =IFERROR(__xludf.DUMMYFUNCTION("""COMPUTED_VALUE"""),"Pre test (diagnóstico)") -> Pre test (diagnóstico) | AF35: =IFERROR(__xludf.DUMMYFUNCTION("TRIM(JOIN("" "",UNIQUE(TOCOL(ARRAYFORMULA(IF( SPLIT(AB35,"" "")=TOCOL(SPLIT(AB34,"" "")),SPLIT(AB35,"" "")&"" "",""""))))))"),"JUAN DAVID QUISPE VARGAS") -> JUAN DAVID QUISPE VARGAS | AY35: A mí me ayuda que mis hijos ayuden en casa y trabajar en equipo
A36: =1+A35 -> 33 | B36: 1675024 | C36: YOLANDA SUAREZ HUERTA | D36: Madre | E36: 33 | F36: Post test (cierre) | G36: =IF(E35=E36,"misma edad","") | H36: =IF(C36=C35,"mismo nombre","") | I36: =IF(B35=B36,"mismo colegio","") | J36: =F36=F35 -> FALSE | K36: =IFERROR(__xludf.DUMMYFUNCTION("TRIM(JOIN("" "",UNIQUE(TOCOL(ARRAYFORMULA(IF( SPLIT(C36,"" "")=TOCOL(SPLIT(C35,"" "")),SPLIT(C36,"" "")&"" "",""""))))))"),"") | L36: =IF(((G36<>"")*(I36<>"")*(K36<>"")*( J36=FALSE)*( H36=""))>=1,"EVALUAR","")&IF(L37="EVALUAR","->WITH THIS","") | M36: =IF(H36="",A36,A35) -> 33 | AA36: =IFERROR(__xludf.DUMMYFUNCTION("""COMPUTED_VALUE"""),"0415869") -> 0415869 | AB36: =IFERROR(__xludf.DUMMYFUNCTION("""COMPUTED_VALUE"""),"JEYSI VALVERDE GREGORIO") -> JEYSI VALVERDE GREGORIO | AC36: =IFERROR(__xludf.DUMMYFUNCTION("""COMPUTED_VALUE"""),"Madre") -> Madre | AD36: =IFERROR(__xludf.DUMMYFUNCTION("""COMPUTED_VALUE"""),31.0) -> 31 | AE36: =IFERROR(__xludf.DUMMYFUNCTION("""COMPUTED_VALUE"""),"Pre test (diagnóstico)") -> Pre test (diagnóstico) | AF36: =IFERROR(__xludf.DUMMYFUNCTION("TRIM(JOIN("" "",UNIQUE(TOCOL(ARRAYFORMULA(IF( SPLIT(AB36,"" "")=TOCOL(SPLIT(AB35,"" "")),SPLIT(AB36,"" "")&"" "",""""))))))"),"") | AY36: A mí me ayuda, como mamá que mi hijo crezca feliz, sano de salud, y ayudar en su crecimiento y en su educación y vivir felices juntos en armonía en familia.
A37: =1+A36 -> 34 | B37: 1551753 | C37: YOLANDA CHAVEZ DOMINGUEZ | D37: Madre | E37: 25 | F37: Post test (cierre) | G37: =IF(E36=E37,"misma edad","") | H37: =IF(C37=C36,"mismo nombre","") | I37: =IF(B36=B37,"mismo colegio","") | J37: =F37=F36 -> TRUE | K37: =IFERROR(__xludf.DUMMYFUNCTION("TRIM(JOIN("" "",UNIQUE(TOCOL(ARRAYFORMULA(IF( SPLIT(C37,"" "")=TOCOL(SPLIT(C36,"" "")),SPLIT(C37,"" "")&"" "",""""))))))"),"YOLANDA") -> YOLANDA | L37: =IF(((G37<>"")*(I37<>"")*(K37<>"")*( J37=FALSE)*( H37=""))>=1,"EVALUAR","")&IF(L38="EVALUAR","->WITH THIS","") | M37: =IF(H37="",A37,A36) -> 34 | AA37: =IFERROR(__xludf.DUMMYFUNCTION("""COMPUTED_VALUE"""),"0415869") -> 0415869 | AB37: =IFERROR(__xludf.DUMMYFUNCTION("""COMPUTED_VALUE"""),"JEYDI VALVERDE GREGORIO") -> JEYDI VALVERDE GREGORIO | AC37: =IFERROR(__xludf.DUMMYFUNCTION("""COMPUTED_VALUE"""),"Madre") -> Madre | AD37: =IFERROR(__xludf.DUMMYFUNCTION("""COMPUTED_VALUE"""),31.0) -> 31 | AE37: =IFERROR(__xludf.DUMMYFUNCTION("""COMPUTED_VALUE"""),"Post test (cierre)") -> Post test (cierre) | AF37: =IFERROR(__xludf.DUMMYFUNCTION("TRIM(JOIN("" "",UNIQUE(TOCOL(ARRAYFORMULA(IF( SPLIT(AB37,"" "")=TOCOL(SPLIT(AB36,"" "")),SPLIT(AB37,"" "")&"" "",""""))))))"),"VALVERDE GREGORIO") -> VALVERDE GREGORIO | AY37: A mí me encanta cuando llega mi hijo feliz y me cuenta lo que hizo en la escuela
A38: =1+A37 -> 35 | B38: 0509711 | C38: YISSELA TICLO GUERRA | D38: Madre | E38: 25 | F38: Pre test (diagnóstico) | G38: =IF(E37=E38,"misma edad","") -> misma edad | H38: =IF(C38=C37,"mismo nombre","") | I38: =IF(B37=B38,"mismo colegio","") | J38: =F38=F37 -> FALSE | K38: =IFERROR(__xludf.DUMMYFUNCTION("TRIM(JOIN("" "",UNIQUE(TOCOL(ARRAYFORMULA(IF( SPLIT(C38,"" "")=TOCOL(SPLIT(C37,"" "")),SPLIT(C38,"" "")&"" "",""""))))))"),"") | L38: =IF(((G38<>"")*(I38<>"")*(K38<>"")*( J38=FALSE)*( H38=""))>=1,"EVALUAR","")&IF(L39="EVALUAR","->WITH THIS","") | M38: =IF(H38="",A38,A37) -> 35 | AA38: =IFERROR(__xludf.DUMMYFUNCTION("""COMPUTED_VALUE"""),"1675032") -> 1675032 | AB38: =IFERROR(__xludf.DUMMYFUNCTION("""COMPUTED_VALUE"""),"HUERTA OBREGON MELVA VALERIANA") -> HUERTA OBREGON MELVA VALERIANA | AC38: =IFERROR(__xludf.DUMMYFUNCTION("""COMPUTED_VALUE"""),"Madre") -> Madre | AD38: =IFERROR(__xludf.DUMMYFUNCTION("""COMPUTED_VALUE"""),26.0) -> 26 | AE38: =IFERROR(__xludf.DUMMYFUNCTION("""COMPUTED_VALUE"""),"Pre test (diagnóstico)") -> Pre test (diagnóstico) | AF38: =IFERROR(__xludf.DUMMYFUNCTION("TRIM(JOIN("" "",UNIQUE(TOCOL(ARRAYFORMULA(IF( SPLIT(AB38,"" "")=TOCOL(SPLIT(AB37,"" "")),SPLIT(AB38,"" "")&"" "",""""))))))"),"") | AY38: A mí me gusta cuando mi hijo me cuenta lo que hizo en el colegio
A39: =1+A38 -> 36 | B39: 0509711 | C39: YISSELA TICLO GUERRA | D39: Madre | E39: 25 | F39: Post test (cierre) | G39: =IF(E38=E39,"misma edad","") -> misma edad | H39: =IF(C39=C38,"mismo nombre","") -> mismo nombre | I39: =IF(B38=B39,"mismo colegio","") -> mismo colegio | J39: =F39=F38 -> FALSE | K39: =IFERROR(__xludf.DUMMYFUNCTION("TRIM(JOIN("" "",UNIQUE(TOCOL(ARRAYFORMULA(IF( SPLIT(C39,"" "")=TOCOL(SPLIT(C38,"" "")),SPLIT(C39,"" "")&"" "",""""))))))"),"YISSELA TICLO GUERRA") -> YISSELA TICLO GUERRA | L39: =IF(((G39<>"")*(I39<>"")*(K39<>"")*( J39=FALSE)*( H39=""))>=1,"EVALUAR","")&IF(L40="EVALUAR","->WITH THIS","") | M39: =IF(H39="",A39,A38) -> 35 | AA39: =IFERROR(__xludf.DUMMYFUNCTION("""COMPUTED_VALUE"""),"1675032") -> 1675032 | AB39: =IFERROR(__xludf.DUMMYFUNCTION("""COMPUTED_VALUE"""),"HUERTA OBREGON MELVA") -> HUERTA OBREGON MELVA | AC39: =IFERROR(__xludf.DUMMYFUNCTION("""COMPUTED_VALUE"""),"Madre") -> Madre | AD39: =IFERROR(__xludf.DUMMYFUNCTION("""COMPUTED_VALUE"""),26.0) -> 26 | AE39: =IFERROR(__xludf.DUMMYFUNCTION("""COMPUTED_VALUE"""),"Post test (cierre)") -> Post test (cierre) | AF39: =IFERROR(__xludf.DUMMYFUNCTION("TRIM(JOIN("" "",UNIQUE(TOCOL(ARRAYFORMULA(IF( SPLIT(AB39,"" "")=TOCOL(SPLIT(AB38,"" "")),SPLIT(AB39,"" "")&"" "",""""))))))"),"HUERTA OBREGON MELVA") -> HUERTA OBREGON MELVA | AY39: A mi me gusta escuchar musica y hablar con mis amigas
A40: =1+A39 -> 37 | B40: 1551738 | C40: YENY ROJAS BAZAM | D40: Madre | E40: 30 | F40: Pre test (diagnóstico) | G40: =IF(E39=E40,"misma edad","") | H40: =IF(C40=C39,"mismo nombre","") | I40: =IF(B39=B40,"mismo colegio","") | J40: =F40=F39 -> FALSE | K40: =IFERROR(__xludf.DUMMYFUNCTION("TRIM(JOIN("" "",UNIQUE(TOCOL(ARRAYFORMULA(IF( SPLIT(C40,"" "")=TOCOL(SPLIT(C39,"" "")),SPLIT(C40,"" "")&"" "",""""))))))"),"") | L40: =IF(((G40<>"")*(I40<>"")*(K40<>"")*( J40=FALSE)*( H40=""))>=1,"EVALUAR","")&IF(L41="EVALUAR","->WITH THIS","") | M40: =IF(H40="",A40,A39) -> 37 | AA40: =IFERROR(__xludf.DUMMYFUNCTION("""COMPUTED_VALUE"""),"0469999") -> 0469999 | AB40: =IFERROR(__xludf.DUMMYFUNCTION("""COMPUTED_VALUE"""),"HERRERA SIPAN, AISSA NAYSHA") -> HERRERA SIPAN, AISSA NAYSHA | AC40: =IFERROR(__xludf.DUMMYFUNCTION("""COMPUTED_VALUE"""),"Madre") -> Madre | AD40: =IFERROR(__xludf.DUMMYFUNCTION("""COMPUTED_VALUE"""),27.0) -> 27 | AE40: =IFERROR(__xludf.DUMMYFUNCTION("""COMPUTED_VALUE"""),"Post test (cierre)") -> Post test (cierre) | AF40: =IFERROR(__xludf.DUMMYFUNCTION("TRIM(JOIN("" "",UNIQUE(TOCOL(ARRAYFORMULA(IF( SPLIT(AB40,"" "")=TOCOL(SPLIT(AB39,"" "")),SPLIT(AB40,"" "")&"" "",""""))))))"),"") | AY40: A mí me gusta estar bien con mi familia, estar bien conmigo misma, me ayuda a dialogar con mi hijo y saber tratarlo bien y vivir en paz y con amor.
A41: =1+A40 -> 38 | B41: 1551738 | C41: YENY ROJAS BAZAM | D41: Madre | E41: 30 | F41: Post test (cierre) | G41: =IF(E40=E41,"misma edad","") -> misma edad | H41: =IF(C41=C40,"mismo nombre","") -> mismo nombre | I41: =IF(B40=B41,"mismo colegio","") -> mismo colegio | J41: =F41=F40 -> FALSE | K41: =IFERROR(__xludf.DUMMYFUNCTION("TRIM(JOIN("" "",UNIQUE(TOCOL(ARRAYFORMULA(IF( SPLIT(C41,"" "")=TOCOL(SPLIT(C40,"" "")),SPLIT(C41,"" "")&"" "",""""))))))"),"YENY ROJAS BAZAM") -> YENY ROJAS BAZAM | L41: =IF(((G41<>"")*(I41<>"")*(K41<>"")*( J41=FALSE)*( H41=""))>=1,"EVALUAR","")&IF(L42="EVALUAR","->WITH THIS","") | M41: =IF(H41="",A41,A40) -> 37 | AA41: =IFERROR(__xludf.DUMMYFUNCTION("""COMPUTED_VALUE"""),"0469999") -> 0469999 | AB41: =IFERROR(__xludf.DUMMYFUNCTION("""COMPUTED_VALUE"""),"HERRERA SIPAN, AISSA") -> HERRERA SIPAN, AISSA | AC41: =IFERROR(__xludf.DUMMYFUNCTION("""COMPUTED_VALUE"""),"Madre") -> Madre | AD41: =IFERROR(__xludf.DUMMYFUNCTION("""COMPUTED_VALUE"""),27.0) -> 27 | AE41: =IFERROR(__xludf.DUMMYFUNCTION("""COMPUTED_VALUE"""),"Pre test (diagnóstico)") -> Pre test (diagnóstico) | AF41: =IFERROR(__xludf.DUMMYFUNCTION("TRIM(JOIN("" "",UNIQUE(TOCOL(ARRAYFORMULA(IF( SPLIT(AB41,"" "")=TOCOL(SPLIT(AB40,"" "")),SPLIT(AB41,"" "")&"" "",""""))))))"),"HERRERA SIPAN, AISSA") -> HERRERA SIPAN, AISSA | AY41: A mi me gusta estar bien con mi mamá y reirme
A42: =1+A41 -> 39 | B42: 1515246 | C42: YENI MINAYA MIRANDA | D42: Madre | E42: 34 | F42: Pre test (diagnóstico) | G42: =IF(E41=E42,"misma edad","") | H42: =IF(C42=C41,"mismo nombre","") | I42: =IF(B41=B42,"mismo colegio","") | J42: =F42=F41 -> FALSE | K42: =IFERROR(__xludf.DUMMYFUNCTION("TRIM(JOIN("" "",UNIQUE(TOCOL(ARRAYFORMULA(IF( SPLIT(C42,"" "")=TOCOL(SPLIT(C41,"" "")),SPLIT(C42,"" "")&"" "",""""))))))"),"") | L42: =IF(((G42<>"")*(I42<>"")*(K42<>"")*( J42=FALSE)*( H42=""))>=1,"EVALUAR","")&IF(L43="EVALUAR","->WITH THIS","") | M42: =IF(H42="",A42,A41) -> 39 | AA42: =IFERROR(__xludf.DUMMYFUNCTION("""COMPUTED_VALUE"""),"1675032") -> 1675032 | AB42: =IFERROR(__xludf.DUMMYFUNCTION("""COMPUTED_VALUE"""),"GOMEZ HUAYTAN YANET ABENCIA") -> GOMEZ HUAYTAN YANET ABENCIA | AC42: =IFERROR(__xludf.DUMMYFUNCTION("""COMPUTED_VALUE"""),"Madre") -> Madre | AD42: =IFERROR(__xludf.DUMMYFUNCTION("""COMPUTED_VALUE"""),24.0) -> 24 | AE42: =IFERROR(__xludf.DUMMYFUNCTION("""COMPUTED_VALUE"""),"Pre test (diagnóstico)") -> Pre test (diagnóstico) | AF42: =IFERROR(__xludf.DUMMYFUNCTION("TRIM(JOIN("" "",UNIQUE(TOCOL(ARRAYFORMULA(IF( SPLIT(AB42,"" "")=TOCOL(SPLIT(AB41,"" "")),SPLIT(AB42,"" "")&"" "",""""))))))"),"") | AY42: A mi me gusta lavar cocinar, jugar y escuchar musica
A43: =1+A42 -> 40 | B43: 1515246 | C43: YENI MINAYA MIRANDA | D43: Madre | E43: 34 | F43: Post test (cierre) | G43: =IF(E42=E43,"misma edad","") -> misma edad | H43: =IF(C43=C42,"mismo nombre","") -> mismo nombre | I43: =IF(B42=B43,"mismo colegio","") -> mismo colegio | J43: =F43=F42 -> FALSE | K43: =IFERROR(__xludf.DUMMYFUNCTION("TRIM(JOIN("" "",UNIQUE(TOCOL(ARRAYFORMULA(IF( SPLIT(C43,"" "")=TOCOL(SPLIT(C42,"" "")),SPLIT(C43,"" "")&"" "",""""))))))"),"YENI MINAYA MIRANDA") -> YENI MINAYA MIRANDA | L43: =IF(((G43<>"")*(I43<>"")*(K43<>"")*( J43=FALSE)*( H43=""))>=1,"EVALUAR","")&IF(L44="EVALUAR","->WITH THIS","") | M43: =IF(H43="",A43,A42) -> 39 | AA43: =IFERROR(__xludf.DUMMYFUNCTION("""COMPUTED_VALUE"""),"1675032") -> 1675032 | AB43: =IFERROR(__xludf.DUMMYFUNCTION("""COMPUTED_VALUE"""),"GOMEZ HUAYTAN YANET") -> GOMEZ HUAYTAN YANET | AC43: =IFERROR(__xludf.DUMMYFUNCTION("""COMPUTED_VALUE"""),"Madre") -> Madre | AD43: =IFERROR(__xludf.DUMMYFUNCTION("""COMPUTED_VALUE"""),24.0) -> 24 | AE43: =IFERROR(__xludf.DUMMYFUNCTION("""COMPUTED_VALUE"""),"Post test (cierre)") -> Post test (cierre) | AF43: =IFERROR(__xludf.DUMMYFUNCTION("TRIM(JOIN("" "",UNIQUE(TOCOL(ARRAYFORMULA(IF( SPLIT(AB43,"" "")=TOCOL(SPLIT(AB42,"" "")),SPLIT(AB43,"" "")&"" "",""""))))))"),"GOMEZ HUAYTAN YANET") -> GOMEZ HUAYTAN YANET | AY43: A mí me gustaría estar siempre que mi hijo necesite estar bien, y que este bien también mi familia tanto en salud y económicamente
A44: =1+A43 -> 41 | B44: 0469999 | C44: YAURI ESPINOZA, KELLY | D44: Madre | E44: 30 | F44: Pre test (diagnóstico) | G44: =IF(E43=E44,"misma edad","") | H44: =IF(C44=C43,"mismo nombre","") | I44: =IF(B43=B44,"mismo colegio","") | J44: =F44=F43 -> FALSE | K44: =IFERROR(__xludf.DUMMYFUNCTION("TRIM(JOIN("" "",UNIQUE(TOCOL(ARRAYFORMULA(IF( SPLIT(C44,"" "")=TOCOL(SPLIT(C43,"" "")),SPLIT(C44,"" "")&"" "",""""))))))"),"") | L44: =IF(((G44<>"")*(I44<>"")*(K44<>"")*( J44=FALSE)*( H44=""))>=1,"EVALUAR","")&IF(L45="EVALUAR","->WITH THIS","") | M44: =IF(H44="",A44,A43) -> 41 | AA44: =IFERROR(__xludf.DUMMYFUNCTION("""COMPUTED_VALUE"""),"1675032") -> 1675032 | AB44: =IFERROR(__xludf.DUMMYFUNCTION("""COMPUTED_VALUE"""),"GOMEZ HUAYTAN ANITA FLORCITA") -> GOMEZ HUAYTAN ANITA FLORCITA | AC44: =IFERROR(__xludf.DUMMYFUNCTION("""COMPUTED_VALUE"""),"Madre") -> Madre | AD44: =IFERROR(__xludf.DUMMYFUNCTION("""COMPUTED_VALUE"""),27.0) -> 27 | AE44: =IFERROR(__xludf.DUMMYFUNCTION("""COMPUTED_VALUE"""),"Post test (cierre)") -> Post test (cierre) | AF44: =IFERROR(__xludf.DUMMYFUNCTION("TRIM(JOIN("" "",UNIQUE(TOCOL(ARRAYFORMULA(IF( SPLIT(AB44,"" "")=TOCOL(SPLIT(AB43,"" "")),SPLIT(AB44,"" "")&"" "",""""))))))"),"GOMEZ HUAYTAN") -> GOMEZ HUAYTAN | AY44: A mí me gustaría que mi hijo llegue siempre feliz, convencido
A45: =1+A44 -> 42 | B45: 0469999 | C45: YAURI ESPINOZA, KELLY | D45: Madre | E45: 30 | F45: Post test (cierre) | G45: =IF(E44=E45,"misma edad","") -> misma edad | H45: =IF(C45=C44,"mismo nombre","") -> mismo nombre | I45: =IF(B44=B45,"mismo colegio","") -> mismo colegio | J45: =F45=F44 -> FALSE | K45: =IFERROR(__xludf.DUMMYFUNCTION("TRIM(JOIN("" "",UNIQUE(TOCOL(ARRAYFORMULA(IF( SPLIT(C45,"" "")=TOCOL(SPLIT(C44,"" "")),SPLIT(C45,"" "")&"" "",""""))))))"),"YAURI ESPINOZA, KELLY") -> YAURI ESPINOZA, KELLY | L45: =IF(((G45<>"")*(I45<>"")*(K45<>"")*( J45=FALSE)*( H45=""))>=1,"EVALUAR","")&IF(L46="EVALUAR","->WITH THIS","") | M45: =IF(H45="",A45,A44) -> 41 | AA45: =IFERROR(__xludf.DUMMYFUNCTION("""COMPUTED_VALUE"""),"1675032") -> 1675032 | AB45: =IFERROR(__xludf.DUMMYFUNCTION("""COMPUTED_VALUE"""),"GOMEZ HUAYTAN ANITA") -> GOMEZ HUAYTAN ANITA | AC45: =IFERROR(__xludf.DUMMYFUNCTION("""COMPUTED_VALUE"""),"Madre") -> Madre | AD45: =IFERROR(__xludf.DUMMYFUNCTION("""COMPUTED_VALUE"""),27.0) -> 27 | AE45: =IFERROR(__xludf.DUMMYFUNCTION("""COMPUTED_VALUE"""),"Pre test (diagnóstico)") -> Pre test (diagnóstico) | AF45: =IFERROR(__xludf.DUMMYFUNCTION("TRIM(JOIN("" "",UNIQUE(TOCOL(ARRAYFORMULA(IF( SPLIT(AB45,"" "")=TOCOL(SPLIT(AB44,"" "")),SPLIT(AB45,"" "")&"" "",""""))))))"),"GOMEZ HUAYTAN ANITA") -> GOMEZ HUAYTAN ANITA | AY45: A mí me motiva a estar feliz que mis hijas estén haciendo sus tareas y tenerles lista sus comidas
A46: =1+A45 -> 43 | B46: 0509711 | C46: YANIRA RAMOS GUERRA | D46: Madre | E46: 39 | F46: Pre test (diagnóstico) | G46: =IF(E45=E46,"misma edad","") | H46: =IF(C46=C45,"mismo nombre","") | I46: =IF(B45=B46,"mismo colegio","") | J46: =F46=F45 -> FALSE | K46: =IFERROR(__xludf.DUMMYFUNCTION("TRIM(JOIN("" "",UNIQUE(TOCOL(ARRAYFORMULA(IF( SPLIT(C46,"" "")=TOCOL(SPLIT(C45,"" "")),SPLIT(C46,"" "")&"" "",""""))))))"),"") | L46: =IF(((G46<>"")*(I46<>"")*(K46<>"")*( J46=FALSE)*( H46=""))>=1,"EVALUAR","")&IF(L47="EVALUAR","->WITH THIS","") -> ->WITH THIS | M46: =IF(H46="",A46,A45) -> 43 | AA46: =IFERROR(__xludf.DUMMYFUNCTION("""COMPUTED_VALUE"""),"1597608") -> 1597608 | AB46: =IFERROR(__xludf.DUMMYFUNCTION("""COMPUTED_VALUE"""),"GARAY ROJAS LILIANA") -> GARAY ROJAS LILIANA | AC46: =IFERROR(__xludf.DUMMYFUNCTION("""COMPUTED_VALUE"""),"Madre") -> Madre | AD46: =IFERROR(__xludf.DUMMYFUNCTION("""COMPUTED_VALUE"""),26.0) -> 26 | AE46: =IFERROR(__xludf.DUMMYFUNCTION("""COMPUTED_VALUE"""),"Post test (cierre)") -> Post test (cierre) | AF46: =IFERROR(__xludf.DUMMYFUNCTION("TRIM(JOIN("" "",UNIQUE(TOCOL(ARRAYFORMULA(IF( SPLIT(AB46,"" "")=TOCOL(SPLIT(AB45,"" "")),SPLIT(AB46,"" "")&"" "",""""))))))"),"") | AY46: A que mi hijo esté feliz
A47: =1+A46 -> 44 | B47: 0509711 | C47: YANINA RAMOS GUERRA | D47: Madre | E47: 39 | F47: Post test (cierre) | G47: =IF(E46=E47,"misma edad","") -> misma edad | H47: =IF(C47=C46,"mismo nombre","") | I47: =IF(B46=B47,"mismo colegio","") -> mismo colegio | J47: =F47=F46 -> FALSE | K47: =IFERROR(__xludf.DUMMYFUNCTION("TRIM(JOIN("" "",UNIQUE(TOCOL(ARRAYFORMULA(IF( SPLIT(C47,"" "")=TOCOL(SPLIT(C46,"" "")),SPLIT(C47,"" "")&"" "",""""))))))"),"RAMOS GUERRA") -> RAMOS GUERRA | L47: =IF(((G47<>"")*(I47<>"")*(K47<>"")*( J47=FALSE)*( H47=""))>=1,"EVALUAR","")&IF(L48="EVALUAR","->WITH THIS","") -> EVALUAR | M47: =IF(H47="",A47,A46) -> 44 | AA47: =IFERROR(__xludf.DUMMYFUNCTION("""COMPUTED_VALUE"""),"1597608") -> 1597608 | AB47: =IFERROR(__xludf.DUMMYFUNCTION("""COMPUTED_VALUE"""),"GARAY RIOS MAVILA LILIANA") -> GARAY RIOS MAVILA LILIANA | AC47: =IFERROR(__xludf.DUMMYFUNCTION("""COMPUTED_VALUE"""),"Madre") -> Madre | AD47: =IFERROR(__xludf.DUMMYFUNCTION("""COMPUTED_VALUE"""),26.0) -> 26 | AE47: =IFERROR(__xludf.DUMMYFUNCTION("""COMPUTED_VALUE"""),"Pre test (diagnóstico)") -> Pre test (diagnóstico) | AF47: =IFERROR(__xludf.DUMMYFUNCTION("TRIM(JOIN("" "",UNIQUE(TOCOL(ARRAYFORMULA(IF( SPLIT(AB47,"" "")=TOCOL(SPLIT(AB46,"" "")),SPLIT(AB47,"" "")&"" "",""""))))))"),"GARAY LILIANA") -> GARAY LILIANA | AY47: A queme hija se sienta felis y tranquila todos los dias
A48: =1+A47 -> 45 | B48: 1551738 | C48: YANETH MILAGROS ALVARO CHAVEZ | D48: Madre | E48: 33 | F48: Pre test (diagnóstico) | G48: =IF(E47=E48,"misma edad","") | H48: =IF(C48=C47,"mismo nombre","") | I48: =IF(B47=B48,"mismo colegio","") | J48: =F48=F47 -> FALSE | K48: =IFERROR(__xludf.DUMMYFUNCTION("TRIM(JOIN("" "",UNIQUE(TOCOL(ARRAYFORMULA(IF( SPLIT(C48,"" "")=TOCOL(SPLIT(C47,"" "")),SPLIT(C48,"" "")&"" "",""""))))))"),"") | L48: =IF(((G48<>"")*(I48<>"")*(K48<>"")*( J48=FALSE)*( H48=""))>=1,"EVALUAR","")&IF(L49="EVALUAR","->WITH THIS","") | M48: =IF(H48="",A48,A47) -> 45 | AA48: =IFERROR(__xludf.DUMMYFUNCTION("""COMPUTED_VALUE"""),"0469999") -> 0469999 | AB48: =IFERROR(__xludf.DUMMYFUNCTION("""COMPUTED_VALUE"""),"FLORES CANTO, ERIKA") -> FLORES CANTO, ERIKA | AC48: =IFERROR(__xludf.DUMMYFUNCTION("""COMPUTED_VALUE"""),"Madre") -> Madre | AD48: =IFERROR(__xludf.DUMMYFUNCTION("""COMPUTED_VALUE"""),42.0) -> 42 | AE48: =IFERROR(__xludf.DUMMYFUNCTION("""COMPUTED_VALUE"""),"Post test (cierre)") -> Post test (cierre) | AF48: =IFERROR(__xludf.DUMMYFUNCTION("TRIM(JOIN("" "",UNIQUE(TOCOL(ARRAYFORMULA(IF( SPLIT(AB48,"" "")=TOCOL(SPLIT(AB47,"" "")),SPLIT(AB48,"" "")&"" "",""""))))))"),"") | AY48: A respirar y tratar bien a mi hijo.
A49: =1+A48 -> 46 | B49: 1551738 | C49: YANETH MILAGROS ALVARO CHAVEZ | D49: Madre | E49: 33 | F49: Post test (cierre) | G49: =IF(E48=E49,"misma edad","") -> misma edad | H49: =IF(C49=C48,"mismo nombre","") -> mismo nombre | I49: =IF(B48=B49,"mismo colegio","") -> mismo colegio | J49: =F49=F48 -> FALSE | K49: =IFERROR(__xludf.DUMMYFUNCTION("TRIM(JOIN("" "",UNIQUE(TOCOL(ARRAYFORMULA(IF( SPLIT(C49,"" "")=TOCOL(SPLIT(C48,"" "")),SPLIT(C49,"" "")&"" "",""""))))))"),"YANETH MILAGROS ALVARO CHAVEZ") -> YANETH MILAGROS ALVARO CHAVEZ | L49: =IF(((G49<>"")*(I49<>"")*(K49<>"")*( J49=FALSE)*( H49=""))>=1,"EVALUAR","")&IF(L50="EVALUAR","->WITH THIS","") | M49: =IF(H49="",A49,A48) -> 45 | AA49: =IFERROR(__xludf.DUMMYFUNCTION("""COMPUTED_VALUE"""),"0469999") -> 0469999 | AB49: =IFERROR(__xludf.DUMMYFUNCTION("""COMPUTED_VALUE"""),"FLORES CANTI, ERIKA") -> FLORES CANTI, ERIKA | AC49: =IFERROR(__xludf.DUMMYFUNCTION("""COMPUTED_VALUE"""),"Madre") -> Madre | AD49: =IFERROR(__xludf.DUMMYFUNCTION("""COMPUTED_VALUE"""),42.0) -> 42 | AE49: =IFERROR(__xludf.DUMMYFUNCTION("""COMPUTED_VALUE"""),"Pre test (diagnóstico)") -> Pre test (diagnóstico) | AF49: =IFERROR(__xludf.DUMMYFUNCTION("TRIM(JOIN("" "",UNIQUE(TOCOL(ARRAYFORMULA(IF( SPLIT(AB49,"" "")=TOCOL(SPLIT(AB48,"" "")),SPLIT(AB49,"" "")&"" "",""""))))))"),"FLORES ERIKA") -> FLORES ERIKA | AY49: A salir adelante junto con mi hija.
A50: =1+A49 -> 47 | B50: 1675040 | C50: YANETH AGUIRRE VEGA | D50: Madre | E50: 24 | F50: Pre test (diagnóstico) | G50: =IF(E49=E50,"misma edad","") | H50: =IF(C50=C49,"mismo nombre","") | I50: =IF(B49=B50,"mismo colegio","") | J50: =F50=F49 -> FALSE | K50: =IFERROR(__xludf.DUMMYFUNCTION("TRIM(JOIN("" "",UNIQUE(TOCOL(ARRAYFORMULA(IF( SPLIT(C50,"" "")=TOCOL(SPLIT(C49,"" "")),SPLIT(C50,"" "")&"" "",""""))))))"),"YANETH") -> YANETH | L50: =IF(((G50<>"")*(I50<>"")*(K50<>"")*( J50=FALSE)*( H50=""))>=1,"EVALUAR","")&IF(L51="EVALUAR","->WITH THIS","") | M50: =IF(H50="",A50,A49) -> 47 | AA50: =IFERROR(__xludf.DUMMYFUNCTION("""COMPUTED_VALUE"""),"0415869") -> 0415869 | AB50: =IFERROR(__xludf.DUMMYFUNCTION("""COMPUTED_VALUE"""),"ENITH NELLY MORALES CACHA") -> ENITH NELLY MORALES CACHA | AC50: =IFERROR(__xludf.DUMMYFUNCTION("""COMPUTED_VALUE"""),"Madre") -> Madre | AD50: =IFERROR(__xludf.DUMMYFUNCTION("""COMPUTED_VALUE"""),33.0) -> 33 | AE50: =IFERROR(__xludf.DUMMYFUNCTION("""COMPUTED_VALUE"""),"Post test (cierre)") -> Post test (cierre) | AF50: =IFERROR(__xludf.DUMMYFUNCTION("TRIM(JOIN("" "",UNIQUE(TOCOL(ARRAYFORMULA(IF( SPLIT(AB50,"" "")=TOCOL(SPLIT(AB49,"" "")),SPLIT(AB50,"" "")&"" "",""""))))))"),"") | AY50: Actividad física, recreación y con familia
A51: =1+A50 -> 48 | B51: 1675040 | C51: YANETH AGUIRRE VEGA | D51: Madre | E51: 24 | F51: Post test (cierre) | G51: =IF(E50=E51,"misma edad","") -> misma edad | H51: =IF(C51=C50,"mismo nombre","") -> mismo nombre | I51: =IF(B50=B51,"mismo colegio","") -> mismo colegio | J51: =F51=F50 -> FALSE | K51: =IFERROR(__xludf.DUMMYFUNCTION("TRIM(JOIN("" "",UNIQUE(TOCOL(ARRAYFORMULA(IF( SPLIT(C51,"" "")=TOCOL(SPLIT(C50,"" "")),SPLIT(C51,"" "")&"" "",""""))))))"),"YANETH AGUIRRE VEGA") -> YANETH AGUIRRE VEGA | L51: =IF(((G51<>"")*(I51<>"")*(K51<>"")*( J51=FALSE)*( H51=""))>=1,"EVALUAR","")&IF(L52="EVALUAR","->WITH THIS","") | M51: =IF(H51="",A51,A50) -> 47 | AA51: =IFERROR(__xludf.DUMMYFUNCTION("""COMPUTED_VALUE"""),"0415869") -> 0415869 | AB51: =IFERROR(__xludf.DUMMYFUNCTION("""COMPUTED_VALUE"""),"ENITH MORALES CACHA") -> ENITH MORALES CACHA | AC51: =IFERROR(__xludf.DUMMYFUNCTION("""COMPUTED_VALUE"""),"Madre") -> Madre | AD51: =IFERROR(__xludf.DUMMYFUNCTION("""COMPUTED_VALUE"""),33.0) -> 33 | AE51: =IFERROR(__xludf.DUMMYFUNCTION("""COMPUTED_VALUE"""),"Pre test (diagnóstico)") -> Pre test (diagnóstico) | AF51: =IFERROR(__xludf.DUMMYFUNCTION("TRIM(JOIN("" "",UNIQUE(TOCOL(ARRAYFORMULA(IF( SPLIT(AB51,"" "")=TOCOL(SPLIT(AB50,"" "")),SPLIT(AB51,"" "")&"" "",""""))))))"),"ENITH MORALES CACHA") -> ENITH MORALES CACHA | AY51: Alcanza algunas cosas.
A52: =1+A51 -> 49 | B52: 1675040 | C52: YANET LUZ RAMIREZ ANAYA | D52: Madre | E52: 21 | F52: Pre test (diagnóstico) | G52: =IF(E51=E52,"misma edad","") | H52: =IF(C52=C51,"mismo nombre","") | I52: =IF(B51=B52,"mismo colegio","") -> mismo colegio | J52: =F52=F51 -> FALSE | K52: =IFERROR(__xludf.DUMMYFUNCTION("TRIM(JOIN("" "",UNIQUE(TOCOL(ARRAYFORMULA(IF( SPLIT(C52,"" "")=TOCOL(SPLIT(C51,"" "")),SPLIT(C52,"" "")&"" "",""""))))))"),"") | L52: =IF(((G52<>"")*(I52<>"")*(K52<>"")*( J52=FALSE)*( H52=""))>=1,"EVALUAR","")&IF(L53="EVALUAR","->WITH THIS","") | M52: =IF(H52="",A52,A51) -> 49 | AA52: =IFERROR(__xludf.DUMMYFUNCTION("""COMPUTED_VALUE"""),"1675032") -> 1675032 | AB52: =IFERROR(__xludf.DUMMYFUNCTION("""COMPUTED_VALUE"""),"DIAZ ZORRILLA LESLY DENISSA") -> DIAZ ZORRILLA LESLY DENISSA | AC52: =IFERROR(__xludf.DUMMYFUNCTION("""COMPUTED_VALUE"""),"Madre") -> Madre | AD52: =IFERROR(__xludf.DUMMYFUNCTION("""COMPUTED_VALUE"""),28.0) -> 28 | AE52: =IFERROR(__xludf.DUMMYFUNCTION("""COMPUTED_VALUE"""),"Post test (cierre)") -> Post test (cierre) | AF52: =IFERROR(__xludf.DUMMYFUNCTION("TRIM(JOIN("" "",UNIQUE(TOCOL(ARRAYFORMULA(IF( SPLIT(AB52,"" "")=TOCOL(SPLIT(AB51,"" "")),SPLIT(AB52,"" "")&"" "",""""))))))"),"") | AY52: Aplicar rutinas- descansar bien
A53: =1+A52 -> 50 | B53: 1675040 | C53: YANET LUZ RAMIREZ ANAYA | D53: Madre | E53: 21 | F53: Post test (cierre) | G53: =IF(E52=E53,"misma edad","") -> misma edad | H53: =IF(C53=C52,"mismo nombre","") -> mismo nombre | I53: =IF(B52=B53,"mismo colegio","") -> mismo colegio | J53: =F53=F52 -> FALSE | K53: =IFERROR(__xludf.DUMMYFUNCTION("TRIM(JOIN("" "",UNIQUE(TOCOL(ARRAYFORMULA(IF( SPLIT(C53,"" "")=TOCOL(SPLIT(C52,"" "")),SPLIT(C53,"" "")&"" "",""""))))))"),"YANET LUZ RAMIREZ ANAYA") -> YANET LUZ RAMIREZ ANAYA | L53: =IF(((G53<>"")*(I53<>"")*(K53<>"")*( J53=FALSE)*( H53=""))>=1,"EVALUAR","")&IF(L54="EVALUAR","->WITH THIS","") | M53: =IF(H53="",A53,A52) -> 49 | AA53: =IFERROR(__xludf.DUMMYFUNCTION("""COMPUTED_VALUE"""),"1675032") -> 1675032 | AB53: =IFERROR(__xludf.DUMMYFUNCTION("""COMPUTED_VALUE"""),"DIAZ ZORRILLA LESLY") -> DIAZ ZORRILLA LESLY | AC53: =IFERROR(__xludf.DUMMYFUNCTION("""COMPUTED_VALUE"""),"Madre") -> Madre | AD53: =IFERROR(__xludf.DUMMYFUNCTION("""COMPUTED_VALUE"""),28.0) -> 28 | AE53: =IFERROR(__xludf.DUMMYFUNCTION("""COMPUTED_VALUE"""),"Pre test (diagnóstico)") -> Pre test (diagnóstico) | AF53: =IFERROR(__xludf.DUMMYFUNCTION("TRIM(JOIN("" "",UNIQUE(TOCOL(ARRAYFORMULA(IF( SPLIT(AB53,"" "")=TOCOL(SPLIT(AB52,"" "")),SPLIT(AB53,"" "")&"" "",""""))))))"),"DIAZ ZORRILLA LESLY") -> DIAZ ZORRILLA LESLY | AY53: Apoyar a hacer su tarea.
A54: =1+A53 -> 51 | B54: 0509711 | C54: YANET DIAZ CASTRO | D54: Madre | E54: 35 | F54: Pre test (diagnóstico) | G54: =IF(E53=E54,"misma edad","") | H54: =IF(C54=C53,"mismo nombre","") | I54: =IF(B53=B54,"mismo colegio","") | J54: =F54=F53 -> FALSE | K54: =IFERROR(__xludf.DUMMYFUNCTION("TRIM(JOIN("" "",UNIQUE(TOCOL(ARRAYFORMULA(IF( SPLIT(C54,"" "")=TOCOL(SPLIT(C53,"" "")),SPLIT(C54,"" "")&"" "",""""))))))"),"YANET") -> YANET | L54: =IF(((G54<>"")*(I54<>"")*(K54<>"")*( J54=FALSE)*( H54=""))>=1,"EVALUAR","")&IF(L55="EVALUAR","->WITH THIS","") | M54: =IF(H54="",A54,A53) -> 51 | AA54: =IFERROR(__xludf.DUMMYFUNCTION("""COMPUTED_VALUE"""),"0415745") -> 0415745 | AB54: =IFERROR(__xludf.DUMMYFUNCTION("""COMPUTED_VALUE"""),"DANIEL JOEL MONTES FLORES | LUCY PAUCAR") -> DANIEL JOEL MONTES FLORES | LUCY PAUCAR | AC54: =IFERROR(__xludf.DUMMYFUNCTION("""COMPUTED_VALUE"""),"Padre") -> Padre | AD54: =IFERROR(__xludf.DUMMYFUNCTION("""COMPUTED_VALUE"""),32.0) -> 32 | AE54: =IFERROR(__xludf.DUMMYFUNCTION("""COMPUTED_VALUE"""),"Post test (cierre)") -> Post test (cierre) | AF54: =IFERROR(__xludf.DUMMYFUNCTION("TRIM(JOIN("" "",UNIQUE(TOCOL(ARRAYFORMULA(IF( SPLIT(AB54,"" "")=TOCOL(SPLIT(AB53,"" "")),SPLIT(AB54,"" "")&"" "",""""))))))"),"") | AY54: Aprender más sobre mi hijo para poder entenderle y ponerme en su lugar de él. Comprender más a mi niño. A veces nuestros hijos son más diferentes. Yo quiero ayudar a mi hijo, Jaziel. Lo amo mucho, y quiero entenderlo mucho más.
A55: =1+A54 -> 52 | B55: 0509711 | C55: YANET DIAZ CASTRO | D55: Madre | E55: 35 | F55: Post test (cierre) | G55: =IF(E54=E55,"misma edad","") -> misma edad | H55: =IF(C55=C54,"mismo nombre","") -> mismo nombre | I55: =IF(B54=B55,"mismo colegio","") -> mismo colegio | J55: =F55=F54 -> FALSE | K55: =IFERROR(__xludf.DUMMYFUNCTION("TRIM(JOIN("" "",UNIQUE(TOCOL(ARRAYFORMULA(IF( SPLIT(C55,"" "")=TOCOL(SPLIT(C54,"" "")),SPLIT(C55,"" "")&"" "",""""))))))"),"YANET DIAZ CASTRO") -> YANET DIAZ CASTRO | L55: =IF(((G55<>"")*(I55<>"")*(K55<>"")*( J55=FALSE)*( H55=""))>=1,"EVALUAR","")&IF(L56="EVALUAR","->WITH THIS","") | M55: =IF(H55="",A55,A54) -> 51 | AA55: =IFERROR(__xludf.DUMMYFUNCTION("""COMPUTED_VALUE"""),"0415745") -> 0415745 | AB55: =IFERROR(__xludf.DUMMYFUNCTION("""COMPUTED_VALUE"""),"DANIEL JOEL MONTES FLORES") -> DANIEL JOEL MONTES FLORES | AC55: =IFERROR(__xludf.DUMMYFUNCTION("""COMPUTED_VALUE"""),"Madre") -> Madre | AD55: =IFERROR(__xludf.DUMMYFUNCTION("""COMPUTED_VALUE"""),32.0) -> 32 | AE55: =IFERROR(__xludf.DUMMYFUNCTION("""COMPUTED_VALUE"""),"Pre test (diagnóstico)") -> Pre test (diagnóstico) | AF55: =IFERROR(__xludf.DUMMYFUNCTION("TRIM(JOIN("" "",UNIQUE(TOCOL(ARRAYFORMULA(IF( SPLIT(AB55,"" "")=TOCOL(SPLIT(AB54,"" "")),SPLIT(AB55,"" "")&"" "",""""))))))"),"DANIEL JOEL MONTES FLORES") -> DANIEL JOEL MONTES FLORES | AY55: Armonía con los integrantes de casa, confianza con mis hijos, pareja y familia, escuchar música fuerte, el orden y la limpieza.
A56: =1+A55 -> 53 | B56: 0509711 | C56: WILMER RIOS DIANES | D56: Padre | E56: 38 | F56: Pre test (diagnóstico) | G56: =IF(E55=E56,"misma edad","") | H56: =IF(C56=C55,"mismo nombre","") | I56: =IF(B55=B56,"mismo colegio","") -> mismo colegio | J56: =F56=F55 -> FALSE | K56: =IFERROR(__xludf.DUMMYFUNCTION("TRIM(JOIN("" "",UNIQUE(TOCOL(ARRAYFORMULA(IF( SPLIT(C56,"" "")=TOCOL(SPLIT(C55,"" "")),SPLIT(C56,"" "")&"" "",""""))))))"),"") | L56: =IF(((G56<>"")*(I56<>"")*(K56<>"")*( J56=FALSE)*( H56=""))>=1,"EVALUAR","")&IF(L57="EVALUAR","->WITH THIS","") -> ->WITH THIS | M56: =IF(H56="",A56,A55) -> 53 | AA56: =IFERROR(__xludf.DUMMYFUNCTION("""COMPUTED_VALUE"""),"0509711") -> 0509711 | AB56: =IFERROR(__xludf.DUMMYFUNCTION("""COMPUTED_VALUE"""),"BRAYAN CARHUAPOMA TARAZONA | MILAGROS GUERRA RAMIREZ") -> BRAYAN CARHUAPOMA TARAZONA | MILAGROS GUERRA RAMIREZ | AC56: =IFERROR(__xludf.DUMMYFUNCTION("""COMPUTED_VALUE"""),"Madre") -> Madre | AD56: =IFERROR(__xludf.DUMMYFUNCTION("""COMPUTED_VALUE"""),24.0) -> 24 | AE56: =IFERROR(__xludf.DUMMYFUNCTION("""COMPUTED_VALUE"""),"Post test (cierre)") -> Post test (cierre) | AF56: =IFERROR(__xludf.DUMMYFUNCTION("TRIM(JOIN("" "",UNIQUE(TOCOL(ARRAYFORMULA(IF( SPLIT(AB56,"" "")=TOCOL(SPLIT(AB55,"" "")),SPLIT(AB56,"" "")&"" "",""""))))))"),"") | AY56: Atender sus emociones de mis hijos de como se sienten.
A57: =1+A56 -> 54 | B57: 0509711 | C57: WILMER RIOS CHAVEZ | ANGELICA DIAZ LLIUYA | D57: Padre | E57: 38 | F57: Post test (cierre) | G57: =IF(E56=E57,"misma edad","") -> misma edad | H57: =IF(C57=C56,"mismo nombre","") | I57: =IF(B56=B57,"mismo colegio","") -> mismo colegio | J57: =F57=F56 -> FALSE | K57: =IFERROR(__xludf.DUMMYFUNCTION("TRIM(JOIN("" "",UNIQUE(TOCOL(ARRAYFORMULA(IF( SPLIT(C57,"" "")=TOCOL(SPLIT(C56,"" "")),SPLIT(C57,"" "")&"" "",""""))))))"),"WILMER RIOS") -> WILMER RIOS | L57: =IF(((G57<>"")*(I57<>"")*(K57<>"")*( J57=FALSE)*( H57=""))>=1,"EVALUAR","")&IF(L58="EVALUAR","->WITH THIS","") -> EVALUAR | M57: =IF(H57="",A57,A56) -> 54 | AA57: =IFERROR(__xludf.DUMMYFUNCTION("""COMPUTED_VALUE"""),"0509711") -> 0509711 | AB57: =IFERROR(__xludf.DUMMYFUNCTION("""COMPUTED_VALUE"""),"BRAYAN CARHUAPOMA TARAZONA") -> BRAYAN CARHUAPOMA TARAZONA | AC57: =IFERROR(__xludf.DUMMYFUNCTION("""COMPUTED_VALUE"""),"Padre") -> Padre | AD57: =IFERROR(__xludf.DUMMYFUNCTION("""COMPUTED_VALUE"""),24.0) -> 24 | AE57: =IFERROR(__xludf.DUMMYFUNCTION("""COMPUTED_VALUE"""),"Pre test (diagnóstico)") -> Pre test (diagnóstico) | AF57: =IFERROR(__xludf.DUMMYFUNCTION("TRIM(JOIN("" "",UNIQUE(TOCOL(ARRAYFORMULA(IF( SPLIT(AB57,"" "")=TOCOL(SPLIT(AB56,"" "")),SPLIT(AB57,"" "")&"" "",""""))))))"),"BRAYAN CARHUAPOMA TARAZONA") -> BRAYAN CARHUAPOMA TARAZONA | AY57: Ayuda terminar las tareas de casa rapido
A58: =1+A57 -> 55 | B58: 0509711 | C58: WAGNER FERNANDEZ AIRA | FLOR HUERTA MALLQUI | D58: Madre | E58: 39 | F58: Post test (cierre) | G58: =IF(E57=E58,"misma edad","") | H58: =IF(C58=C57,"mismo nombre","") | I58: =IF(B57=B58,"mismo colegio","") -> mismo colegio | J58: =F58=F57 -> TRUE | K58: =IFERROR(__xludf.DUMMYFUNCTION("TRIM(JOIN("" "",UNIQUE(TOCOL(ARRAYFORMULA(IF( SPLIT(C58,"" "")=TOCOL(SPLIT(C57,"" "")),SPLIT(C58,"" "")&"" "",""""))))))"),"|") -> | | L58: =IF(((G58<>"")*(I58<>"")*(K58<>"")*( J58=FALSE)*( H58=""))>=1,"EVALUAR","")&IF(L59="EVALUAR","->WITH THIS","") -> ->WITH THIS | M58: =IF(H58="",A58,A57) -> 55 | AA58: =IFERROR(__xludf.DUMMYFUNCTION("""COMPUTED_VALUE"""),"1675032") -> 1675032 | AB58: =IFERROR(__xludf.DUMMYFUNCTION("""COMPUTED_VALUE"""),"ALMERCON VERAMENDI BETY MAGDALENA") -> ALMERCON VERAMENDI BETY MAGDALENA | AC58: =IFERROR(__xludf.DUMMYFUNCTION("""COMPUTED_VALUE"""),"Madre") -> Madre | AD58: =IFERROR(__xludf.DUMMYFUNCTION("""COMPUTED_VALUE"""),29.0) -> 29 | AE58: =IFERROR(__xludf.DUMMYFUNCTION("""COMPUTED_VALUE"""),"Post test (cierre)") -> Post test (cierre) | AF58: =IFERROR(__xludf.DUMMYFUNCTION("TRIM(JOIN("" "",UNIQUE(TOCOL(ARRAYFORMULA(IF( SPLIT(AB58,"" "")=TOCOL(SPLIT(AB57,"" "")),SPLIT(AB58,"" "")&"" "",""""))))))"),"") | AY58: Ayudar a las mamas y a los niños en cualquier cosa
A59: =1+A58 -> 56 | B59: 0509711 | C59: WAGNER FERNANDEZ AIRA | D59: Padre | E59: 39 | F59: Pre test (diagnóstico) | G59: =IF(E58=E59,"misma edad","") -> misma edad | H59: =IF(C59=C58,"mismo nombre","") | I59: =IF(B58=B59,"mismo colegio","") -> mismo colegio | J59: =F59=F58 -> FALSE | K59: =IFERROR(__xludf.DUMMYFUNCTION("TRIM(JOIN("" "",UNIQUE(TOCOL(ARRAYFORMULA(IF( SPLIT(C59,"" "")=TOCOL(SPLIT(C58,"" "")),SPLIT(C59,"" "")&"" "",""""))))))"),"WAGNER FERNANDEZ AIRA") -> WAGNER FERNANDEZ AIRA | L59: =IF(((G59<>"")*(I59<>"")*(K59<>"")*( J59=FALSE)*( H59=""))>=1,"EVALUAR","")&IF(L60="EVALUAR","->WITH THIS","") -> EVALUAR | M59: =IF(H59="",A59,A58) -> 56 | AA59: =IFERROR(__xludf.DUMMYFUNCTION("""COMPUTED_VALUE"""),"1675032") -> 1675032 | AB59: =IFERROR(__xludf.DUMMYFUNCTION("""COMPUTED_VALUE"""),"ALMERCON VERAMENDI BETY") -> ALMERCON VERAMENDI BETY | AC59: =IFERROR(__xludf.DUMMYFUNCTION("""COMPUTED_VALUE"""),"Madre") -> Madre | AD59: =IFERROR(__xludf.DUMMYFUNCTION("""COMPUTED_VALUE"""),29.0) -> 29 | AE59: =IFERROR(__xludf.DUMMYFUNCTION("""COMPUTED_VALUE"""),"Pre test (diagnóstico)") -> Pre test (diagnóstico) | AF59: =IFERROR(__xludf.DUMMYFUNCTION("TRIM(JOIN("" "",UNIQUE(TOCOL(ARRAYFORMULA(IF( SPLIT(AB59,"" "")=TOCOL(SPLIT(AB58,"" "")),SPLIT(AB59,"" "")&"" "",""""))))))"),"ALMERCON VERAMENDI BETY") -> ALMERCON VERAMENDI BETY | AY59: Ayudar a mi hija, cuidando a mis niños y o discutir al lado del niño.
A60: =1+A59 -> 57 | B60: 1645373 | C60: VIVIANA NOEMI PALOMARES | D60: Madre | E60: 24 | F60: Pre test (diagnóstico) | G60: =IF(E59=E60,"misma edad","") | H60: =IF(C60=C59,"mismo nombre","") | I60: =IF(B59=B60,"mismo colegio","") | J60: =F60=F59 -> TRUE | K60: =IFERROR(__xludf.DUMMYFUNCTION("TRIM(JOIN("" "",UNIQUE(TOCOL(ARRAYFORMULA(IF( SPLIT(C60,"" "")=TOCOL(SPLIT(C59,"" "")),SPLIT(C60,"" "")&"" "",""""))))))"),"") | L60: =IF(((G60<>"")*(I60<>"")*(K60<>"")*( J60=FALSE)*( H60=""))>=1,"EVALUAR","")&IF(L61="EVALUAR","->WITH THIS","") | M60: =IF(H60="",A60,A59) -> 57 | AY60: Ayudar con sus tareas
A61: =1+A60 -> 58 | B61: 0509711 | C61: VIONE CATIRE ENRIQUE | D61: Madre | E61: 30 | F61: Pre test (diagnóstico) | G61: =IF(E60=E61,"misma edad","") | H61: =IF(C61=C60,"mismo nombre","") | I61: =IF(B60=B61,"mismo colegio","") | J61: =F61=F60 -> TRUE | K61: =IFERROR(__xludf.DUMMYFUNCTION("TRIM(JOIN("" "",UNIQUE(TOCOL(ARRAYFORMULA(IF( SPLIT(C61,"" "")=TOCOL(SPLIT(C60,"" "")),SPLIT(C61,"" "")&"" "",""""))))))"),"") | L61: =IF(((G61<>"")*(I61<>"")*(K61<>"")*( J61=FALSE)*( H61=""))>=1,"EVALUAR","")&IF(L62="EVALUAR","->WITH THIS","") | M61: =IF(H61="",A61,A60) -> 58 | AY61: Ayudar con sus tareas a mis hijos hablar con mis hijos como comportarse
A62: =1+A61 -> 59 | B62: 0509711 | C62: VIONE CATIRE ENRIQUE | D62: Madre | E62: 30 | F62: Post test (cierre) | G62: =IF(E61=E62,"misma edad","") -> misma edad | H62: =IF(C62=C61,"mismo nombre","") -> mismo nombre | I62: =IF(B61=B62,"mismo colegio","") -> mismo colegio | J62: =F62=F61 -> FALSE | K62: =IFERROR(__xludf.DUMMYFUNCTION("TRIM(JOIN("" "",UNIQUE(TOCOL(ARRAYFORMULA(IF( SPLIT(C62,"" "")=TOCOL(SPLIT(C61,"" "")),SPLIT(C62,"" "")&"" "",""""))))))"),"VIONE CATIRE ENRIQUE") -> VIONE CATIRE ENRIQUE | L62: =IF(((G62<>"")*(I62<>"")*(K62<>"")*( J62=FALSE)*( H62=""))>=1,"EVALUAR","")&IF(L63="EVALUAR","->WITH THIS","") | M62: =IF(H62="",A62,A61) -> 58 | AY62: Ayudar en las tareas.
A63: =1+A62 -> 60 | B63: 0509711 | C63: VIOLETA AMADO SALAZAR | D63: Madre | E63: 37 | F63: Pre test (diagnóstico) | G63: =IF(E62=E63,"misma edad","") | H63: =IF(C63=C62,"mismo nombre","") | I63: =IF(B62=B63,"mismo colegio","") -> mismo colegio | J63: =F63=F62 -> FALSE | K63: =IFERROR(__xludf.DUMMYFUNCTION("TRIM(JOIN("" "",UNIQUE(TOCOL(ARRAYFORMULA(IF( SPLIT(C63,"" "")=TOCOL(SPLIT(C62,"" "")),SPLIT(C63,"" "")&"" "",""""))))))"),"") | L63: =IF(((G63<>"")*(I63<>"")*(K63<>"")*( J63=FALSE)*( H63=""))>=1,"EVALUAR","")&IF(L64="EVALUAR","->WITH THIS","") | M63: =IF(H63="",A63,A62) -> 60 | AY63: Ayudar en todas las tareas
A64: =1+A63 -> 61 | B64: 0509711 | C64: VIOLETA AMADO SALAZAR | D64: Madre | E64: 37 | F64: Post test (cierre) | G64: =IF(E63=E64,"misma edad","") -> misma edad | H64: =IF(C64=C63,"mismo nombre","") -> mismo nombre | I64: =IF(B63=B64,"mismo colegio","") -> mismo colegio | J64: =F64=F63 -> FALSE | K64: =IFERROR(__xludf.DUMMYFUNCTION("TRIM(JOIN("" "",UNIQUE(TOCOL(ARRAYFORMULA(IF( SPLIT(C64,"" "")=TOCOL(SPLIT(C63,"" "")),SPLIT(C64,"" "")&"" "",""""))))))"),"VIOLETA AMADO SALAZAR") -> VIOLETA AMADO SALAZAR | L64: =IF(((G64<>"")*(I64<>"")*(K64<>"")*( J64=FALSE)*( H64=""))>=1,"EVALUAR","")&IF(L65="EVALUAR","->WITH THIS","") | M64: =IF(H64="",A64,A63) -> 60 | AY64: Ayudar hacer con sus tareas mi hija y enseñar quehaceres en la casa, ordenar sus cosas
A65: =1+A64 -> 62 | B65: 1558782 | C65: VILLASUAN SOTO ESTEFANY | D65: Madre | E65: 22 | F65: Pre test (diagnóstico) | G65: =IF(E64=E65,"misma edad","") | H65: =IF(C65=C64,"mismo nombre","") | I65: =IF(B64=B65,"mismo colegio","") | J65: =F65=F64 -> FALSE | K65: =IFERROR(__xludf.DUMMYFUNCTION("TRIM(JOIN("" "",UNIQUE(TOCOL(ARRAYFORMULA(IF( SPLIT(C65,"" "")=TOCOL(SPLIT(C64,"" "")),SPLIT(C65,"" "")&"" "",""""))))))"),"") | L65: =IF(((G65<>"")*(I65<>"")*(K65<>"")*( J65=FALSE)*( H65=""))>=1,"EVALUAR","")&IF(L66="EVALUAR","->WITH THIS","") | M65: =IF(H65="",A65,A64) -> 62 | AY65: Ayudarle en sus tareas y que sea respetuosa.
A66: =1+A65 -> 63 | B66: 1043652 | C66: VILLAFUERTE PAJUELO, KELY MARINA | D66: Madre | E66: 35 | F66: Pre test (diagnóstico) | G66: =IF(E65=E66,"misma edad","") | H66: =IF(C66=C65,"mismo nombre","") | I66: =IF(B65=B66,"mismo colegio","") | J66: =F66=F65 -> TRUE | K66: =IFERROR(__xludf.DUMMYFUNCTION("TRIM(JOIN("" "",UNIQUE(TOCOL(ARRAYFORMULA(IF( SPLIT(C66,"" "")=TOCOL(SPLIT(C65,"" "")),SPLIT(C66,"" "")&"" "",""""))))))"),"") | L66: =IF(((G66<>"")*(I66<>"")*(K66<>"")*( J66=FALSE)*( H66=""))>=1,"EVALUAR","")&IF(L67="EVALUAR","->WITH THIS","") | M66: =IF(H66="",A66,A65) -> 63 | AY66: Bailar
A67: =1+A66 -> 64 | B67: 1043652 | C67: VILLAFUERTE PAJUELO, KELY MARINA | D67: Madre | E67: 35 | F67: Post test (cierre) | G67: =IF(E66=E67,"misma edad","") -> misma edad | H67: =IF(C67=C66,"mismo nombre","") -> mismo nombre | I67: =IF(B66=B67,"mismo colegio","") -> mismo colegio | J67: =F67=F66 -> FALSE | K67: =IFERROR(__xludf.DUMMYFUNCTION("TRIM(JOIN("" "",UNIQUE(TOCOL(ARRAYFORMULA(IF( SPLIT(C67,"" "")=TOCOL(SPLIT(C66,"" "")),SPLIT(C67,"" "")&"" "",""""))))))"),"VILLAFUERTE PAJUELO, KELY MARINA") -> VILLAFUERTE PAJUELO, KELY MARINA | L67: =IF(((G67<>"")*(I67<>"")*(K67<>"")*( J67=FALSE)*( H67=""))>=1,"EVALUAR","")&IF(L68="EVALUAR","->WITH THIS","") | M67: =IF(H67="",A67,A66) -> 63 | AY67: Bailar, caminar, cantar
A68: =1+A67 -> 65 | B68: 1597608 | C68: VILCA PEÑA CARLOS | D68: Padre | E68: 39 | F68: Pre test (diagnóstico) | G68: =IF(E67=E68,"misma edad","") | H68: =IF(C68=C67,"mismo nombre","") | I68: =IF(B67=B68,"mismo colegio","") | J68: =F68=F67 -> FALSE | K68: =IFERROR(__xludf.DUMMYFUNCTION("TRIM(JOIN("" "",UNIQUE(TOCOL(ARRAYFORMULA(IF( SPLIT(C68,"" "")=TOCOL(SPLIT(C67,"" "")),SPLIT(C68,"" "")&"" "",""""))))))"),"") | L68: =IF(((G68<>"")*(I68<>"")*(K68<>"")*( J68=FALSE)*( H68=""))>=1,"EVALUAR","")&IF(L69="EVALUAR","->WITH THIS","") | M68: =IF(H68="",A68,A67) -> 65 | AY68: Bailar, cantar y sentirme bonita
A69: =1+A68 -> 66 | B69: 1675024 | C69: VICTORIO AYDE AQUINO LOARTE | D69: Madre | E69: 22 | F69: Pre test (diagnóstico) | G69: =IF(E68=E69,"misma edad","") | H69: =IF(C69=C68,"mismo nombre","") | I69: =IF(B68=B69,"mismo colegio","") | J69: =F69=F68 -> TRUE | K69: =IFERROR(__xludf.DUMMYFUNCTION("TRIM(JOIN("" "",UNIQUE(TOCOL(ARRAYFORMULA(IF( SPLIT(C69,"" "")=TOCOL(SPLIT(C68,"" "")),SPLIT(C69,"" "")&"" "",""""))))))"),"") | L69: =IF(((G69<>"")*(I69<>"")*(K69<>"")*( J69=FALSE)*( H69=""))>=1,"EVALUAR","")&IF(L70="EVALUAR","->WITH THIS","") | M69: =IF(H69="",A69,A68) -> 66 | AY69: Bien de salud con toda mi familia
A70: =1+A69 -> 67 | B70: 1675024 | C70: VICTORIO AYDE AQUINO LOARTE | D70: Madre | F70: Post test (cierre) | G70: =IF(E69=E70,"misma edad","") | H70: =IF(C70=C69,"mismo nombre","") -> mismo nombre | I70: =IF(B69=B70,"mismo colegio","") -> mismo colegio | J70: =F70=F69 -> FALSE | K70: =IFERROR(__xludf.DUMMYFUNCTION("TRIM(JOIN("" "",UNIQUE(TOCOL(ARRAYFORMULA(IF( SPLIT(C70,"" "")=TOCOL(SPLIT(C69,"" "")),SPLIT(C70,"" "")&"" "",""""))))))"),"VICTORIO AYDE AQUINO LOARTE") -> VICTORIO AYDE AQUINO LOARTE | L70: =IF(((G70<>"")*(I70<>"")*(K70<>"")*( J70=FALSE)*( H70=""))>=1,"EVALUAR","")&IF(L71="EVALUAR","->WITH THIS","") | M70: =IF(H70="",A70,A69) -> 66 | AY70: Bienestar de mi familia
A71: =1+A70 -> 68 | B71: 1551738 | C71: VICTORIA OBREGON FLORES | D71: Madre | E71: 33 | F71: Pre test (diagnóstico) | G71: =IF(E70=E71,"misma edad","") | H71: =IF(C71=C70,"mismo nombre","") | I71: =IF(B70=B71,"mismo colegio","") | J71: =F71=F70 -> FALSE | K71: =IFERROR(__xludf.DUMMYFUNCTION("TRIM(JOIN("" "",UNIQUE(TOCOL(ARRAYFORMULA(IF( SPLIT(C71,"" "")=TOCOL(SPLIT(C70,"" "")),SPLIT(C71,"" "")&"" "",""""))))))"),"") | L71: =IF(((G71<>"")*(I71<>"")*(K71<>"")*( J71=FALSE)*( H71=""))>=1,"EVALUAR","")&IF(L72="EVALUAR","->WITH THIS","") | M71: =IF(H71="",A71,A70) -> 68 | AY71: Bueno como mamá a mí me gusta que mi hijo este bien de salud , que este bien en su salon, donde estudia y que sea un niño sano y fuerte.
A72: =1+A71 -> 69 | B72: 1551738 | C72: VICTORIA OBREGON FLORES | D72: Madre | E72: 33 | F72: Post test (cierre) | G72: =IF(E71=E72,"misma edad","") -> misma edad | H72: =IF(C72=C71,"mismo nombre","") -> mismo nombre | I72: =IF(B71=B72,"mismo colegio","") -> mismo colegio | J72: =F72=F71 -> FALSE | K72: =IFERROR(__xludf.DUMMYFUNCTION("TRIM(JOIN("" "",UNIQUE(TOCOL(ARRAYFORMULA(IF( SPLIT(C72,"" "")=TOCOL(SPLIT(C71,"" "")),SPLIT(C72,"" "")&"" "",""""))))))"),"VICTORIA OBREGON FLORES") -> VICTORIA OBREGON FLORES | L72: =IF(((G72<>"")*(I72<>"")*(K72<>"")*( J72=FALSE)*( H72=""))>=1,"EVALUAR","")&IF(L73="EVALUAR","->WITH THIS","") | M72: =IF(H72="",A72,A71) -> 68 | AY72: Caminar y cantar
A73: =1+A72 -> 70 | B73: 1645506 | C73: VICTORIA GARAY CABALLERO | D73: Madre | E73: 45 | F73: Pre test (diagnóstico) | G73: =IF(E72=E73,"misma edad","") | H73: =IF(C73=C72,"mismo nombre","") | I73: =IF(B72=B73,"mismo colegio","") | J73: =F73=F72 -> FALSE | K73: =IFERROR(__xludf.DUMMYFUNCTION("TRIM(JOIN("" "",UNIQUE(TOCOL(ARRAYFORMULA(IF( SPLIT(C73,"" "")=TOCOL(SPLIT(C72,"" "")),SPLIT(C73,"" "")&"" "",""""))))))"),"VICTORIA") -> VICTORIA | L73: =IF(((G73<>"")*(I73<>"")*(K73<>"")*( J73=FALSE)*( H73=""))>=1,"EVALUAR","")&IF(L74="EVALUAR","->WITH THIS","") | M73: =IF(H73="",A73,A72) -> 70 | AY73: Cocinar para mi hijo.
A74: =1+A73 -> 71 | B74: 1645506 | C74: VICTORIA GARAY CABALLERO | D74: Madre | E74: 45 | F74: Post test (cierre) | G74: =IF(E73=E74,"misma edad","") -> misma edad | H74: =IF(C74=C73,"mismo nombre","") -> mismo nombre | I74: =IF(B73=B74,"mismo colegio","") -> mismo colegio | J74: =F74=F73 -> FALSE | K74: =IFERROR(__xludf.DUMMYFUNCTION("TRIM(JOIN("" "",UNIQUE(TOCOL(ARRAYFORMULA(IF( SPLIT(C74,"" "")=TOCOL(SPLIT(C73,"" "")),SPLIT(C74,"" "")&"" "",""""))))))"),"VICTORIA GARAY CABALLERO") -> VICTORIA GARAY CABALLERO | L74: =IF(((G74<>"")*(I74<>"")*(K74<>"")*( J74=FALSE)*( H74=""))>=1,"EVALUAR","")&IF(L75="EVALUAR","->WITH THIS","") | M74: =IF(H74="",A74,A73) -> 70 | AY74: Cocinar y compartir con sus hijos
A75: =1+A74 -> 72 | B75: 0509711 | C75: VICTORIA DAVILA LOARTE | D75: Madre | E75: 25 | F75: Post test (cierre) | G75: =IF(E74=E75,"misma edad","") | H75: =IF(C75=C74,"mismo nombre","") | I75: =IF(B74=B75,"mismo colegio","") | J75: =F75=F74 -> TRUE | K75: =IFERROR(__xludf.DUMMYFUNCTION("TRIM(JOIN("" "",UNIQUE(TOCOL(ARRAYFORMULA(IF( SPLIT(C75,"" "")=TOCOL(SPLIT(C74,"" "")),SPLIT(C75,"" "")&"" "",""""))))))"),"VICTORIA") -> VICTORIA | L75: =IF(((G75<>"")*(I75<>"")*(K75<>"")*( J75=FALSE)*( H75=""))>=1,"EVALUAR","")&IF(L76="EVALUAR","->WITH THIS","") | M75: =IF(H75="",A75,A74) -> 72 | AY75: Cocinar, escuchar musica y salir al campo a distraerme
A76: =1+A75 -> 73 | B76: 0509711 | C76: VICTOR ADRIANO LEÓN | DELINA GUERRA VEGA | D76: Madre | E76: 34 | F76: Post test (cierre) | G76: =IF(E75=E76,"misma edad","") | H76: =IF(C76=C75,"mismo nombre","") | I76: =IF(B75=B76,"mismo colegio","") -> mismo colegio | J76: =F76=F75 -> TRUE | K76: =IFERROR(__xludf.DUMMYFUNCTION("TRIM(JOIN("" "",UNIQUE(TOCOL(ARRAYFORMULA(IF( SPLIT(C76,"" "")=TOCOL(SPLIT(C75,"" "")),SPLIT(C76,"" "")&"" "",""""))))))"),"") | L76: =IF(((G76<>"")*(I76<>"")*(K76<>"")*( J76=FALSE)*( H76=""))>=1,"EVALUAR","")&IF(L77="EVALUAR","->WITH THIS","") | M76: =IF(H76="",A76,A75) -> 73 | AY76: Cocinar, escuchar musica, lavar, salir al campo
A77: =1+A76 -> 74 | B77: 0509711 | C77: VICTOR ADRIANO LEÓN | D77: Padre | E77: 40 | F77: Pre test (diagnóstico) | G77: =IF(E76=E77,"misma edad","") | H77: =IF(C77=C76,"mismo nombre","") | I77: =IF(B76=B77,"mismo colegio","") -> mismo colegio | J77: =F77=F76 -> FALSE | K77: =IFERROR(__xludf.DUMMYFUNCTION("TRIM(JOIN("" "",UNIQUE(TOCOL(ARRAYFORMULA(IF( SPLIT(C77,"" "")=TOCOL(SPLIT(C76,"" "")),SPLIT(C77,"" "")&"" "",""""))))))"),"VICTOR ADRIANO LEÓN") -> VICTOR ADRIANO LEÓN | L77: =IF(((G77<>"")*(I77<>"")*(K77<>"")*( J77=FALSE)*( H77=""))>=1,"EVALUAR","")&IF(L78="EVALUAR","->WITH THIS","") | M77: =IF(H77="",A77,A76) -> 74 | AY77: Cocinar, trabajar
A78: =1+A77 -> 75 | B78: 0360305 | C78: VICENCIO CARBAJAL BELHIÑA | D78: Madre | E78: 38 | F78: Pre test (diagnóstico) | G78: =IF(E77=E78,"misma edad","") | H78: =IF(C78=C77,"mismo nombre","") | I78: =IF(B77=B78,"mismo colegio","") | J78: =F78=F77 -> TRUE | K78: =IFERROR(__xludf.DUMMYFUNCTION("TRIM(JOIN("" "",UNIQUE(TOCOL(ARRAYFORMULA(IF( SPLIT(C78,"" "")=TOCOL(SPLIT(C77,"" "")),SPLIT(C78,"" "")&"" "",""""))))))"),"") | L78: =IF(((G78<>"")*(I78<>"")*(K78<>"")*( J78=FALSE)*( H78=""))>=1,"EVALUAR","")&IF(L79="EVALUAR","->WITH THIS","") | M78: =IF(H78="",A78,A77) -> 75 | AY78: Comer con mis hijos, viajar
A79: =1+A78 -> 76 | B79: 0415745 | C79: VERONICA SILVIA JARA ZEVALLOS | D79: Madre | E79: 44 | F79: Pre test (diagnóstico) | G79: =IF(E78=E79,"misma edad","") | H79: =IF(C79=C78,"mismo nombre","") | I79: =IF(B78=B79,"mismo colegio","") | J79: =F79=F78 -> TRUE | K79: =IFERROR(__xludf.DUMMYFUNCTION("TRIM(JOIN("" "",UNIQUE(TOCOL(ARRAYFORMULA(IF( SPLIT(C79,"" "")=TOCOL(SPLIT(C78,"" "")),SPLIT(C79,"" "")&"" "",""""))))))"),"") | L79: =IF(((G79<>"")*(I79<>"")*(K79<>"")*( J79=FALSE)*( H79=""))>=1,"EVALUAR","")&IF(L80="EVALUAR","->WITH THIS","") | M79: =IF(H79="",A79,A78) -> 76 | AY79: Como hermana me gusta hablar con él, saber cómo esta
A80: =1+A79 -> 77 | B80: 1597566 | C80: VERAMENDI TRUJILLO ANTONIA | D80: Madre | E80: 35 | F80: Pre test (diagnóstico) | G80: =IF(E79=E80,"misma edad","") | H80: =IF(C80=C79,"mismo nombre","") | I80: =IF(B79=B80,"mismo colegio","") | J80: =F80=F79 -> TRUE | K80: =IFERROR(__xludf.DUMMYFUNCTION("TRIM(JOIN("" "",UNIQUE(TOCOL(ARRAYFORMULA(IF( SPLIT(C80,"" "")=TOCOL(SPLIT(C79,"" "")),SPLIT(C80,"" "")&"" "",""""))))))"),"") | L80: =IF(((G80<>"")*(I80<>"")*(K80<>"")*( J80=FALSE)*( H80=""))>=1,"EVALUAR","")&IF(L81="EVALUAR","->WITH THIS","") | M80: =IF(H80="",A80,A79) -> 77 | AY80: Como madre de doy cuenta cuando mi niña esta mal o estaba bien y me hace sentir bien hablando con ella y que ella esté bien
A81: =1+A80 -> 78 | B81: 1597566 | C81: VERAMENDI TRUJILLO ANTONIA | D81: Madre | E81: 35 | F81: Post test (cierre) | G81: =IF(E80=E81,"misma edad","") -> misma edad | H81: =IF(C81=C80,"mismo nombre","") -> mismo nombre | I81: =IF(B80=B81,"mismo colegio","") -> mismo colegio | J81: =F81=F80 -> FALSE | K81: =IFERROR(__xludf.DUMMYFUNCTION("TRIM(JOIN("" "",UNIQUE(TOCOL(ARRAYFORMULA(IF( SPLIT(C81,"" "")=TOCOL(SPLIT(C80,"" "")),SPLIT(C81,"" "")&"" "",""""))))))"),"VERAMENDI TRUJILLO ANTONIA") -> VERAMENDI TRUJILLO ANTONIA | L81: =IF(((G81<>"")*(I81<>"")*(K81<>"")*( J81=FALSE)*( H81=""))>=1,"EVALUAR","")&IF(L82="EVALUAR","->WITH THIS","") | M81: =IF(H81="",A81,A80) -> 77 | AY81: Como madre me ayuda el respirar un poco cada que trato de hbalar con mi hija lo que es bueno o malo
A82: =1+A81 -> 79 | B82: 1551720 | C82: VERAMENDI FRANCISCO ROXANA YAQUI | D82: Madre | E82: 26 | F82: Pre test (diagnóstico) | G82: =IF(E81=E82,"misma edad","") | H82: =IF(C82=C81,"mismo nombre","") | I82: =IF(B81=B82,"mismo colegio","") | J82: =F82=F81 -> FALSE | K82: =IFERROR(__xludf.DUMMYFUNCTION("TRIM(JOIN("" "",UNIQUE(TOCOL(ARRAYFORMULA(IF( SPLIT(C82,"" "")=TOCOL(SPLIT(C81,"" "")),SPLIT(C82,"" "")&"" "",""""))))))"),"VERAMENDI") -> VERAMENDI | L82: =IF(((G82<>"")*(I82<>"")*(K82<>"")*( J82=FALSE)*( H82=""))>=1,"EVALUAR","")&IF(L83="EVALUAR","->WITH THIS","") | M82: =IF(H82="",A82,A81) -> 79 | AY82: Como madre, para sentirme bien, me ayuda a ver a mis hijos que estén bien de salud, luego ver su educación para salir adelante en el futuro.
A83: =1+A82 -> 80 | B83: 1597608 | C83: VERAMENDI CASTRO JULIA | D83: Madre | E83: 42 | F83: Pre test (diagnóstico) | G83: =IF(E82=E83,"misma edad","") | H83: =IF(C83=C82,"mismo nombre","") | I83: =IF(B82=B83,"mismo colegio","") | J83: =F83=F82 -> TRUE | K83: =IFERROR(__xludf.DUMMYFUNCTION("TRIM(JOIN("" "",UNIQUE(TOCOL(ARRAYFORMULA(IF( SPLIT(C83,"" "")=TOCOL(SPLIT(C82,"" "")),SPLIT(C83,"" "")&"" "",""""))))))"),"VERAMENDI") -> VERAMENDI | L83: =IF(((G83<>"")*(I83<>"")*(K83<>"")*( J83=FALSE)*( H83=""))>=1,"EVALUAR","")&IF(L84="EVALUAR","->WITH THIS","") | M83: =IF(H83="",A83,A82) -> 80 | AY83: Como mamá dar los buenos valores y ser un ejemplo para la vida cotidiana.
A84: =1+A83 -> 81 | B84: 1551720 | C84: VERAMENDI CASTRO JULIA | D84: Madre | E84: 38 | F84: Post test (cierre) | G84: =IF(E83=E84,"misma edad","") | H84: =IF(C84=C83,"mismo nombre","") -> mismo nombre | I84: =IF(B83=B84,"mismo colegio","") | J84: =F84=F83 -> FALSE | K84: =IFERROR(__xludf.DUMMYFUNCTION("TRIM(JOIN("" "",UNIQUE(TOCOL(ARRAYFORMULA(IF( SPLIT(C84,"" "")=TOCOL(SPLIT(C83,"" "")),SPLIT(C84,"" "")&"" "",""""))))))"),"VERAMENDI CASTRO JULIA") -> VERAMENDI CASTRO JULIA | L84: =IF(((G84<>"")*(I84<>"")*(K84<>"")*( J84=FALSE)*( H84=""))>=1,"EVALUAR","")&IF(L85="EVALUAR","->WITH THIS","") | M84: =IF(H84="",A84,A83) -> 80 | AY84: Como mamá me ayuda a calmar a mi hija, sobrellevar lo que me hace entenderla porque es pequeña y dia a dia hablarle bien
A85: =1+A84 -> 82 | B85: 1597608 | C85: VERAMENDI CASTRO JULIA | D85: Madre | F85: Post test (cierre) | G85: =IF(E84=E85,"misma edad","") | H85: =IF(C85=C84,"mismo nombre","") -> mismo nombre | I85: =IF(B84=B85,"mismo colegio","") | J85: =F85=F84 -> TRUE | K85: =IFERROR(__xludf.DUMMYFUNCTION("TRIM(JOIN("" "",UNIQUE(TOCOL(ARRAYFORMULA(IF( SPLIT(C85,"" "")=TOCOL(SPLIT(C84,"" "")),SPLIT(C85,"" "")&"" "",""""))))))"),"VERAMENDI CASTRO JULIA") -> VERAMENDI CASTRO JULIA | L85: =IF(((G85<>"")*(I85<>"")*(K85<>"")*( J85=FALSE)*( H85=""))>=1,"EVALUAR","")&IF(L86="EVALUAR","->WITH THIS","") | M85: =IF(H85="",A85,A84) -> 81 | AY85: Como mamá me ayuda a estar bien con mis hijos, tranquila, calmada, escuchar música y apoyar a mis hijos en lo que necesita.
A86: =1+A85 -> 83 | B86: 1597608 | C86: VERAMENDI CASTRO GLORIA | D86: Madre | E86: - | F86: Pre test (diagnóstico) | G86: =IF(E85=E86,"misma edad","") | H86: =IF(C86=C85,"mismo nombre","") | I86: =IF(B85=B86,"mismo colegio","") -> mismo colegio | J86: =F86=F85 -> FALSE | K86: =IFERROR(__xludf.DUMMYFUNCTION("TRIM(JOIN("" "",UNIQUE(TOCOL(ARRAYFORMULA(IF( SPLIT(C86,"" "")=TOCOL(SPLIT(C85,"" "")),SPLIT(C86,"" "")&"" "",""""))))))"),"VERAMENDI CASTRO") -> VERAMENDI CASTRO | L86: =IF(((G86<>"")*(I86<>"")*(K86<>"")*( J86=FALSE)*( H86=""))>=1,"EVALUAR","")&IF(L87="EVALUAR","->WITH THIS","") | M86: =IF(H86="",A86,A85) -> 83 | AY86: Como mamá me ayuda a estar bien conversar sobre lo que está pasando en la familia, salir a distraerme un rato
A87: =1+A86 -> 84 | B87: 1597608 | C87: VERAMENDI CASTRO GLORIA | D87: Madre | F87: Post test (cierre) | G87: =IF(E86=E87,"misma edad","") | H87: =IF(C87=C86,"mismo nombre","") -> mismo nombre | I87: =IF(B86=B87,"mismo colegio","") -> mismo colegio | J87: =F87=F86 -> FALSE | K87: =IFERROR(__xludf.DUMMYFUNCTION("TRIM(JOIN("" "",UNIQUE(TOCOL(ARRAYFORMULA(IF( SPLIT(C87,"" "")=TOCOL(SPLIT(C86,"" "")),SPLIT(C87,"" "")&"" "",""""))))))"),"VERAMENDI CASTRO GLORIA") -> VERAMENDI CASTRO GLORIA | L87: =IF(((G87<>"")*(I87<>"")*(K87<>"")*( J87=FALSE)*( H87=""))>=1,"EVALUAR","")&IF(L88="EVALUAR","->WITH THIS","") | M87: =IF(H87="",A87,A86) -> 83 | AY87: Como mamá me ayuda a estar bien establecer comunicación con mis hijos y esposo, tomar decisiones juntos, cuando es necesario buscar apoyo.
A88: =1+A87 -> 85 | B88: 1675032 | C88: VERAMENDI BAJOMERO ESTHER | D88: Madre | F88: Post test (cierre) | G88: =IF(E87=E88,"misma edad","") -> misma edad | H88: =IF(C88=C87,"mismo nombre","") | I88: =IF(B87=B88,"mismo colegio","") | J88: =F88=F87 -> TRUE | K88: =IFERROR(__xludf.DUMMYFUNCTION("TRIM(JOIN("" "",UNIQUE(TOCOL(ARRAYFORMULA(IF( SPLIT(C88,"" "")=TOCOL(SPLIT(C87,"" "")),SPLIT(C88,"" "")&"" "",""""))))))"),"VERAMENDI") -> VERAMENDI | L88: =IF(((G88<>"")*(I88<>"")*(K88<>"")*( J88=FALSE)*( H88=""))>=1,"EVALUAR","")&IF(L89="EVALUAR","->WITH THIS","") | M88: =IF(H88="",A88,A87) -> 85 | AY88: Como mamá me ayuda conversar con mis hijos, tener confianza y ser como una amiga para ellos
A89: =1+A88 -> 86 | B89: 1043652 | C89: VENTURO SILVA, CARMEN | D89: Madre | F89: Pre test (diagnóstico) | G89: =IF(E88=E89,"misma edad","") -> misma edad | H89: =IF(C89=C88,"mismo nombre","") | I89: =IF(B88=B89,"mismo colegio","") | J89: =F89=F88 -> FALSE | K89: =IFERROR(__xludf.DUMMYFUNCTION("TRIM(JOIN("" "",UNIQUE(TOCOL(ARRAYFORMULA(IF( SPLIT(C89,"" "")=TOCOL(SPLIT(C88,"" "")),SPLIT(C89,"" "")&"" "",""""))))))"),"") | L89: =IF(((G89<>"")*(I89<>"")*(K89<>"")*( J89=FALSE)*( H89=""))>=1,"EVALUAR","")&IF(L90="EVALUAR","->WITH THIS","") | M89: =IF(H89="",A89,A88) -> 86 | AY89: Como mamá me ayudó a estar bien cuando mis hijos estan bien de salud y salir en las tardes a los juegos
A90: =1+A89 -> 87 | B90: 1043652 | C90: VENTURO SILVA, CARMEN | D90: Madre | F90: Post test (cierre) | G90: =IF(E89=E90,"misma edad","") -> misma edad | H90: =IF(C90=C89,"mismo nombre","") -> mismo nombre | I90: =IF(B89=B90,"mismo colegio","") -> mismo colegio | J90: =F90=F89 -> FALSE | K90: =IFERROR(__xludf.DUMMYFUNCTION("TRIM(JOIN("" "",UNIQUE(TOCOL(ARRAYFORMULA(IF( SPLIT(C90,"" "")=TOCOL(SPLIT(C89,"" "")),SPLIT(C90,"" "")&"" "",""""))))))"),"VENTURO SILVA, CARMEN") -> VENTURO SILVA, CARMEN | L90: =IF(((G90<>"")*(I90<>"")*(K90<>"")*( J90=FALSE)*( H90=""))>=1,"EVALUAR","")&IF(L91="EVALUAR","->WITH THIS","") | M90: =IF(H90="",A90,A89) -> 86 | AY90: Como mamá me gusta revisar las tareas con mi hijito
A91: =1+A90 -> 88 | B91: 1100635 | C91: VASQUEZ OLIVAS BEINA | D91: Madre | E91: 51 | F91: Post test (cierre) | G91: =IF(E90=E91,"misma edad","") | H91: =IF(C91=C90,"mismo nombre","") | I91: =IF(B90=B91,"mismo colegio","") | J91: =F91=F90 -> TRUE | K91: =IFERROR(__xludf.DUMMYFUNCTION("TRIM(JOIN("" "",UNIQUE(TOCOL(ARRAYFORMULA(IF( SPLIT(C91,"" "")=TOCOL(SPLIT(C90,"" "")),SPLIT(C91,"" "")&"" "",""""))))))"),"") | L91: =IF(((G91<>"")*(I91<>"")*(K91<>"")*( J91=FALSE)*( H91=""))>=1,"EVALUAR","")&IF(L92="EVALUAR","->WITH THIS","") | M91: =IF(H91="",A91,A90) -> 88 | AY91: Como mamá me gustaría ver feliz a mis hijos
A92: =1+A91 -> 89 | B92: 1100635 | C92: VASQUEZ GOMEZ DAISY | D92: Madre | E92: 30 | F92: Post test (cierre) | G92: =IF(E91=E92,"misma edad","") | H92: =IF(C92=C91,"mismo nombre","") | I92: =IF(B91=B92,"mismo colegio","") -> mismo colegio | J92: =F92=F91 -> TRUE | K92: =IFERROR(__xludf.DUMMYFUNCTION("TRIM(JOIN("" "",UNIQUE(TOCOL(ARRAYFORMULA(IF( SPLIT(C92,"" "")=TOCOL(SPLIT(C91,"" "")),SPLIT(C92,"" "")&"" "",""""))))))"),"VASQUEZ") -> VASQUEZ | L92: =IF(((G92<>"")*(I92<>"")*(K92<>"")*( J92=FALSE)*( H92=""))>=1,"EVALUAR","")&IF(L93="EVALUAR","->WITH THIS","") | M92: =IF(H92="",A92,A91) -> 89 | AY92: Como mamá me siento bien en apoyar con sus actividades a mis hijos, en sus tareas, cuando juega, es una niña encantadora
A93: =1+A92 -> 90 | B93: 1551753 | C93: VARGAS MIRANDA, JHOSMEL | D93: Padre | E93: 30 | F93: Post test (cierre) | G93: =IF(E92=E93,"misma edad","") -> misma edad | H93: =IF(C93=C92,"mismo nombre","") | I93: =IF(B92=B93,"mismo colegio","") | J93: =F93=F92 -> TRUE | K93: =IFERROR(__xludf.DUMMYFUNCTION("TRIM(JOIN("" "",UNIQUE(TOCOL(ARRAYFORMULA(IF( SPLIT(C93,"" "")=TOCOL(SPLIT(C92,"" "")),SPLIT(C93,"" "")&"" "",""""))))))"),"") | L93: =IF(((G93<>"")*(I93<>"")*(K93<>"")*( J93=FALSE)*( H93=""))>=1,"EVALUAR","")&IF(L94="EVALUAR","->WITH THIS","") | M93: =IF(H93="",A93,A92) -> 90 | AY93: Como mamá me siento feliz cuando mi hija llega a casa muy feliz saludando con un abrazo
A94: =1+A93 -> 91 | B94: 0360305 | C94: VARA MEJÍA YASMELY | D94: Madre | E94: 22 | F94: Pre test (diagnóstico) | G94: =IF(E93=E94,"misma edad","") | H94: =IF(C94=C93,"mismo nombre","") | I94: =IF(B93=B94,"mismo colegio","") | J94: =F94=F93 -> FALSE | K94: =IFERROR(__xludf.DUMMYFUNCTION("TRIM(JOIN("" "",UNIQUE(TOCOL(ARRAYFORMULA(IF( SPLIT(C94,"" "")=TOCOL(SPLIT(C93,"" "")),SPLIT(C94,"" "")&"" "",""""))))))"),"") | L94: =IF(((G94<>"")*(I94<>"")*(K94<>"")*( J94=FALSE)*( H94=""))>=1,"EVALUAR","")&IF(L95="EVALUAR","->WITH THIS","") | M94: =IF(H94="",A94,A93) -> 91 | AY94: Como mamá que mis hjos esten bien es lo que me hace sentir bien
A95: =1+A94 -> 92 | B95: 0360305 | C95: VARA MEJÍA YASMELY | D95: Madre | E95: 22 | F95: Post test (cierre) | G95: =IF(E94=E95,"misma edad","") -> misma edad | H95: =IF(C95=C94,"mismo nombre","") -> mismo nombre | I95: =IF(B94=B95,"mismo colegio","") -> mismo colegio | J95: =F95=F94 -> FALSE | K95: =IFERROR(__xludf.DUMMYFUNCTION("TRIM(JOIN("" "",UNIQUE(TOCOL(ARRAYFORMULA(IF( SPLIT(C95,"" "")=TOCOL(SPLIT(C94,"" "")),SPLIT(C95,"" "")&"" "",""""))))))"),"VARA MEJÍA YASMELY") -> VARA MEJÍA YASMELY | L95: =IF(((G95<>"")*(I95<>"")*(K95<>"")*( J95=FALSE)*( H95=""))>=1,"EVALUAR","")&IF(L96="EVALUAR","->WITH THIS","") | M95: =IF(H95="",A95,A94) -> 91 | AY95: Como mamá yo me siento bien estar con mis hijos y siempre le ayudo en todo a mis hijos aunque no tengo fuerza siempre le sonrio
A96: =1+A95 -> 93 | B96: 1551555 | C96: VALVERDE ASIS, YANINA | D96: Madre | E96: 24 | F96: Pre test (diagnóstico) | G96: =IF(E95=E96,"misma edad","") | H96: =IF(C96=C95,"mismo nombre","") | I96: =IF(B95=B96,"mismo colegio","") | J96: =F96=F95 -> FALSE | K96: =IFERROR(__xludf.DUMMYFUNCTION("TRIM(JOIN("" "",UNIQUE(TOCOL(ARRAYFORMULA(IF( SPLIT(C96,"" "")=TOCOL(SPLIT(C95,"" "")),SPLIT(C96,"" "")&"" "",""""))))))"),"") | L96: =IF(((G96<>"")*(I96<>"")*(K96<>"")*( J96=FALSE)*( H96=""))>=1,"EVALUAR","")&IF(L97="EVALUAR","->WITH THIS","") | M96: =IF(H96="",A96,A95) -> 93 | AY96: Como papá me siento feliz porque mi hija avanza en su estudio
A97: =1+A96 -> 94 | B97: 1551738 | C97: VALENTINA ROJAS LOARTE | D97: Madre | E97: 42 | F97: Pre test (diagnóstico) | G97: =IF(E96=E97,"misma edad","") | H97: =IF(C97=C96,"mismo nombre","") | I97: =IF(B96=B97,"mismo colegio","") | J97: =F97=F96 -> TRUE | K97: =IFERROR(__xludf.DUMMYFUNCTION("TRIM(JOIN("" "",UNIQUE(TOCOL(ARRAYFORMULA(IF( SPLIT(C97,"" "")=TOCOL(SPLIT(C96,"" "")),SPLIT(C97,"" "")&"" "",""""))))))"),"") | L97: =IF(((G97<>"")*(I97<>"")*(K97<>"")*( J97=FALSE)*( H97=""))>=1,"EVALUAR","")&IF(L98="EVALUAR","->WITH THIS","") | M97: =IF(H97="",A97,A96) -> 94 | AY97: Compartir con mis hijos de todo lo que uno consigue para ellos y hacer deporte con mis hijos.
A98: =1+A97 -> 95 | B98: 1551738 | C98: VALENTINA ROJAS LOARTE | D98: Madre | E98: 42 | F98: Post test (cierre) | G98: =IF(E97=E98,"misma edad","") -> misma edad | H98: =IF(C98=C97,"mismo nombre","") -> mismo nombre | I98: =IF(B97=B98,"mismo colegio","") -> mismo colegio | J98: =F98=F97 -> FALSE | K98: =IFERROR(__xludf.DUMMYFUNCTION("TRIM(JOIN("" "",UNIQUE(TOCOL(ARRAYFORMULA(IF( SPLIT(C98,"" "")=TOCOL(SPLIT(C97,"" "")),SPLIT(C98,"" "")&"" "",""""))))))"),"VALENTINA ROJAS LOARTE") -> VALENTINA ROJAS LOARTE | L98: =IF(((G98<>"")*(I98<>"")*(K98<>"")*( J98=FALSE)*( H98=""))>=1,"EVALUAR","")&IF(L99="EVALUAR","->WITH THIS","") | M98: =IF(H98="",A98,A97) -> 94 | AY98: Compartir con mis hijos y cocinar
A99: =1+A98 -> 96 | B99: 1675024 | C99: VALENTIN MELGAREJO OBREGÓN | D99: Padre | E99: 33 | F99: Pre test (diagnóstico) | G99: =IF(E98=E99,"misma edad","") | H99: =IF(C99=C98,"mismo nombre","") | I99: =IF(B98=B99,"mismo colegio","") | J99: =F99=F98 -> FALSE | K99: =IFERROR(__xludf.DUMMYFUNCTION("TRIM(JOIN("" "",UNIQUE(TOCOL(ARRAYFORMULA(IF( SPLIT(C99,"" "")=TOCOL(SPLIT(C98,"" "")),SPLIT(C99,"" "")&"" "",""""))))))"),"") | L99: =IF(((G99<>"")*(I99<>"")*(K99<>"")*( J99=FALSE)*( H99=""))>=1,"EVALUAR","")&IF(L100="EVALUAR","->WITH THIS","") | M99: =IF(H99="",A99,A98) -> 96 | AY99: Compartir tiempo en familia
A100: =1+A99 -> 97 | B100: 1675024 | C100: VALENTIN MELGAREJO OBREGÓN | D100: Padre | E100: 33 | F100: Post test (cierre) | G100: =IF(E99=E100,"misma edad","") -> misma edad | H100: =IF(C100=C99,"mismo nombre","") -> mismo nombre | I100: =IF(B99=B100,"mismo colegio","") -> mismo colegio | J100: =F100=F99 -> FALSE | K100: =IFERROR(__xludf.DUMMYFUNCTION("TRIM(JOIN("" "",UNIQUE(TOCOL(ARRAYFORMULA(IF( SPLIT(C100,"" "")=TOCOL(SPLIT(C99,"" "")),SPLIT(C100,"" "")&"" "",""""))))))"),"VALENTIN MELGAREJO OBREGÓN") -> VALENTIN MELGAREJO OBREGÓN | L100: =IF(((G100<>"")*(I100<>"")*(K100<>"")*( J100=FALSE)*( H100=""))>=1,"EVALUAR","")&IF(L101="EVALUAR","->WITH THIS","") | M100: =IF(H100="",A100,A99) -> 96 | AY100: Comunicación con la familia, estar bien, salir a caminar, tomar aire libre, escuchar música, tomar mi café y conversar.
A101: =1+A100 -> 98 | B101: 1645506 | C101: URSULA JOSIFINA REYNA MATOS | D101: Madre | E101: 23 | F101: Pre test (diagnóstico) | G101: =IF(E100=E101,"misma edad","") | H101: =IF(C101=C100,"mismo nombre","") | I101: =IF(B100=B101,"mismo colegio","") | J101: =F101=F100 -> FALSE | K101: =IFERROR(__xludf.DUMMYFUNCTION("TRIM(JOIN("" "",UNIQUE(TOCOL(ARRAYFORMULA(IF( SPLIT(C101,"" "")=TOCOL(SPLIT(C100,"" "")),SPLIT(C101,"" "")&"" "",""""))))))"),"") | L101: =IF(((G101<>"")*(I101<>"")*(K101<>"")*( J101=FALSE)*( H101=""))>=1,"EVALUAR","")&IF(L102="EVALUAR","->WITH THIS","") | M101: =IF(H101="",A101,A100) -> 98 | AY101: Comunicacion con mi familia
...

Sheet Eva. Estudiantes
B1: UGT | C1: Provincia | D1: Distrito | E1: Centro Poblado | F1: Institución educativa | G1: Nivel modular | H1: Cod modular | I1: Cod local | J1: Grado | K1: Aula/Sección | L1: Apellidos y nombres | M1: Fecha de aplicación | N1: Corte de evaluación | O1: Identifica al menos 3 emociones básicas al observar imágenes | P1: Representa gráficamente dos emociones con rasgos diferenciados | Q1: Relaciona una emoción con una experiencia personal | R1: Reconoce una emoción incómoda en sí mismo. | S1: Participa en una estrategia de autorregulación (ej. respiración) | T1: Identifica una situación en la que podría usar la estrategia | U1: Identifica correctamente la emoción de otra persona | V1: Justifica su respuesta con base en la imagen | W1: Relaciona la emoción ajena con una experiencia propia | X1: Escucha y responde a las acciones/palabras del otro | Y1: Respeta turnos o espera con paciencia | Z1: Coopera para lograr un objetivo común | AA1: Reconoce que las acciones tienen consecuencias | AB1: Propone una acción positiva o prosocial | AC1: Justifica su elección de forma comprensible | AD1: Comentarios | AE1: Facilitador/a
B2: MINA | C2: HUARI | D2: SAN MARCOS | E2: CARHUAYOC | F2: 248 | G2: Inicial - Jardín | H2: 0509711 | I2: 025227 | J2: Ini-4rto | K2: 4 años | L2: Aparicio Garay Keira Yatziry | M2: 45852 | N2: Pre test (diagnóstico) | O2: Evidencia suficiente: el niño/a lo realiza o verbaliza con claridad y de forma autónoma | P2: Evidencia parcial: el niño/a lo realiza con ayuda, duda o lo menciona sin claridad | Q2: Evidencia suficiente: el niño/a lo realiza o verbaliza con claridad y de forma autónoma | R2: Evidencia suficiente: el niño/a lo realiza o verbaliza con claridad y de forma autónoma | S2: Evidencia suficiente: el niño/a lo realiza o verbaliza con claridad y de forma autónoma | T2: Evidencia parcial: el niño/a lo realiza con ayuda, duda o lo menciona sin claridad | U2: Evidencia suficiente: el niño/a lo realiza o verbaliza con claridad y de forma autónoma | V2: Evidencia suficiente: el niño/a lo realiza o verbaliza con claridad y de forma autónoma | W2: Evidencia parcial: el niño/a lo realiza con ayuda, duda o lo menciona sin claridad | X2: Evidencia parcial: el niño/a lo realiza con ayuda, duda o lo menciona sin claridad | Y2: Evidencia parcial: el niño/a lo realiza con ayuda, duda o lo menciona sin claridad | Z2: No hay evidencia observable | AA2: Evidencia suficiente: el niño/a lo realiza o verbaliza con claridad y de forma autónoma | AB2: Evidencia parcial: el niño/a lo realiza con ayuda, duda o lo menciona sin claridad | AC2: Evidencia parcial: el niño/a lo realiza con ayuda, duda o lo menciona sin claridad | AE2: Stephany Decheco Vera
B3: MINA | C3: HUARI | D3: SAN MARCOS | E3: CARHUAYOC | F3: 248 | G3: Inicial - Jardín | H3: 0509711 | I3: 025227 | J3: Ini-4rto | K3: 4 años | L3: Carhuapoma Guerra Edward | M3: 45852 | N3: Pre test (diagnóstico) | O3: Evidencia suficiente: el niño/a lo realiza o verbaliza con claridad y de forma autónoma | P3: Evidencia suficiente: el niño/a lo realiza o verbaliza con claridad y de forma autónoma | Q3: Evidencia suficiente: el niño/a lo realiza o verbaliza con claridad y de forma autónoma | R3: Evidencia suficiente: el niño/a lo realiza o verbaliza con claridad y de forma autónoma | S3: Evidencia suficiente: el niño/a lo realiza o verbaliza con claridad y de forma autónoma | T3: Evidencia suficiente: el niño/a lo realiza o verbaliza con claridad y de forma autónoma | U3: Evidencia suficiente: el niño/a lo realiza o verbaliza con claridad y de forma autónoma | V3: Evidencia suficiente: el niño/a lo realiza o verbaliza con claridad y de forma autónoma | W3: Evidencia suficiente: el niño/a lo realiza o verbaliza con claridad y de forma autónoma | X3: Evidencia suficiente: el niño/a lo realiza o verbaliza con claridad y de forma autónoma | Y3: Evidencia parcial: el niño/a lo realiza con ayuda, duda o lo menciona sin claridad | Z3: No hay evidencia observable | AA3: Evidencia suficiente: el niño/a lo realiza o verbaliza con claridad y de forma autónoma | AB3: Evidencia suficiente: el niño/a lo realiza o verbaliza con claridad y de forma autónoma | AC3: Evidencia suficiente: el niño/a lo realiza o verbaliza con claridad y de forma autónoma | AE3: Stephany Decheco Vera
B4: MINA | C4: HUARI | D4: SAN MARCOS | E4: CARHUAYOC | F4: 248 | G4: Inicial - Jardín | H4: 0509711 | I4: 025227 | J4: Ini-4rto | K4: 4 años | L4: Culla Espinoza Heidi Zuleyka | M4: 45852 | N4: Pre test (diagnóstico) | O4: Evidencia suficiente: el niño/a lo realiza o verbaliza con claridad y de forma autónoma | P4: Evidencia suficiente: el niño/a lo realiza o verbaliza con claridad y de forma autónoma | Q4: Evidencia suficiente: el niño/a lo realiza o verbaliza con claridad y de forma autónoma | R4: Evidencia suficiente: el niño/a lo realiza o verbaliza con claridad y de forma autónoma | S4: Evidencia suficiente: el niño/a lo realiza o verbaliza con claridad y de forma autónoma | T4: No hay evidencia observable | U4: Evidencia suficiente: el niño/a lo realiza o verbaliza con claridad y de forma autónoma | V4: Evidencia parcial: el niño/a lo realiza con ayuda, duda o lo menciona sin claridad | W4: Evidencia parcial: el niño/a lo realiza con ayuda, duda o lo menciona sin claridad | X4: Evidencia suficiente: el niño/a lo realiza o verbaliza con claridad y de forma autónoma | Y4: Evidencia parcial: el niño/a lo realiza con ayuda, duda o lo menciona sin claridad | Z4: No hay evidencia observable | AA4: Evidencia suficiente: el niño/a lo realiza o verbaliza con claridad y de forma autónoma | AB4: Evidencia parcial: el niño/a lo realiza con ayuda, duda o lo menciona sin claridad | AC4: No hay evidencia observable | AE4: Stephany Decheco Vera
B5: MINA | C5: HUARI | D5: SAN MARCOS | E5: CARHUAYOC | F5: 248 | G5: Inicial - Jardín | H5: 0509711 | I5: 025227 | J5: Ini-4rto | K5: 4 años | L5: Flores Ticlo Jair Eithan | M5: 45852 | N5: Pre test (diagnóstico) | O5: Evidencia suficiente: el niño/a lo realiza o verbaliza con claridad y de forma autónoma | P5: Evidencia suficiente: el niño/a lo realiza o verbaliza con claridad y de forma autónoma | Q5: Evidencia suficiente: el niño/a lo realiza o verbaliza con claridad y de forma autónoma | R5: Evidencia suficiente: el niño/a lo realiza o verbaliza con claridad y de forma autónoma | S5: Evidencia suficiente: el niño/a lo realiza o verbaliza con claridad y de forma autónoma | T5: Evidencia suficiente: el niño/a lo realiza o verbaliza con claridad y de forma autónoma | U5: Evidencia suficiente: el niño/a lo realiza o verbaliza con claridad y de forma autónoma | V5: Evidencia suficiente: el niño/a lo realiza o verbaliza con claridad y de forma autónoma | W5: Evidencia parcial: el niño/a lo realiza con ayuda, duda o lo menciona sin claridad | X5: Evidencia suficiente: el niño/a lo realiza o verbaliza con claridad y de forma autónoma | Y5: Evidencia suficiente: el niño/a lo realiza o verbaliza con claridad y de forma autónoma | Z5: Evidencia parcial: el niño/a lo realiza con ayuda, duda o lo menciona sin claridad | AA5: Evidencia suficiente: el niño/a lo realiza o verbaliza con claridad y de forma autónoma | AB5: Evidencia suficiente: el niño/a lo realiza o verbaliza con claridad y de forma autónoma | AC5: Evidencia suficiente: el niño/a lo realiza o verbaliza con claridad y de forma autónoma | AE5: Stephany Decheco Vera
B6: MINA | C6: HUARI | D6: SAN MARCOS | E6: CARHUAYOC | F6: 248 | G6: Inicial - Jardín | H6: 0509711 | I6: 025227 | J6: Ini-4rto | K6: 4 años | L6: Garay Amado Granyelina Favela | M6: 45852 | N6: Pre test (diagnóstico) | O6: Evidencia suficiente: el niño/a lo realiza o verbaliza con claridad y de forma autónoma | P6: Evidencia suficiente: el niño/a lo realiza o verbaliza con claridad y de forma autónoma | Q6: Evidencia suficiente: el niño/a lo realiza o verbaliza con claridad y de forma autónoma | R6: Evidencia suficiente: el niño/a lo realiza o verbaliza con claridad y de forma autónoma | S6: Evidencia suficiente: el niño/a lo realiza o verbaliza con claridad y de forma autónoma | T6: Evidencia suficiente: el niño/a lo realiza o verbaliza con claridad y de forma autónoma | U6: Evidencia suficiente: el niño/a lo realiza o verbaliza con claridad y de forma autónoma | V6: Evidencia suficiente: el niño/a lo realiza o verbaliza con claridad y de forma autónoma | W6: No hay evidencia observable | X6: Evidencia parcial: el niño/a lo realiza con ayuda, duda o lo menciona sin claridad | Y6: Evidencia suficiente: el niño/a lo realiza o verbaliza con claridad y de forma autónoma | Z6: Evidencia parcial: el niño/a lo realiza con ayuda, duda o lo menciona sin claridad | AA6: Evidencia suficiente: el niño/a lo realiza o verbaliza con claridad y de forma autónoma | AB6: Evidencia suficiente: el niño/a lo realiza o verbaliza con claridad y de forma autónoma | AC6: Evidencia parcial: el niño/a lo realiza con ayuda, duda o lo menciona sin claridad | AE6: Stephany Decheco Vera
B7: MINA | C7: HUARI | D7: SAN MARCOS | E7: CARHUAYOC | F7: 248 | G7: Inicial - Jardín | H7: 0509711 | I7: 025227 | J7: Ini-4rto | K7: 4 años | L7: Guerra Acevedo Sterling Yemil | M7: 45852 | N7: Pre test (diagnóstico) | O7: Evidencia suficiente: el niño/a lo realiza o verbaliza con claridad y de forma autónoma | P7: Evidencia suficiente: el niño/a lo realiza o verbaliza con claridad y de forma autónoma | Q7: Evidencia suficiente: el niño/a lo realiza o verbaliza con claridad y de forma autónoma | R7: Evidencia suficiente: el niño/a lo realiza o verbaliza con claridad y de forma autónoma | S7: Evidencia suficiente: el niño/a lo realiza o verbaliza con claridad y de forma autónoma | T7: Evidencia suficiente: el niño/a lo realiza o verbaliza con claridad y de forma autónoma | U7: Evidencia suficiente: el niño/a lo realiza o verbaliza con claridad y de forma autónoma | V7: Evidencia suficiente: el niño/a lo realiza o verbaliza con claridad y de forma autónoma | W7: Evidencia suficiente: el niño/a lo realiza o verbaliza con claridad y de forma autónoma | X7: Evidencia suficiente: el niño/a lo realiza o verbaliza con claridad y de forma autónoma | Y7: Evidencia suficiente: el niño/a lo realiza o verbaliza con claridad y de forma autónoma | Z7: Evidencia parcial: el niño/a lo realiza con ayuda, duda o lo menciona sin claridad | AA7: Evidencia suficiente: el niño/a lo realiza o verbaliza con claridad y de forma autónoma | AB7: Evidencia suficiente: el niño/a lo realiza o verbaliza con claridad y de forma autónoma | AC7: Evidencia suficiente: el niño/a lo realiza o verbaliza con claridad y de forma autónoma | AE7: Stephany Decheco Vera
B8: MINA | C8: HUARI | D8: SAN MARCOS | E8: CARHUAYOC | F8: 248 | G8: Inicial - Jardín | H8: 0509711 | I8: 025227 | J8: Ini-4rto | K8: 4 años | L8: Guerra Enrique Sebastián Liam | M8: 45852 | N8: Pre test (diagnóstico) | O8: Evidencia suficiente: el niño/a lo realiza o verbaliza con claridad y de forma autónoma | P8: Evidencia parcial: el niño/a lo realiza con ayuda, duda o lo menciona sin claridad | Q8: Evidencia parcial: el niño/a lo realiza con ayuda, duda o lo menciona sin claridad | R8: Evidencia suficiente: el niño/a lo realiza o verbaliza con claridad y de forma autónoma | S8: Evidencia suficiente: el niño/a lo realiza o verbaliza con claridad y de forma autónoma | T8: Evidencia parcial: el niño/a lo realiza con ayuda, duda o lo menciona sin claridad | U8: Evidencia suficiente: el niño/a lo realiza o verbaliza con claridad y de forma autónoma | V8: Evidencia suficiente: el niño/a lo realiza o verbaliza con claridad y de forma autónoma | W8: Evidencia parcial: el niño/a lo realiza con ayuda, duda o lo menciona sin claridad | X8: Evidencia suficiente: el niño/a lo realiza o verbaliza con claridad y de forma autónoma | Y8: Evidencia suficiente: el niño/a lo realiza o verbaliza con claridad y de forma autónoma | Z8: Evidencia parcial: el niño/a lo realiza con ayuda, duda o lo menciona sin claridad | AA8: Evidencia suficiente: el niño/a lo realiza o verbaliza con claridad y de forma autónoma | AB8: Evidencia suficiente: el niño/a lo realiza o verbaliza con claridad y de forma autónoma | AC8: No hay evidencia observable | AE8: Stephany Decheco Vera
B9: MINA | C9: HUARI | D9: SAN MARCOS | E9: CARHUAYOC | F9: 248 | G9: Inicial - Jardín | H9: 0509711 | I9: 025227 | J9: Ini-4rto | K9: 4 años | L9: Huanca Valle Sahmir Said | M9: 45852 | N9: Pre test (diagnóstico) | O9: Evidencia suficiente: el niño/a lo realiza o verbaliza con claridad y de forma autónoma | P9: Evidencia suficiente: el niño/a lo realiza o verbaliza con claridad y de forma autónoma | Q9: Evidencia suficiente: el niño/a lo realiza o verbaliza con claridad y de forma autónoma | R9: Evidencia suficiente: el niño/a lo realiza o verbaliza con claridad y de forma autónoma | S9: Evidencia suficiente: el niño/a lo realiza o verbaliza con claridad y de forma autónoma | T9: Evidencia parcial: el niño/a lo realiza con ayuda, duda o lo menciona sin claridad | U9: Evidencia suficiente: el niño/a lo realiza o verbaliza con claridad y de forma autónoma | V9: Evidencia suficiente: el niño/a lo realiza o verbaliza con claridad y de forma autónoma | W9: Evidencia parcial: el niño/a lo realiza con ayuda, duda o lo menciona sin claridad | X9: Evidencia suficiente: el niño/a lo realiza o verbaliza con claridad y de forma autónoma | Y9: Evidencia parcial: el niño/a lo realiza con ayuda, duda o lo menciona sin claridad | Z9: Evidencia parcial: el niño/a lo realiza con ayuda, duda o lo menciona sin claridad | AA9: Evidencia suficiente: el niño/a lo realiza o verbaliza con claridad y de forma autónoma | AB9: Evidencia suficiente: el niño/a lo realiza o verbaliza con claridad y de forma autónoma | AC9: Evidencia parcial: el niño/a lo realiza con ayuda, duda o lo menciona sin claridad | AE9: Stephany Decheco Vera
B10: MINA | C10: HUARI | D10: SAN MARCOS | E10: CARHUAYOC | F10: 248 | G10: Inicial - Jardín | H10: 0509711 | I10: 025227 | J10: Ini-4rto | K10: 4 años | L10: Mendoza Mallqui Juan David | M10: 45852 | N10: Pre test (diagnóstico) | O10: Evidencia suficiente: el niño/a lo realiza o verbaliza con claridad y de forma autónoma | P10: Evidencia suficiente: el niño/a lo realiza o verbaliza con claridad y de forma autónoma | Q10: Evidencia suficiente: el niño/a lo realiza o verbaliza con claridad y de forma autónoma | R10: Evidencia suficiente: el niño/a lo realiza o verbaliza con claridad y de forma autónoma | S10: Evidencia suficiente: el niño/a lo realiza o verbaliza con claridad y de forma autónoma | T10: Evidencia suficiente: el niño/a lo realiza o verbaliza con claridad y de forma autónoma | U10: Evidencia suficiente: el niño/a lo realiza o verbaliza con claridad y de forma autónoma | V10: Evidencia suficiente: el niño/a lo realiza o verbaliza con claridad y de forma autónoma | W10: No hay evidencia observable | X10: Evidencia suficiente: el niño/a lo realiza o verbaliza con claridad y de forma autónoma | Y10: Evidencia parcial: el niño/a lo realiza con ayuda, duda o lo menciona sin claridad | Z10: Evidencia parcial: el niño/a lo realiza con ayuda, duda o lo menciona sin claridad | AA10: Evidencia suficiente: el niño/a lo realiza o verbaliza con claridad y de forma autónoma | AB10: Evidencia suficiente: el niño/a lo realiza o verbaliza con claridad y de forma autónoma | AC10: Evidencia parcial: el niño/a lo realiza con ayuda, duda o lo menciona sin claridad | AE10: Stephany Decheco Vera
B11: MINA | C11: HUARI | D11: SAN MARCOS | E11: CARHUAYOC | F11: 248 | G11: Inicial - Jardín | H11: 0509711 | I11: 025227 | J11: Ini-4rto | K11: 4 años | L11: Obregon Guerra Yareli Corina | M11: 45852 | N11: Pre test (diagnóstico) | O11: Evidencia suficiente: el niño/a lo realiza o verbaliza con claridad y de forma autónoma | P11: Evidencia suficiente: el niño/a lo realiza o verbaliza con claridad y de forma autónoma | Q11: Evidencia suficiente: el niño/a lo realiza o verbaliza con claridad y de forma autónoma | R11: Evidencia parcial: el niño/a lo realiza con ayuda, duda o lo menciona sin claridad | S11: Evidencia suficiente: el niño/a lo realiza o verbaliza con claridad y de forma autónoma | T11: Evidencia suficiente: el niño/a lo realiza o verbaliza con claridad y de forma autónoma | U11: Evidencia suficiente: el niño/a lo realiza o verbaliza con claridad y de forma autónoma | V11: Evidencia suficiente: el niño/a lo realiza o verbaliza con claridad y de forma autónoma | W11: Evidencia suficiente: el niño/a lo realiza o verbaliza con claridad y de forma autónoma | X11: Evidencia parcial: el niño/a lo realiza con ayuda, duda o lo menciona sin claridad | Y11: Evidencia parcial: el niño/a lo realiza con ayuda, duda o lo menciona sin claridad | Z11: Evidencia parcial: el niño/a lo realiza con ayuda, duda o lo menciona sin claridad | AA11: Evidencia suficiente: el niño/a lo realiza o verbaliza con claridad y de forma autónoma | AB11: Evidencia parcial: el niño/a lo realiza con ayuda, duda o lo menciona sin claridad | AC11: Evidencia parcial: el niño/a lo realiza con ayuda, duda o lo menciona sin claridad | AE11: Stephany Decheco Vera
B12: MINA | C12: HUARI | D12: SAN MARCOS | E12: CARHUAYOC | F12: 248 | G12: Inicial - Jardín | H12: 0509711 | I12: 025227 | J12: Ini-4rto | K12: 4 años | L12: Osorio Lopez Victor Marino | M12: 45852 | N12: Pre test (diagnóstico) | O12: Evidencia suficiente: el niño/a lo realiza o verbaliza con claridad y de forma autónoma | P12: Evidencia parcial: el niño/a lo realiza con ayuda, duda o lo menciona sin claridad | Q12: No hay evidencia observable | R12: Evidencia parcial: el niño/a lo realiza con ayuda, duda o lo menciona sin claridad | S12: Evidencia parcial: el niño/a lo realiza con ayuda, duda o lo menciona sin claridad | T12: No hay evidencia observable | U12: No hay evidencia observable | V12: No hay evidencia observable | W12: No hay evidencia observable | X12: Evidencia suficiente: el niño/a lo realiza o verbaliza con claridad y de forma autónoma | Y12: Evidencia parcial: el niño/a lo realiza con ayuda, duda o lo menciona sin claridad | Z12: Evidencia parcial: el niño/a lo realiza con ayuda, duda o lo menciona sin claridad | AA12: No hay evidencia observable | AB12: No hay evidencia observable | AC12: No hay evidencia observable | AE12: Stephany Decheco Vera
B13: MINA | C13: HUARI | D13: SAN MARCOS | E13: CARHUAYOC | F13: 248 | G13: Inicial - Jardín | H13: 0509711 | I13: 025227 | J13: Ini-4rto | K13: 4 años | L13: Ramirez Nonlaya Thais Kahori | M13: 45852 | N13: Pre test (diagnóstico) | O13: Evidencia suficiente: el niño/a lo realiza o verbaliza con claridad y de forma autónoma | P13: Evidencia suficiente: el niño/a lo realiza o verbaliza con claridad y de forma autónoma | Q13: Evidencia suficiente: el niño/a lo realiza o verbaliza con claridad y de forma autónoma | R13: Evidencia suficiente: el niño/a lo realiza o verbaliza con claridad y de forma autónoma | S13: Evidencia parcial: el niño/a lo realiza con ayuda, duda o lo menciona sin claridad | T13: Evidencia parcial: el niño/a lo realiza con ayuda, duda o lo menciona sin claridad | U13: Evidencia suficiente: el niño/a lo realiza o verbaliza con claridad y de forma autónoma | V13: Evidencia suficiente: el niño/a lo realiza o verbaliza con claridad y de forma autónoma | W13: Evidencia parcial: el niño/a lo realiza con ayuda, duda o lo menciona sin claridad | X13: Evidencia parcial: el niño/a lo realiza con ayuda, duda o lo menciona sin claridad | Y13: Evidencia parcial: el niño/a lo realiza con ayuda, duda o lo menciona sin claridad | Z13: Evidencia parcial: el niño/a lo realiza con ayuda, duda o lo menciona sin claridad | AA13: Evidencia suficiente: el niño/a lo realiza o verbaliza con claridad y de forma autónoma | AB13: Evidencia parcial: el niño/a lo realiza con ayuda, duda o lo menciona sin claridad | AC13: Evidencia parcial: el niño/a lo realiza con ayuda, duda o lo menciona sin claridad | AE13: Stephany Decheco Vera
